Workbook

Sheet Template
A1: Columns | B1: Status | C1: Error Message | D1: Action | E1: ProjectNumber | F1: ProjectName | H1: ProjectStatusCode | I1: LegalEntityName | K1: OwningOrganizationName | M1: SourceTemplateName | O1: AllowCapitalizedInterestFlag | P1: AssetAllocationMethodCode | Q1: BurdenScheduleName | R1: BurdenScheduleFixedDate | S1: CapitalEventProcessingMethodCode | T1: CIntRateSchName | U1: CIntStopDate | V1: ProjectCurrencyCode | W1: CurrencyConvDate | X1: CurrencyConvRateType | Y1: CurrencyConvDateTypeCode | Z1: IncludeNotesInKPINotificationsFlag | AA1: KPINotificationEnabledFlag | AB1: PlanningProjectFlag | AC1: AllowCrossChargeFlag | AD1: TaskName | AE1: ExternalTaskId | AF1: ExternalParentTaskId | AG1: ElementType | AH1: ExpenseResourceName | AI1: LaborResourceName | AJ1: LaborResourceEmail | AK1: LaborPrimaryResource | AL1: RuleNumber | AM1: Billable | AN1: Chargeable | AO1: ExternalPredecessorTaskId | AP1: ExternalTaskId | AQ1: Lag | AR1: DependencyType | AS1: PersonEmail | AT1: ProjectRole | AU1: StartDate | AV1: ClassCategory | AW1: ClassCode | AX1: CodePercentage | AY1: OpportunityNumber | AZ1: OpportunityName | BA1: OpportunityAmount | BB1: OpportunityCustomerName | BC1: OpportunityCustomerNumber | BD1: OpportunityStatus | BE1: OpportunityWinConfPercent | BF1: PartyName | BG1: PartyNumber | BH1: BusinessUnitName | BI1: CategoryName | BJ1: DatatypeCode | BK1: FileContents | BL1: Title | BM1: FileName | BN1: ProjectEndDate | BO1: ProjectStartDate | BP1: crmNumber | BQ1: supplierPaymentProcess | BR1: supplierPaymentProcess_Display | BS1: domain | BT1: marketSegment | BU1: domain_Display | BV1: marketSegment_Display | BW1: specificities | BX1: specificities_Display | BY1: fundingSource | BZ1: fundingSource_Display | CA1: subFundingSource | CB1: subFundingSource_Display | CC1: procedures | CD1: procedures_Display | CE1: countryDestinationView | CF1: stateOrProvince | CG1: TaskFinishDate | CH1: TaskNumber | CI1: TaskStartDate | CJ1: ObjectType | CK1: ElementType
A2: Status | B2: Technical | C2: Technical | D2: Action | E2: Header | F2: Header | H2: Header | I2: Header | K2: Header | M2: Header | O2: Header | P2: Header | Q2: Header | R2: Header | S2: Header | T2: Header | U2: Header | V2: Header | W2: Header | X2: Header | Y2: Header | Z2: Header | AA2: Header | AB2: Header | AC2: Header | AD2: Tasks | AE2: Tasks | AF2: Tasks | AG2: Tasks | AH2: ExpenseResourceAssignments | AI2: LaborResourceAssignments | AJ2: LaborResourceAssignments | AK2: LaborResourceAssignments | AL2: TaskTransactionControls | AM2: TaskTransactionControls | AN2: TaskTransactionControls | AO2: TaskDependencies | AP2: TaskDependencies | AQ2: TaskDependencies | AR2: TaskDependencies | AS2: ProjectTeamMembers | AT2: ProjectTeamMembers | AU2: ProjectTeamMembers | AV2: ProjectClassifications | AW2: ProjectClassifications | AX2: ProjectClassifications | AY2: ProjectOpportunities | AZ2: ProjectOpportunities | BA2: ProjectOpportunities | BB2: ProjectOpportunities | BC2: ProjectOpportunities | BD2: ProjectOpportunities | BE2: ProjectOpportunities | BF2: ProjectCustomers | BG2: ProjectCustomers | BH2: ProviderBusinessUnits | BI2: Attachments | BJ2: Attachments | BK2: Attachments | BL2: Attachments | BM2: Attachments | BN2: Header | BO2: Header | BP2: Header | BQ2: Header | BR2: Header | BS2: Header | BT2: Header | BU2: Header | BV2: Header | BW2: Header | BX2: Header | BY2: Header | BZ2: Header | CA2: Header | CB2: Header | CC2: Header | CD2: Header | CE2: Header | CF2: Header | CG2: Tasks | CH2: Tasks | CI2: Tasks | CJ2: Tasks | CK2: Tasks
A3: Type | B3: Standard | C3: Standard | D3: Standard | E3: Standard | F3: Standard | H3: Standard | I3: Standard | K3: Standard | M3: Standard | O3: Standard | P3: Standard | Q3: Standard | R3: Standard | S3: Standard | T3: Standard | U3: Standard | V3: Standard | W3: Standard | X3: Standard | Y3: Standard | Z3: Standard | AA3: Standard | AB3: Standard | AC3: Standard | AD3: Standard | AE3: Standard | AF3: Standard | AG3: Standard | AH3: Standard | AI3: Standard | AJ3: Standard | AK3: Standard | AL3: Standard | AM3: Standard | AN3: Standard | AO3: Standard | AP3: Standard | AQ3: Standard | AR3: Standard | AS3: Standard | AT3: Standard | AU3: Standard | AV3: Standard | AW3: Standard | AX3: Standard | AY3: Standard | AZ3: Standard | BA3: Standard | BB3: Standard | BC3: Standard | BD3: Standard | BE3: Standard | BF3: Standard | BG3: Standard | BH3: Standard | BI3: Standard | BJ3: Standard | BK3: Standard | BL3: Standard | BM3: Standard | BN3: Standard | BO3: Standard | BP3: ProjectDFF | BQ3: ProjectDFF | BR3: ProjectDFF | BS3: ProjectDFF | BT3: ProjectDFF | BU3: ProjectDFF | BV3: ProjectDFF | BW3: ProjectDFF | BX3: ProjectDFF | BY3: ProjectDFF | BZ3: ProjectDFF | CA3: ProjectDFF | CB3: ProjectDFF | CC3: ProjectDFF | CD3: ProjectDFF | CE3: ProjectDFF | CF3: ProjectDFF | CG3: Standard | CH3: Standard | CI3: Standard | CJ3: TasksDFF | CK3: TasksDFF
A4: Custom Labels | B4: Status | C4: Error Message | D4: Action | E4: Project Number | F4: Project Name | G4: ProjectName to migrate | H4: Project Status Code | I4: Legal Entity Name | J4: Legal Entity Name to migrate | K4: Owning Organization Name | L4: Owning Organization Name to migrate | M4: Source Template Name | N4: SourceTemplateName to migrate | O4: Allow Capitalized Interest Flag | P4: Asset Allocation Method Code | Q4: Burden Schedule Name | R4: Burden Schedule Fixed Date | S4: Capital Event Processing Method Code | T4: CIntRateSchName | U4: CIntStopDate | V4: Project Currency Code | W4: Currency Conv Date | X4: Currency Conv Rate Type | Y4: Currency Conv Date Type Code | Z4: Include Notes In KPI Notifications Flag | AA4: KPI Notification Enabled Flag | AB4: Planning Project lag | AC4: Allow cross-charge transactions from other business units | AD4: Task Name | AE4: External Task Id | AF4: External Parent Task Id | AG4: Element Type | AH4: Expense Resource Name | AI4: Labor Resource Name | AJ4: Labor Resource Email | AK4: Labor Primary Resource | AL4: Rule Number | AM4: Billable | AN4: Chargeable | AO4: External Predecessor Task Id | AP4: External Task Id | AQ4: Lag | AR4: Dependency Type | AS4: Person Email | AT4: Project Role | AU4: Start Date | AV4: Class Category | AW4: Class Code | AX4: Code Percentage | AY4: Opportunity Number | AZ4: Opportunity Name | BA4: Opportunity Amount | BB4: Opportunity Customer Name | BC4: Opportunity Customer Number | BD4: Opportunity Status | BE4: Opportunity Win Conf Percent | BF4: Party Name | BG4: Party Number | BH4: BusinessUnitName | BI4: Category Name | BJ4: Data type Code | BK4: File Contents | BL4: Title | BM4: File Name | BN4: Project Finish Date | BO4: Project Start Date | CG4: Task Finish Date | CH4: Task Number | CI4: Task Start Date
B5: OK | D5: CREATE | E5: BIL-1007342 | F5: TESTUK1 | G5: ETS-BIL-1007342-TESTUK1 | H5: DRAFT | I5: EGIS UK - CONSULTING AND ENGINEERING LIMITED | J5: =_xlfn.XLOOKUP(I5,LE!A:A,LE!F:F,,1) -> 0 | K5: SL-Nuclear SL-CC-12-NTAI-21-Nuclear Technical Assistance-BU-GB03958GB_EGIS UK | L5: =_xlfn.XLOOKUP(K5,'ORG name (PPM)'!A:A,'ORG name (PPM)'!G:G,,1) -> 0 | M5: EGIS UK - CONSULTING AND ENGINEERING LIMITED Billable | N5: =_xlfn.XLOOKUP(M5,'source template'!A:A,'source template'!I:I,,1) -> 0 | V5: GBP | X5: Corporate | Y5: T | Z5: FALSE | AA5: FALSE | AB5: TRUE | AD5: Tender Costs | AE5: P01 | AG5: FINANCIAL | BN5: 47848 | BO5: 44927 | BP5: ZZZZZ | BQ5: STD | BR5: Standard | CG5: 47848 | CH5: P01 | CI5: 44927 | CJ5: PJF_TASKS | CK5: FINANCIAL
B6: OK | D6: CREATE | E6: BIL-1007342 | F6: TESTUK1 | G6: ETS-BIL-1007342-TESTUK1 | H6: DRAFT | I6: EGIS UK - CONSULTING AND ENGINEERING LIMITED | J6: =_xlfn.XLOOKUP(I6,LE!A:A,LE!F:F,,1) -> 0 | K6: SL-Nuclear SL-CC-12-NTAI-21-Nuclear Technical Assistance-BU-GB03958GB_EGIS UK | L6: =_xlfn.XLOOKUP(K6,'ORG name (PPM)'!A:A,'ORG name (PPM)'!G:G,,1) -> 0 | M6: EGIS UK - CONSULTING AND ENGINEERING LIMITED Billable | N6: =_xlfn.XLOOKUP(M6,'source template'!A:A,'source template'!I:I,,1) -> 0 | V6: GBP | X6: Corporate | Y6: T | Z6: FALSE | AA6: FALSE | AB6: TRUE | AD6: Budget | AE6: P02 | AG6: FINANCIAL | BN6: 47848 | BO6: 44927 | BP6: ZZZZZ | BQ6: STD | BR6: Standard | CG6: 47848 | CH6: P02 | CI6: 44927 | CJ6: PJF_TASKS | CK6: FINANCIAL
B7: OK | D7: CREATE | E7: BIL-1007342 | F7: TESTUK1 | G7: ETS-BIL-1007342-TESTUK1 | H7: DRAFT | I7: EGIS UK - CONSULTING AND ENGINEERING LIMITED | J7: =_xlfn.XLOOKUP(I7,LE!A:A,LE!F:F,,1) -> 0 | K7: SL-Nuclear SL-CC-12-NTAI-21-Nuclear Technical Assistance-BU-GB03958GB_EGIS UK | L7: =_xlfn.XLOOKUP(K7,'ORG name (PPM)'!A:A,'ORG name (PPM)'!G:G,,1) -> 0 | M7: EGIS UK - CONSULTING AND ENGINEERING LIMITED Billable | N7: =_xlfn.XLOOKUP(M7,'source template'!A:A,'source template'!I:I,,1) -> 0 | V7: GBP | X7: Corporate | Y7: T | Z7: FALSE | AA7: FALSE | AB7: TRUE | AD7: Non charegable to client | AE7: P03 | AG7: FINANCIAL | BN7: 47848 | BO7: 44927 | BP7: ZZZZZ | BQ7: STD | BR7: Standard | CG7: 47848 | CH7: P03 | CI7: 44927 | CJ7: PJF_TASKS | CK7: FINANCIAL
B8: OK | D8: CREATE | E8: BIL-1007342 | F8: TESTUK1 | G8: ETS-BIL-1007342-TESTUK1 | H8: DRAFT | I8: EGIS UK - CONSULTING AND ENGINEERING LIMITED | J8: =_xlfn.XLOOKUP(I8,LE!A:A,LE!F:F,,1) -> 0 | K8: SL-Nuclear SL-CC-12-NTAI-21-Nuclear Technical Assistance-BU-GB03958GB_EGIS UK | L8: =_xlfn.XLOOKUP(K8,'ORG name (PPM)'!A:A,'ORG name (PPM)'!G:G,,1) -> 0 | M8: EGIS UK - CONSULTING AND ENGINEERING LIMITED Billable | N8: =_xlfn.XLOOKUP(M8,'source template'!A:A,'source template'!I:I,,1) -> 0 | V8: GBP | X8: Corporate | Y8: T | Z8: FALSE | AA8: FALSE | AB8: TRUE | AD8: 425770 - Egis Structures and Environment - CM | AE8: P04 | AG8: FINANCIAL | BN8: 47848 | BO8: 44927 | BP8: ZZZZZ | BQ8: STD | BR8: Standard | CG8: 47848 | CH8: P04 | CI8: 44927 | CJ8: PJF_TASKS | CK8: FINANCIAL
B9: OK | D9: CREATE | E9: BIL-1007342 | F9: TESTUK1 | G9: ETS-BIL-1007342-TESTUK1 | H9: DRAFT | I9: EGIS UK - CONSULTING AND ENGINEERING LIMITED | J9: =_xlfn.XLOOKUP(I9,LE!A:A,LE!F:F,,1) -> 0 | K9: SL-Nuclear SL-CC-12-NTAI-21-Nuclear Technical Assistance-BU-GB03958GB_EGIS UK | L9: =_xlfn.XLOOKUP(K9,'ORG name (PPM)'!A:A,'ORG name (PPM)'!G:G,,1) -> 0 | M9: EGIS UK - CONSULTING AND ENGINEERING LIMITED Billable | N9: =_xlfn.XLOOKUP(M9,'source template'!A:A,'source template'!I:I,,1) -> 0 | V9: GBP | X9: Corporate | Y9: T | Z9: FALSE | AA9: FALSE | AB9: TRUE | AD9: P05 - Phase 05 | AE9: P05 | AG9: FINANCIAL | BN9: 47848 | BO9: 44927 | BP9: ZZZZZ | BQ9: STD | BR9: Standard | CG9: 47848 | CH9: P05 | CI9: 44927 | CJ9: PJF_TASKS | CK9: FINANCIAL
E10: FR03319FR-4896 | F10: 30 Logements Siguy [3319_4896] | G10: ="TESTME"&"-"&E10&"-"&F10 -> TESTME-FR03319FR-4896-30 Logements Siguy [3319_4896] | H10: ACTIVE | I10: EGIS BATIMENTS ANTILLES GUYANE | J10: =_xlfn.XLOOKUP(I10,LE!A:A,LE!F:F,,1) -> EGIS BATIMENTS ILE DE FRANCE | K10: SL-Buildings-CC-12-IDMI-01-Ile de France-BU-FR03305FR_EGIS BAT IDF | L10: SL-Buildings-CC-12-IDMI-01-Ile de France-BU-FR03305FR_EGIS BAT IDF | M10: EGIS BATIMENTS ILE DE FRANCE Billable E&SC Small Project | N10: EGIS BATIMENTS ILE DE FRANCE Billable E&SC Small Project | V10: EUR | X10: Corporate | Y10: T | Z10: FALSE | AA10: FALSE | AB10: TRUE | AC10: TRUE | AD10: O | AE10: P01 | AG10: FINANCIAL | BN10: 46203 | BO10: 41275 | BP10: 319-000008 | BQ10: STD | BR10: Standard | CG10: 45657 | CH10: P01 | CI10: 41275 | CJ10: PJF_TASKS | CK10: FINANCIAL
B11: OK | D11: CREATE | E11: BIL-1007990 | F11: TESTME-FR03319FR-BAPD25501-GUY Collège ECO-Q RM [3319_BAPD25501] | G11: TESTME-FR03319FR-BAPD25501-GUY Collège ECO-Q RM [3319_BAPD25501] | H11: DRAFT | I11: EGIS BATIMENTS ILE DE FRANCE | J11: =_xlfn.XLOOKUP(I11,LE!A:A,LE!F:F,,1) -> 0 | K11: SL-Buildings-CC-12-IDMI-01-Ile de France-BU-FR03305FR_EGIS BAT IDF | L11: SL-Buildings-CC-12-IDMI-01-Ile de France-BU-FR03305FR_EGIS BAT IDF | M11: EGIS BATIMENTS ILE DE FRANCE Billable E&SC Small Project | N11: EGIS BATIMENTS ILE DE FRANCE Billable E&SC Small Project | V11: EUR | X11: Corporate | Y11: T | Z11: FALSE | AA11: FALSE | AB11: TRUE | AC11: TRUE | AD11: O - Offre | AE11: P01 | AG11: FINANCIAL | BN11: 46387 | BO11: 43679 | BP11: BAPD255 | BQ11: STD | BR11: Standard | CG11: 45657 | CH11: P01 | CI11: 43679 | CJ11: PJF_TASKS | CK11: FINANCIAL
B12: OK | D12: CREATE | E12: BIL-1007990 | F12: TESTME-FR03319FR-BAPD25501-GUY Collège ECO-Q RM [3319_BAPD25501] | G12: TESTME-FR03319FR-BAPD25501-GUY Collège ECO-Q RM [3319_BAPD25501] | H12: DRAFT | I12: EGIS BATIMENTS ILE DE FRANCE | J12: =_xlfn.XLOOKUP(I12,LE!A:A,LE!F:F,,1) -> 0 | K12: SL-Buildings-CC-12-IDMI-01-Ile de France-BU-FR03305FR_EGIS BAT IDF | L12: SL-Buildings-CC-12-IDMI-01-Ile de France-BU-FR03305FR_EGIS BAT IDF | M12: EGIS BATIMENTS ILE DE FRANCE Billable E&SC Small Project | N12: EGIS BATIMENTS ILE DE FRANCE Billable E&SC Small Project | V12: EUR | X12: Corporate | Y12: T | Z12: FALSE | AA12: FALSE | AB12: TRUE | AC12: TRUE | AD12: ESQ APS PC APD Loi EAU | AE12: P02 | AG12: FINANCIAL | BN12: 46387 | BO12: 43679 | BP12: BAPD255 | BQ12: STD | BR12: Standard | CG12: 46162 | CH12: P02 | CI12: 43679 | CJ12: PJF_TASKS | CK12: FINANCIAL
B13: OK | D13: CREATE | E13: BIL-1007990 | F13: TESTME-FR03319FR-BAPD25501-GUY Collège ECO-Q RM [3319_BAPD25501] | G13: TESTME-FR03319FR-BAPD25501-GUY Collège ECO-Q RM [3319_BAPD25501] | H13: DRAFT | I13: EGIS BATIMENTS ILE DE FRANCE | J13: =_xlfn.XLOOKUP(I13,LE!A:A,LE!F:F,,1) -> 0 | K13: SL-Buildings-CC-12-IDMI-01-Ile de France-BU-FR03305FR_EGIS BAT IDF | L13: SL-Buildings-CC-12-IDMI-01-Ile de France-BU-FR03305FR_EGIS BAT IDF | M13: EGIS BATIMENTS ILE DE FRANCE Billable E&SC Small Project | N13: EGIS BATIMENTS ILE DE FRANCE Billable E&SC Small Project | V13: EUR | X13: Corporate | Y13: T | Z13: FALSE | AA13: FALSE | AB13: TRUE | AC13: TRUE | AD13: PRO | AE13: P03 | AG13: FINANCIAL | BN13: 46387 | BO13: 43679 | BP13: BAPD255 | BQ13: STD | BR13: Standard | CG13: 46162 | CH13: P03 | CI13: 43679 | CJ13: PJF_TASKS | CK13: FINANCIAL
B14: OK | D14: CREATE | E14: BIL-1007990 | F14: TESTME-FR03319FR-BAPD25501-GUY Collège ECO-Q RM [3319_BAPD25501] | G14: TESTME-FR03319FR-BAPD25501-GUY Collège ECO-Q RM [3319_BAPD25501] | H14: DRAFT | I14: EGIS BATIMENTS ILE DE FRANCE | J14: =_xlfn.XLOOKUP(I14,LE!A:A,LE!F:F,,1) -> 0 | K14: SL-Buildings-CC-12-IDMI-01-Ile de France-BU-FR03305FR_EGIS BAT IDF | L14: SL-Buildings-CC-12-IDMI-01-Ile de France-BU-FR03305FR_EGIS BAT IDF | M14: EGIS BATIMENTS ILE DE FRANCE Billable E&SC Small Project | N14: EGIS BATIMENTS ILE DE FRANCE Billable E&SC Small Project | V14: EUR | X14: Corporate | Y14: T | Z14: FALSE | AA14: FALSE | AB14: TRUE | AC14: TRUE | AD14: ACT | AE14: P04 | AG14: FINANCIAL | BN14: 46387 | BO14: 43679 | BP14: BAPD255 | BQ14: STD | BR14: Standard | CG14: 46162 | CH14: P04 | CI14: 43679 | CJ14: PJF_TASKS | CK14: FINANCIAL
B15: OK | D15: CREATE | E15: BIL-1007990 | F15: TESTME-FR03319FR-BAPD25501-GUY Collège ECO-Q RM [3319_BAPD25501] | G15: TESTME-FR03319FR-BAPD25501-GUY Collège ECO-Q RM [3319_BAPD25501] | H15: DRAFT | I15: EGIS BATIMENTS ILE DE FRANCE | J15: =_xlfn.XLOOKUP(I15,LE!A:A,LE!F:F,,1) -> 0 | K15: SL-Buildings-CC-12-IDMI-01-Ile de France-BU-FR03305FR_EGIS BAT IDF | L15: SL-Buildings-CC-12-IDMI-01-Ile de France-BU-FR03305FR_EGIS BAT IDF | M15: EGIS BATIMENTS ILE DE FRANCE Billable E&SC Small Project | N15: EGIS BATIMENTS ILE DE FRANCE Billable E&SC Small Project | V15: EUR | X15: Corporate | Y15: T | Z15: FALSE | AA15: FALSE | AB15: TRUE | AC15: TRUE | AD15: VISA DET AOR | AE15: P05 | AG15: FINANCIAL | BN15: 46387 | BO15: 43679 | BP15: BAPD255 | BQ15: STD | BR15: Standard | CG15: 46387 | CH15: P05 | CI15: 43679 | CJ15: PJF_TASKS | CK15: FINANCIAL
B16: OK | D16: CREATE | E16: BIL-1007990 | F16: TESTME-FR03319FR-BAPD25501-GUY Collège ECO-Q RM [3319_BAPD25501] | G16: TESTME-FR03319FR-BAPD25501-GUY Collège ECO-Q RM [3319_BAPD25501] | H16: DRAFT | I16: EGIS BATIMENTS ILE DE FRANCE | J16: =_xlfn.XLOOKUP(I16,LE!A:A,LE!F:F,,1) -> 0 | K16: SL-Buildings-CC-12-IDMI-01-Ile de France-BU-FR03305FR_EGIS BAT IDF | L16: SL-Buildings-CC-12-IDMI-01-Ile de France-BU-FR03305FR_EGIS BAT IDF | M16: EGIS BATIMENTS ILE DE FRANCE Billable E&SC Small Project | N16: EGIS BATIMENTS ILE DE FRANCE Billable E&SC Small Project | V16: EUR | X16: Corporate | Y16: T | Z16: FALSE | AA16: FALSE | AB16: TRUE | AC16: TRUE | AD16: Facturation Milestone Oracle 2025 | AE16: P97 | AG16: FINANCIAL | BN16: 46387 | BO16: 43679 | BP16: BAPD255 | BQ16: STD | BR16: Standard | CG16: 46162 | CH16: P97 | CI16: 43679 | CJ16: PJF_TASKS | CK16: FINANCIAL
B17: OK | D17: CREATE | E17: BIL-1007990 | F17: TESTME-FR03319FR-BAPD25501-GUY Collège ECO-Q RM [3319_BAPD25501] | G17: TESTME-FR03319FR-BAPD25501-GUY Collège ECO-Q RM [3319_BAPD25501] | H17: DRAFT | I17: EGIS BATIMENTS ILE DE FRANCE | J17: =_xlfn.XLOOKUP(I17,LE!A:A,LE!F:F,,1) -> 0 | K17: SL-Buildings-CC-12-IDMI-01-Ile de France-BU-FR03305FR_EGIS BAT IDF | L17: SL-Buildings-CC-12-IDMI-01-Ile de France-BU-FR03305FR_EGIS BAT IDF | M17: EGIS BATIMENTS ILE DE FRANCE Billable E&SC Small Project | N17: EGIS BATIMENTS ILE DE FRANCE Billable E&SC Small Project | V17: EUR | X17: Corporate | Y17: T | Z17: FALSE | AA17: FALSE | AB17: TRUE | AC17: TRUE | AV17: Project Classification | AW17: Client Project | BN17: 46387 | BO17: 43679 | BP17: BAPD255 | BQ17: STD | BR17: Standard
B18: OK | D18: CREATE | E18: BIL-1007990 | F18: TESTME-FR03319FR-BAPD25501-GUY Collège ECO-Q RM [3319_BAPD25501] | G18: TESTME-FR03319FR-BAPD25501-GUY Collège ECO-Q RM [3319_BAPD25501] | H18: DRAFT | I18: EGIS BATIMENTS ILE DE FRANCE | J18: =_xlfn.XLOOKUP(I18,LE!A:A,LE!F:F,,1) -> 0 | K18: SL-Buildings-CC-12-IDMI-01-Ile de France-BU-FR03305FR_EGIS BAT IDF | L18: SL-Buildings-CC-12-IDMI-01-Ile de France-BU-FR03305FR_EGIS BAT IDF | M18: EGIS BATIMENTS ILE DE FRANCE Billable E&SC Small Project | N18: EGIS BATIMENTS ILE DE FRANCE Billable E&SC Small Project | V18: EUR | X18: Corporate | Y18: T | Z18: FALSE | AA18: FALSE | AB18: TRUE | AC18: TRUE | AS18: Benoit.THERON@egis-group.com | AT18: Project Manager | AU18: 43679 | BN18: 46387 | BO18: 43679 | BP18: BAPD255 | BQ18: STD | BR18: Standard
B19: OK | D19: CREATE | E19: BIL-1007990 | F19: TESTME-FR03319FR-BAPD25501-GUY Collège ECO-Q RM [3319_BAPD25501] | G19: TESTME-FR03319FR-BAPD25501-GUY Collège ECO-Q RM [3319_BAPD25501] | H19: DRAFT | I19: EGIS BATIMENTS ILE DE FRANCE | J19: =_xlfn.XLOOKUP(I19,LE!A:A,LE!F:F,,1) -> 0 | K19: SL-Buildings-CC-12-IDMI-01-Ile de France-BU-FR03305FR_EGIS BAT IDF | L19: SL-Buildings-CC-12-IDMI-01-Ile de France-BU-FR03305FR_EGIS BAT IDF | M19: EGIS BATIMENTS ILE DE FRANCE Billable E&SC Small Project | N19: EGIS BATIMENTS ILE DE FRANCE Billable E&SC Small Project | V19: EUR | X19: Corporate | Y19: T | Z19: FALSE | AA19: FALSE | AB19: TRUE | AC19: TRUE | AS19: Rokhaya.NDIAYE@egis-group.com | AT19: Financial Controller | AU19: 43679 | BN19: 46387 | BO19: 43679 | BP19: BAPD255 | BQ19: STD | BR19: Standard
B20: OK | D20: CREATE | E20: BIL-1007990 | F20: TESTME-FR03319FR-BAPD25501-GUY Collège ECO-Q RM [3319_BAPD25501] | G20: TESTME-FR03319FR-BAPD25501-GUY Collège ECO-Q RM [3319_BAPD25501] | H20: DRAFT | I20: EGIS BATIMENTS ILE DE FRANCE | J20: =_xlfn.XLOOKUP(I20,LE!A:A,LE!F:F,,1) -> 0 | K20: SL-Buildings-CC-12-IDMI-01-Ile de France-BU-FR03305FR_EGIS BAT IDF | L20: SL-Buildings-CC-12-IDMI-01-Ile de France-BU-FR03305FR_EGIS BAT IDF | M20: EGIS BATIMENTS ILE DE FRANCE Billable E&SC Small Project | N20: EGIS BATIMENTS ILE DE FRANCE Billable E&SC Small Project | V20: EUR | X20: Corporate | Y20: T | Z20: FALSE | AA20: FALSE | AB20: TRUE | AC20: TRUE | AS20: Sebastien.PLICHON@egis-group.com | AT20: RBLD | AU20: 43679 | BN20: 46387 | BO20: 43679 | BP20: BAPD255 | BQ20: STD | BR20: Standard
B21: OK | D21: CREATE | E21: BIL-1007990 | F21: TESTME-FR03319FR-BAPD25501-GUY Collège ECO-Q RM [3319_BAPD25501] | G21: TESTME-FR03319FR-BAPD25501-GUY Collège ECO-Q RM [3319_BAPD25501] | H21: DRAFT | I21: EGIS BATIMENTS ILE DE FRANCE | J21: =_xlfn.XLOOKUP(I21,LE!A:A,LE!F:F,,1) -> 0 | K21: SL-Buildings-CC-12-IDMI-01-Ile de France-BU-FR03305FR_EGIS BAT IDF | L21: SL-Buildings-CC-12-IDMI-01-Ile de France-BU-FR03305FR_EGIS BAT IDF | M21: EGIS BATIMENTS ILE DE FRANCE Billable E&SC Small Project | N21: EGIS BATIMENTS ILE DE FRANCE Billable E&SC Small Project | V21: EUR | X21: Corporate | Y21: T | Z21: FALSE | AA21: FALSE | AB21: TRUE | AC21: TRUE | AS21: Cedric.ARNAUD@egis-group.com | AT21: Project Sponsor / RBLD Delegate | AU21: 45658 | BN21: 46387 | BO21: 43679 | BP21: BAPD255 | BQ21: STD | BR21: Standard
B22: OK | D22: CREATE | E22: BIL-1007990 | F22: TESTME-FR03319FR-BAPD25501-GUY Collège ECO-Q RM [3319_BAPD25501] | G22: TESTME-FR03319FR-BAPD25501-GUY Collège ECO-Q RM [3319_BAPD25501] | H22: DRAFT | I22: EGIS BATIMENTS ILE DE FRANCE | J22: =_xlfn.XLOOKUP(I22,LE!A:A,LE!F:F,,1) -> 0 | K22: SL-Buildings-CC-12-IDMI-01-Ile de France-BU-FR03305FR_EGIS BAT IDF | L22: SL-Buildings-CC-12-IDMI-01-Ile de France-BU-FR03305FR_EGIS BAT IDF | M22: EGIS BATIMENTS ILE DE FRANCE Billable E&SC Small Project | N22: EGIS BATIMENTS ILE DE FRANCE Billable E&SC Small Project | V22: EUR | X22: Corporate | Y22: T | Z22: FALSE | AA22: FALSE | AB22: TRUE | AC22: TRUE | AS22: Cedric.ARNAUD@egis-group.com | AT22: Project Manager | AU22: 45658 | BN22: 46387 | BO22: 43679 | BP22: BAPD255 | BQ22: STD | BR22: Standard
B23: OK | D23: CREATE | E23: BIL-1007991 | F23: TESTME--TESTME-FR03319FR-BAPD25501-GUY Collège ECO-Q RM [3319_BAPD25501] | G23: TESTME--TESTME-FR03319FR-BAPD25501-GUY Collège ECO-Q RM [3319_BAPD25501] | H23: DRAFT | I23: EGIS BATIMENTS ILE DE FRANCE | J23: =_xlfn.XLOOKUP(I23,LE!A:A,LE!F:F,,1) -> 0 | K23: SL-Buildings-CC-12-IDMI-01-Ile de France-BU-FR03305FR_EGIS BAT IDF | L23: SL-Buildings-CC-12-IDMI-01-Ile de France-BU-FR03305FR_EGIS BAT IDF | M23: EGIS BATIMENTS ILE DE FRANCE Billable E&SC Small Project | N23: EGIS BATIMENTS ILE DE FRANCE Billable E&SC Small Project | V23: EUR | X23: Corporate | Y23: T | Z23: FALSE | AA23: FALSE | AB23: TRUE | AC23: TRUE | AD23: O - Offre | AE23: P01 | AG23: FINANCIAL | BN23: 47087 | BO23: 43644 | BP23: AVPC038 | BQ23: STD | BR23: Standard | CG23: 45657 | CH23: P01 | CI23: 43644 | CJ23: PJF_TASKS | CK23: FINANCIAL
B24: OK | D24: CREATE | E24: BIL-1007991 | F24: TESTME--TESTME-FR03319FR-BAPD25501-GUY Collège ECO-Q RM [3319_BAPD25501] | G24: TESTME--TESTME-FR03319FR-BAPD25501-GUY Collège ECO-Q RM [3319_BAPD25501] | H24: DRAFT | I24: EGIS BATIMENTS ILE DE FRANCE | J24: =_xlfn.XLOOKUP(I24,LE!A:A,LE!F:F,,1) -> 0 | K24: SL-Buildings-CC-12-IDMI-01-Ile de France-BU-FR03305FR_EGIS BAT IDF | L24: SL-Buildings-CC-12-IDMI-01-Ile de France-BU-FR03305FR_EGIS BAT IDF | M24: EGIS BATIMENTS ILE DE FRANCE Billable E&SC Small Project | N24: EGIS BATIMENTS ILE DE FRANCE Billable E&SC Small Project | V24: EUR | X24: Corporate | Y24: T | Z24: FALSE | AA24: FALSE | AB24: TRUE | AC24: TRUE | AD24: E - Etudes | AE24: P02 | AG24: FINANCIAL | BN24: 47087 | BO24: 43644 | BP24: AVPC038 | BQ24: STD | BR24: Standard | CG24: 47087 | CH24: P02 | CI24: 43644 | CJ24: PJF_TASKS | CK24: FINANCIAL
B25: OK | D25: CREATE | E25: BIL-1007991 | F25: TESTME--TESTME-FR03319FR-BAPD25501-GUY Collège ECO-Q RM [3319_BAPD25501] | G25: TESTME--TESTME-FR03319FR-BAPD25501-GUY Collège ECO-Q RM [3319_BAPD25501] | H25: DRAFT | I25: EGIS BATIMENTS ILE DE FRANCE | J25: =_xlfn.XLOOKUP(I25,LE!A:A,LE!F:F,,1) -> 0 | K25: SL-Buildings-CC-12-IDMI-01-Ile de France-BU-FR03305FR_EGIS BAT IDF | L25: SL-Buildings-CC-12-IDMI-01-Ile de France-BU-FR03305FR_EGIS BAT IDF | M25: EGIS BATIMENTS ILE DE FRANCE Billable E&SC Small Project | N25: EGIS BATIMENTS ILE DE FRANCE Billable E&SC Small Project | V25: EUR | X25: Corporate | Y25: T | Z25: FALSE | AA25: FALSE | AB25: TRUE | AC25: TRUE | AD25: P03 - Phase 03 | AE25: P03 | AG25: FINANCIAL | BN25: 47087 | BO25: 43644 | BP25: AVPC038 | BQ25: STD | BR25: Standard | CG25: 47087 | CH25: P03 | CI25: 43644 | CJ25: PJF_TASKS | CK25: FINANCIAL
B26: OK | D26: CREATE | E26: BIL-1007991 | F26: TESTME--TESTME-FR03319FR-BAPD25501-GUY Collège ECO-Q RM [3319_BAPD25501] | G26: TESTME--TESTME-FR03319FR-BAPD25501-GUY Collège ECO-Q RM [3319_BAPD25501] | H26: DRAFT | I26: EGIS BATIMENTS ILE DE FRANCE | J26: =_xlfn.XLOOKUP(I26,LE!A:A,LE!F:F,,1) -> 0 | K26: SL-Buildings-CC-12-IDMI-01-Ile de France-BU-FR03305FR_EGIS BAT IDF | L26: SL-Buildings-CC-12-IDMI-01-Ile de France-BU-FR03305FR_EGIS BAT IDF | M26: EGIS BATIMENTS ILE DE FRANCE Billable E&SC Small Project | N26: EGIS BATIMENTS ILE DE FRANCE Billable E&SC Small Project | V26: EUR | X26: Corporate | Y26: T | Z26: FALSE | AA26: FALSE | AB26: TRUE | AC26: TRUE | AD26: Facturation Milestone Oracle 2025 | AE26: P97 | AG26: FINANCIAL | BN26: 47087 | BO26: 43644 | BP26: AVPC038 | BQ26: STD | BR26: Standard | CG26: 47087 | CH26: P97 | CI26: 43644 | CJ26: PJF_TASKS | CK26: FINANCIAL
B27: OK | D27: CREATE | E27: BIL-1007991 | F27: TESTME--TESTME-FR03319FR-BAPD25501-GUY Collège ECO-Q RM [3319_BAPD25501] | G27: TESTME--TESTME-FR03319FR-BAPD25501-GUY Collège ECO-Q RM [3319_BAPD25501] | H27: DRAFT | I27: EGIS BATIMENTS ILE DE FRANCE | J27: =_xlfn.XLOOKUP(I27,LE!A:A,LE!F:F,,1) -> 0 | K27: SL-Buildings-CC-12-IDMI-01-Ile de France-BU-FR03305FR_EGIS BAT IDF | L27: SL-Buildings-CC-12-IDMI-01-Ile de France-BU-FR03305FR_EGIS BAT IDF | M27: EGIS BATIMENTS ILE DE FRANCE Billable E&SC Small Project | N27: EGIS BATIMENTS ILE DE FRANCE Billable E&SC Small Project | V27: EUR | X27: Corporate | Y27: T | Z27: FALSE | AA27: FALSE | AB27: TRUE | AC27: TRUE | AV27: Project Classification | AW27: Client Project | BN27: 47087 | BO27: 43644 | BP27: AVPC038 | BQ27: STD | BR27: Standard
B28: OK | D28: CREATE | E28: BIL-1007991 | F28: TESTME--TESTME-FR03319FR-BAPD25501-GUY Collège ECO-Q RM [3319_BAPD25501] | G28: TESTME--TESTME-FR03319FR-BAPD25501-GUY Collège ECO-Q RM [3319_BAPD25501] | H28: DRAFT | I28: EGIS BATIMENTS ILE DE FRANCE | J28: =_xlfn.XLOOKUP(I28,LE!A:A,LE!F:F,,1) -> 0 | K28: SL-Buildings-CC-12-IDMI-01-Ile de France-BU-FR03305FR_EGIS BAT IDF | L28: SL-Buildings-CC-12-IDMI-01-Ile de France-BU-FR03305FR_EGIS BAT IDF | M28: EGIS BATIMENTS ILE DE FRANCE Billable E&SC Small Project | N28: EGIS BATIMENTS ILE DE FRANCE Billable E&SC Small Project | V28: EUR | X28: Corporate | Y28: T | Z28: FALSE | AA28: FALSE | AB28: TRUE | AC28: TRUE | AS28: Romain.PENNES@egis-group.com | AT28: Project Manager | AU28: 44749 | BN28: 47087 | BO28: 43644 | BP28: AVPC038 | BQ28: STD | BR28: Standard
B29: OK | D29: CREATE | E29: BIL-1007991 | F29: TESTME--TESTME-FR03319FR-BAPD25501-GUY Collège ECO-Q RM [3319_BAPD25501] | G29: TESTME--TESTME-FR03319FR-BAPD25501-GUY Collège ECO-Q RM [3319_BAPD25501] | H29: DRAFT | I29: EGIS BATIMENTS ILE DE FRANCE | J29: =_xlfn.XLOOKUP(I29,LE!A:A,LE!F:F,,1) -> 0 | K29: SL-Buildings-CC-12-IDMI-01-Ile de France-BU-FR03305FR_EGIS BAT IDF | L29: SL-Buildings-CC-12-IDMI-01-Ile de France-BU-FR03305FR_EGIS BAT IDF | M29: EGIS BATIMENTS ILE DE FRANCE Billable E&SC Small Project | N29: EGIS BATIMENTS ILE DE FRANCE Billable E&SC Small Project | V29: EUR | X29: Corporate | Y29: T | Z29: FALSE | AA29: FALSE | AB29: TRUE | AC29: TRUE | AS29: Rokhaya.NDIAYE@egis-group.com | AT29: Financial Controller | AU29: 43644 | BN29: 47087 | BO29: 43644 | BP29: AVPC038 | BQ29: STD | BR29: Standard
B30: OK | D30: CREATE | E30: BIL-1007991 | F30: TESTME--TESTME-FR03319FR-BAPD25501-GUY Collège ECO-Q RM [3319_BAPD25501] | G30: TESTME--TESTME-FR03319FR-BAPD25501-GUY Collège ECO-Q RM [3319_BAPD25501] | H30: DRAFT | I30: EGIS BATIMENTS ILE DE FRANCE | J30: =_xlfn.XLOOKUP(I30,LE!A:A,LE!F:F,,1) -> 0 | K30: SL-Buildings-CC-12-IDMI-01-Ile de France-BU-FR03305FR_EGIS BAT IDF | L30: SL-Buildings-CC-12-IDMI-01-Ile de France-BU-FR03305FR_EGIS BAT IDF | M30: EGIS BATIMENTS ILE DE FRANCE Billable E&SC Small Project | N30: EGIS BATIMENTS ILE DE FRANCE Billable E&SC Small Project | V30: EUR | X30: Corporate | Y30: T | Z30: FALSE | AA30: FALSE | AB30: TRUE | AC30: TRUE | AS30: Cedric.ARNAUD@egis-group.com | AT30: Project Sponsor / RBLD Delegate | AU30: 45352 | BN30: 47087 | BO30: 43644 | BP30: AVPC038 | BQ30: STD | BR30: Standard
B31: OK | D31: CREATE | E31: BIL-1007991 | F31: TESTME--TESTME-FR03319FR-BAPD25501-GUY Collège ECO-Q RM [3319_BAPD25501] | G31: TESTME--TESTME-FR03319FR-BAPD25501-GUY Collège ECO-Q RM [3319_BAPD25501] | H31: DRAFT | I31: EGIS BATIMENTS ILE DE FRANCE | J31: =_xlfn.XLOOKUP(I31,LE!A:A,LE!F:F,,1) -> 0 | K31: SL-Buildings-CC-12-IDMI-01-Ile de France-BU-FR03305FR_EGIS BAT IDF | L31: SL-Buildings-CC-12-IDMI-01-Ile de France-BU-FR03305FR_EGIS BAT IDF | M31: EGIS BATIMENTS ILE DE FRANCE Billable E&SC Small Project | N31: EGIS BATIMENTS ILE DE FRANCE Billable E&SC Small Project | V31: EUR | X31: Corporate | Y31: T | Z31: FALSE | AA31: FALSE | AB31: TRUE | AC31: TRUE | AS31: Sebastien.PLICHON@egis-group.com | AT31: RBLD | AU31: 43644 | BN31: 47087 | BO31: 43644 | BP31: AVPC038 | BQ31: STD | BR31: Standard
B32: OK | D32: CREATE | E32: BIL-1007991 | F32: TESTME--TESTME-FR03319FR-BAPD25501-GUY Collège ECO-Q RM [3319_BAPD25501] | G32: TESTME--TESTME-FR03319FR-BAPD25501-GUY Collège ECO-Q RM [3319_BAPD25501] | H32: DRAFT | I32: EGIS BATIMENTS ILE DE FRANCE | J32: =_xlfn.XLOOKUP(I32,LE!A:A,LE!F:F,,1) -> 0 | K32: SL-Buildings-CC-12-IDMI-01-Ile de France-BU-FR03305FR_EGIS BAT IDF | L32: SL-Buildings-CC-12-IDMI-01-Ile de France-BU-FR03305FR_EGIS BAT IDF | M32: EGIS BATIMENTS ILE DE FRANCE Billable E&SC Small Project | N32: EGIS BATIMENTS ILE DE FRANCE Billable E&SC Small Project | V32: EUR | X32: Corporate | Y32: T | Z32: FALSE | AA32: FALSE | AB32: TRUE | AC32: TRUE | AS32: Cedric.ARNAUD@egis-group.com | AT32: Project Manager | AU32: 45658 | BN32: 47087 | BO32: 43644 | BP32: AVPC038 | BQ32: STD | BR32: Standard
B33: OK | D33: CREATE | E33: BIL-1007992 | F33: TESTME-FR03319FR-AVPC03801-GUAD> SSI Ext T1 P Caraïbes [3319_AVPC03801] | G33: TESTME-FR03319FR-AVPC03801-GUAD> SSI Ext T1 P Caraïbes [3319_AVPC03801] | H33: DRAFT | I33: EGIS BATIMENTS ILE DE FRANCE | J33: EGIS BATIMENTS ILE DE FRANCE | K33: SL-Buildings-CC-12-IDMI-01-Ile de France-BU-FR03305FR_EGIS BAT IDF | L33: SL-Buildings-CC-12-IDMI-01-Ile de France-BU-FR03305FR_EGIS BAT IDF | M33: EGIS BATIMENTS ILE DE FRANCE Billable E&SC Small Project | N33: EGIS BATIMENTS ILE DE FRANCE Billable E&SC Small Project | V33: EUR | X33: Corporate | Y33: T | Z33: FALSE | AA33: FALSE | AB33: TRUE | AC33: TRUE | AD33: O - Offre | AE33: P01 | AG33: FINANCIAL | BN33: 47087 | BO33: 43644 | BP33: AVPC038 | BQ33: STD | BR33: Standard | CG33: 45657 | CH33: P01 | CI33: 43644 | CJ33: PJF_TASKS | CK33: FINANCIAL
B34: OK | D34: CREATE | E34: BIL-1007992 | F34: TESTME-FR03319FR-AVPC03801-GUAD> SSI Ext T1 P Caraïbes [3319_AVPC03801] | G34: TESTME-FR03319FR-AVPC03801-GUAD> SSI Ext T1 P Caraïbes [3319_AVPC03801] | H34: DRAFT | I34: EGIS BATIMENTS ILE DE FRANCE | J34: EGIS BATIMENTS ILE DE FRANCE | K34: SL-Buildings-CC-12-IDMI-01-Ile de France-BU-FR03305FR_EGIS BAT IDF | L34: SL-Buildings-CC-12-IDMI-01-Ile de France-BU-FR03305FR_EGIS BAT IDF | M34: EGIS BATIMENTS ILE DE FRANCE Billable E&SC Small Project | N34: EGIS BATIMENTS ILE DE FRANCE Billable E&SC Small Project | V34: EUR | X34: Corporate | Y34: T | Z34: FALSE | AA34: FALSE | AB34: TRUE | AC34: TRUE | AD34: E - Etudes | AE34: P02 | AG34: FINANCIAL | BN34: 47087 | BO34: 43644 | BP34: AVPC038 | BQ34: STD | BR34: Standard | CG34: 47087 | CH34: P02 | CI34: 43644 | CJ34: PJF_TASKS | CK34: FINANCIAL
B35: OK | D35: CREATE | E35: BIL-1007992 | F35: TESTME-FR03319FR-AVPC03801-GUAD> SSI Ext T1 P Caraïbes [3319_AVPC03801] | G35: TESTME-FR03319FR-AVPC03801-GUAD> SSI Ext T1 P Caraïbes [3319_AVPC03801] | H35: DRAFT | I35: EGIS BATIMENTS ILE DE FRANCE | J35: EGIS BATIMENTS ILE DE FRANCE | K35: SL-Buildings-CC-12-IDMI-01-Ile de France-BU-FR03305FR_EGIS BAT IDF | L35: SL-Buildings-CC-12-IDMI-01-Ile de France-BU-FR03305FR_EGIS BAT IDF | M35: EGIS BATIMENTS ILE DE FRANCE Billable E&SC Small Project | N35: EGIS BATIMENTS ILE DE FRANCE Billable E&SC Small Project | V35: EUR | X35: Corporate | Y35: T | Z35: FALSE | AA35: FALSE | AB35: TRUE | AC35: TRUE | AD35: P03 - Phase 03 | AE35: P03 | AG35: FINANCIAL | BN35: 47087 | BO35: 43644 | BP35: AVPC038 | BQ35: STD | BR35: Standard | CG35: 47087 | CH35: P03 | CI35: 43644 | CJ35: PJF_TASKS | CK35: FINANCIAL
B36: OK | D36: CREATE | E36: BIL-1007992 | F36: TESTME-FR03319FR-AVPC03801-GUAD> SSI Ext T1 P Caraïbes [3319_AVPC03801] | G36: TESTME-FR03319FR-AVPC03801-GUAD> SSI Ext T1 P Caraïbes [3319_AVPC03801] | H36: DRAFT | I36: EGIS BATIMENTS ILE DE FRANCE | J36: EGIS BATIMENTS ILE DE FRANCE | K36: SL-Buildings-CC-12-IDMI-01-Ile de France-BU-FR03305FR_EGIS BAT IDF | L36: SL-Buildings-CC-12-IDMI-01-Ile de France-BU-FR03305FR_EGIS BAT IDF | M36: EGIS BATIMENTS ILE DE FRANCE Billable E&SC Small Project | N36: EGIS BATIMENTS ILE DE FRANCE Billable E&SC Small Project | V36: EUR | X36: Corporate | Y36: T | Z36: FALSE | AA36: FALSE | AB36: TRUE | AC36: TRUE | AD36: Facturation Milestone Oracle 2025 | AE36: P97 | AG36: FINANCIAL | BN36: 47087 | BO36: 43644 | BP36: AVPC038 | BQ36: STD | BR36: Standard | CG36: 47087 | CH36: P97 | CI36: 43644 | CJ36: PJF_TASKS | CK36: FINANCIAL
B37: OK | D37: CREATE | E37: BIL-1007992 | F37: TESTME-FR03319FR-AVPC03801-GUAD> SSI Ext T1 P Caraïbes [3319_AVPC03801] | G37: TESTME-FR03319FR-AVPC03801-GUAD> SSI Ext T1 P Caraïbes [3319_AVPC03801] | H37: DRAFT | I37: EGIS BATIMENTS ILE DE FRANCE | J37: EGIS BATIMENTS ILE DE FRANCE | K37: SL-Buildings-CC-12-IDMI-01-Ile de France-BU-FR03305FR_EGIS BAT IDF | L37: SL-Buildings-CC-12-IDMI-01-Ile de France-BU-FR03305FR_EGIS BAT IDF | M37: EGIS BATIMENTS ILE DE FRANCE Billable E&SC Small Project | N37: EGIS BATIMENTS ILE DE FRANCE Billable E&SC Small Project | V37: EUR | X37: Corporate | Y37: T | Z37: FALSE | AA37: FALSE | AB37: TRUE | AC37: TRUE | AV37: Project Classification | AW37: Client Project | BN37: 47087 | BO37: 43644 | BP37: AVPC038 | BQ37: STD | BR37: Standard
B38: OK | D38: CREATE | E38: BIL-1007992 | F38: TESTME-FR03319FR-AVPC03801-GUAD> SSI Ext T1 P Caraïbes [3319_AVPC03801] | G38: TESTME-FR03319FR-AVPC03801-GUAD> SSI Ext T1 P Caraïbes [3319_AVPC03801] | H38: DRAFT | I38: EGIS BATIMENTS ILE DE FRANCE | J38: EGIS BATIMENTS ILE DE FRANCE | K38: SL-Buildings-CC-12-IDMI-01-Ile de France-BU-FR03305FR_EGIS BAT IDF | L38: SL-Buildings-CC-12-IDMI-01-Ile de France-BU-FR03305FR_EGIS BAT IDF | M38: EGIS BATIMENTS ILE DE FRANCE Billable E&SC Small Project | N38: EGIS BATIMENTS ILE DE FRANCE Billable E&SC Small Project | V38: EUR | X38: Corporate | Y38: T | Z38: FALSE | AA38: FALSE | AB38: TRUE | AC38: TRUE | AS38: Romain.PENNES@egis-group.com | AT38: Project Manager | AU38: 44749 | BN38: 47087 | BO38: 43644 | BP38: AVPC038 | BQ38: STD | BR38: Standard
B39: OK | D39: CREATE | E39: BIL-1007992 | F39: TESTME-FR03319FR-AVPC03801-GUAD> SSI Ext T1 P Caraïbes [3319_AVPC03801] | G39: TESTME-FR03319FR-AVPC03801-GUAD> SSI Ext T1 P Caraïbes [3319_AVPC03801] | H39: DRAFT | I39: EGIS BATIMENTS ILE DE FRANCE | J39: EGIS BATIMENTS ILE DE FRANCE | K39: SL-Buildings-CC-12-IDMI-01-Ile de France-BU-FR03305FR_EGIS BAT IDF | L39: SL-Buildings-CC-12-IDMI-01-Ile de France-BU-FR03305FR_EGIS BAT IDF | M39: EGIS BATIMENTS ILE DE FRANCE Billable E&SC Small Project | N39: EGIS BATIMENTS ILE DE FRANCE Billable E&SC Small Project | V39: EUR | X39: Corporate | Y39: T | Z39: FALSE | AA39: FALSE | AB39: TRUE | AC39: TRUE | AS39: Rokhaya.NDIAYE@egis-group.com | AT39: Financial Controller | AU39: 43644 | BN39: 47087 | BO39: 43644 | BP39: AVPC038 | BQ39: STD | BR39: Standard
B40: OK | D40: CREATE | E40: BIL-1007992 | F40: TESTME-FR03319FR-AVPC03801-GUAD> SSI Ext T1 P Caraïbes [3319_AVPC03801] | G40: TESTME-FR03319FR-AVPC03801-GUAD> SSI Ext T1 P Caraïbes [3319_AVPC03801] | H40: DRAFT | I40: EGIS BATIMENTS ILE DE FRANCE | J40: EGIS BATIMENTS ILE DE FRANCE | K40: SL-Buildings-CC-12-IDMI-01-Ile de France-BU-FR03305FR_EGIS BAT IDF | L40: SL-Buildings-CC-12-IDMI-01-Ile de France-BU-FR03305FR_EGIS BAT IDF | M40: EGIS BATIMENTS ILE DE FRANCE Billable E&SC Small Project | N40: EGIS BATIMENTS ILE DE FRANCE Billable E&SC Small Project | V40: EUR | X40: Corporate | Y40: T | Z40: FALSE | AA40: FALSE | AB40: TRUE | AC40: TRUE | AS40: Cedric.ARNAUD@egis-group.com | AT40: Project Sponsor / RBLD Delegate | AU40: 45352 | BN40: 47087 | BO40: 43644 | BP40: AVPC038 | BQ40: STD | BR40: Standard
B41: OK | D41: CREATE | E41: BIL-1007992 | F41: TESTME-FR03319FR-AVPC03801-GUAD> SSI Ext T1 P Caraïbes [3319_AVPC03801] | G41: TESTME-FR03319FR-AVPC03801-GUAD> SSI Ext T1 P Caraïbes [3319_AVPC03801] | H41: DRAFT | I41: EGIS BATIMENTS ILE DE FRANCE | J41: EGIS BATIMENTS ILE DE FRANCE | K41: SL-Buildings-CC-12-IDMI-01-Ile de France-BU-FR03305FR_EGIS BAT IDF | L41: SL-Buildings-CC-12-IDMI-01-Ile de France-BU-FR03305FR_EGIS BAT IDF | M41: EGIS BATIMENTS ILE DE FRANCE Billable E&SC Small Project | N41: EGIS BATIMENTS ILE DE FRANCE Billable E&SC Small Project | V41: EUR | X41: Corporate | Y41: T | Z41: FALSE | AA41: FALSE | AB41: TRUE | AC41: TRUE | AS41: Sebastien.PLICHON@egis-group.com | AT41: RBLD | AU41: 43644 | BN41: 47087 | BO41: 43644 | BP41: AVPC038 | BQ41: STD | BR41: Standard
B42: OK | D42: CREATE | E42: BIL-1007992 | F42: TESTME-FR03319FR-AVPC03801-GUAD> SSI Ext T1 P Caraïbes [3319_AVPC03801] | G42: TESTME-FR03319FR-AVPC03801-GUAD> SSI Ext T1 P Caraïbes [3319_AVPC03801] | H42: DRAFT | I42: EGIS BATIMENTS ILE DE FRANCE | J42: EGIS BATIMENTS ILE DE FRANCE | K42: SL-Buildings-CC-12-IDMI-01-Ile de France-BU-FR03305FR_EGIS BAT IDF | L42: SL-Buildings-CC-12-IDMI-01-Ile de France-BU-FR03305FR_EGIS BAT IDF | M42: EGIS BATIMENTS ILE DE FRANCE Billable E&SC Small Project | N42: EGIS BATIMENTS ILE DE FRANCE Billable E&SC Small Project | V42: EUR | X42: Corporate | Y42: T | Z42: FALSE | AA42: FALSE | AB42: TRUE | AC42: TRUE | AS42: Cedric.ARNAUD@egis-group.com | AT42: Project Manager | AU42: 45658 | BN42: 47087 | BO42: 43644 | BP42: AVPC038 | BQ42: STD | BR42: Standard
B43: OK | D43: CREATE | E43: BIL-1007993 | F43: TESTME-FR03319FR-AVPC03802-GUAD> OPC Ext T1 P Caraïbes [3319_AVPC03802] | G43: TESTME-FR03319FR-AVPC03802-GUAD> OPC Ext T1 P Caraïbes [3319_AVPC03802] | H43: DRAFT | I43: EGIS BATIMENTS ILE DE FRANCE | J43: EGIS BATIMENTS ILE DE FRANCE | K43: SL-Buildings-CC-12-IDMI-01-Ile de France-BU-FR03305FR_EGIS BAT IDF | L43: SL-Buildings-CC-12-IDMI-01-Ile de France-BU-FR03305FR_EGIS BAT IDF | M43: EGIS BATIMENTS ILE DE FRANCE Billable E&SC Small Project | N43: EGIS BATIMENTS ILE DE FRANCE Billable E&SC Small Project | V43: EUR | X43: Corporate | Y43: T | Z43: FALSE | AA43: FALSE | AB43: TRUE | AC43: TRUE | AD43: O - Offre | AE43: P01 | AG43: FINANCIAL | BN43: 47117 | BO43: 43731 | BP43: AVPC038 | BQ43: STD | BR43: Standard | CG43: 45657 | CH43: P01 | CI43: 43731 | CJ43: PJF_TASKS | CK43: FINANCIAL
B44: OK | D44: CREATE | E44: BIL-1007993 | F44: TESTME-FR03319FR-AVPC03802-GUAD> OPC Ext T1 P Caraïbes [3319_AVPC03802] | G44: TESTME-FR03319FR-AVPC03802-GUAD> OPC Ext T1 P Caraïbes [3319_AVPC03802] | H44: DRAFT | I44: EGIS BATIMENTS ILE DE FRANCE | J44: EGIS BATIMENTS ILE DE FRANCE | K44: SL-Buildings-CC-12-IDMI-01-Ile de France-BU-FR03305FR_EGIS BAT IDF | L44: SL-Buildings-CC-12-IDMI-01-Ile de France-BU-FR03305FR_EGIS BAT IDF | M44: EGIS BATIMENTS ILE DE FRANCE Billable E&SC Small Project | N44: EGIS BATIMENTS ILE DE FRANCE Billable E&SC Small Project | V44: EUR | X44: Corporate | Y44: T | Z44: FALSE | AA44: FALSE | AB44: TRUE | AC44: TRUE | AD44: T - Tri bagages | AE44: P02 | AG44: FINANCIAL | BN44: 47117 | BO44: 43731 | BP44: AVPC038 | BQ44: STD | BR44: Standard | CG44: 47117 | CH44: P02 | CI44: 43731 | CJ44: PJF_TASKS | CK44: FINANCIAL
B45: OK | D45: CREATE | E45: BIL-1007993 | F45: TESTME-FR03319FR-AVPC03802-GUAD> OPC Ext T1 P Caraïbes [3319_AVPC03802] | G45: TESTME-FR03319FR-AVPC03802-GUAD> OPC Ext T1 P Caraïbes [3319_AVPC03802] | H45: DRAFT | I45: EGIS BATIMENTS ILE DE FRANCE | J45: EGIS BATIMENTS ILE DE FRANCE | K45: SL-Buildings-CC-12-IDMI-01-Ile de France-BU-FR03305FR_EGIS BAT IDF | L45: SL-Buildings-CC-12-IDMI-01-Ile de France-BU-FR03305FR_EGIS BAT IDF | M45: EGIS BATIMENTS ILE DE FRANCE Billable E&SC Small Project | N45: EGIS BATIMENTS ILE DE FRANCE Billable E&SC Small Project | V45: EUR | X45: Corporate | Y45: T | Z45: FALSE | AA45: FALSE | AB45: TRUE | AC45: TRUE | AD45: T -Travaux - Ext T1 Salle bagages | AE45: P03 | AG45: FINANCIAL | BN45: 47117 | BO45: 43731 | BP45: AVPC038 | BQ45: STD | BR45: Standard | CG45: 47117 | CH45: P03 | CI45: 43731 | CJ45: PJF_TASKS | CK45: FINANCIAL
B46: OK | D46: CREATE | E46: BIL-1007993 | F46: TESTME-FR03319FR-AVPC03802-GUAD> OPC Ext T1 P Caraïbes [3319_AVPC03802] | G46: TESTME-FR03319FR-AVPC03802-GUAD> OPC Ext T1 P Caraïbes [3319_AVPC03802] | H46: DRAFT | I46: EGIS BATIMENTS ILE DE FRANCE | J46: EGIS BATIMENTS ILE DE FRANCE | K46: SL-Buildings-CC-12-IDMI-01-Ile de France-BU-FR03305FR_EGIS BAT IDF | L46: SL-Buildings-CC-12-IDMI-01-Ile de France-BU-FR03305FR_EGIS BAT IDF | M46: EGIS BATIMENTS ILE DE FRANCE Billable E&SC Small Project | N46: EGIS BATIMENTS ILE DE FRANCE Billable E&SC Small Project | V46: EUR | X46: Corporate | Y46: T | Z46: FALSE | AA46: FALSE | AB46: TRUE | AC46: TRUE | AD46: Facturation Milestone Oracle 2025 | AE46: P97 | AG46: FINANCIAL | BN46: 47117 | BO46: 43731 | BP46: AVPC038 | BQ46: STD | BR46: Standard | CG46: 47117 | CH46: P97 | CI46: 43731 | CJ46: PJF_TASKS | CK46: FINANCIAL
B47: OK | D47: CREATE | E47: BIL-1007993 | F47: TESTME-FR03319FR-AVPC03802-GUAD> OPC Ext T1 P Caraïbes [3319_AVPC03802] | G47: TESTME-FR03319FR-AVPC03802-GUAD> OPC Ext T1 P Caraïbes [3319_AVPC03802] | H47: DRAFT | I47: EGIS BATIMENTS ILE DE FRANCE | J47: EGIS BATIMENTS ILE DE FRANCE | K47: SL-Buildings-CC-12-IDMI-01-Ile de France-BU-FR03305FR_EGIS BAT IDF | L47: SL-Buildings-CC-12-IDMI-01-Ile de France-BU-FR03305FR_EGIS BAT IDF | M47: EGIS BATIMENTS ILE DE FRANCE Billable E&SC Small Project | N47: EGIS BATIMENTS ILE DE FRANCE Billable E&SC Small Project | V47: EUR | X47: Corporate | Y47: T | Z47: FALSE | AA47: FALSE | AB47: TRUE | AC47: TRUE | AV47: Project Classification | AW47: Client Project | BN47: 47117 | BO47: 43731 | BP47: AVPC038 | BQ47: STD | BR47: Standard
B48: OK | D48: CREATE | E48: BIL-1007993 | F48: TESTME-FR03319FR-AVPC03802-GUAD> OPC Ext T1 P Caraïbes [3319_AVPC03802] | G48: TESTME-FR03319FR-AVPC03802-GUAD> OPC Ext T1 P Caraïbes [3319_AVPC03802] | H48: DRAFT | I48: EGIS BATIMENTS ILE DE FRANCE | J48: EGIS BATIMENTS ILE DE FRANCE | K48: SL-Buildings-CC-12-IDMI-01-Ile de France-BU-FR03305FR_EGIS BAT IDF | L48: SL-Buildings-CC-12-IDMI-01-Ile de France-BU-FR03305FR_EGIS BAT IDF | M48: EGIS BATIMENTS ILE DE FRANCE Billable E&SC Small Project | N48: EGIS BATIMENTS ILE DE FRANCE Billable E&SC Small Project | V48: EUR | X48: Corporate | Y48: T | Z48: FALSE | AA48: FALSE | AB48: TRUE | AC48: TRUE | AS48: Regis.AUBERT@egis-group.com | AT48: Project Manager | AU48: 44502 | BN48: 47117 | BO48: 43731 | BP48: AVPC038 | BQ48: STD | BR48: Standard
B49: OK | D49: CREATE | E49: BIL-1007993 | F49: TESTME-FR03319FR-AVPC03802-GUAD> OPC Ext T1 P Caraïbes [3319_AVPC03802] | G49: TESTME-FR03319FR-AVPC03802-GUAD> OPC Ext T1 P Caraïbes [3319_AVPC03802] | H49: DRAFT | I49: EGIS BATIMENTS ILE DE FRANCE | J49: EGIS BATIMENTS ILE DE FRANCE | K49: SL-Buildings-CC-12-IDMI-01-Ile de France-BU-FR03305FR_EGIS BAT IDF | L49: SL-Buildings-CC-12-IDMI-01-Ile de France-BU-FR03305FR_EGIS BAT IDF | M49: EGIS BATIMENTS ILE DE FRANCE Billable E&SC Small Project | N49: EGIS BATIMENTS ILE DE FRANCE Billable E&SC Small Project | V49: EUR | X49: Corporate | Y49: T | Z49: FALSE | AA49: FALSE | AB49: TRUE | AC49: TRUE | AS49: Rokhaya.NDIAYE@egis-group.com | AT49: Financial Controller | AU49: 43731 | BN49: 47117 | BO49: 43731 | BP49: AVPC038 | BQ49: STD | BR49: Standard
B50: OK | D50: CREATE | E50: BIL-1007993 | F50: TESTME-FR03319FR-AVPC03802-GUAD> OPC Ext T1 P Caraïbes [3319_AVPC03802] | G50: TESTME-FR03319FR-AVPC03802-GUAD> OPC Ext T1 P Caraïbes [3319_AVPC03802] | H50: DRAFT | I50: EGIS BATIMENTS ILE DE FRANCE | J50: EGIS BATIMENTS ILE DE FRANCE | K50: SL-Buildings-CC-12-IDMI-01-Ile de France-BU-FR03305FR_EGIS BAT IDF | L50: SL-Buildings-CC-12-IDMI-01-Ile de France-BU-FR03305FR_EGIS BAT IDF | M50: EGIS BATIMENTS ILE DE FRANCE Billable E&SC Small Project | N50: EGIS BATIMENTS ILE DE FRANCE Billable E&SC Small Project | V50: EUR | X50: Corporate | Y50: T | Z50: FALSE | AA50: FALSE | AB50: TRUE | AC50: TRUE | AS50: Sebastien.PLICHON@egis-group.com | AT50: RBLD | AU50: 43731 | BN50: 47117 | BO50: 43731 | BP50: AVPC038 | BQ50: STD | BR50: Standard
B51: OK | D51: CREATE | E51: BIL-1007993 | F51: TESTME-FR03319FR-AVPC03802-GUAD> OPC Ext T1 P Caraïbes [3319_AVPC03802] | G51: TESTME-FR03319FR-AVPC03802-GUAD> OPC Ext T1 P Caraïbes [3319_AVPC03802] | H51: DRAFT | I51: EGIS BATIMENTS ILE DE FRANCE | J51: EGIS BATIMENTS ILE DE FRANCE | K51: SL-Buildings-CC-12-IDMI-01-Ile de France-BU-FR03305FR_EGIS BAT IDF | L51: SL-Buildings-CC-12-IDMI-01-Ile de France-BU-FR03305FR_EGIS BAT IDF | M51: EGIS BATIMENTS ILE DE FRANCE Billable E&SC Small Project | N51: EGIS BATIMENTS ILE DE FRANCE Billable E&SC Small Project | V51: EUR | X51: Corporate | Y51: T | Z51: FALSE | AA51: FALSE | AB51: TRUE | AC51: TRUE | AS51: Cedric.ARNAUD@egis-group.com | AT51: Project Sponsor / RBLD Delegate | AU51: 45658 | BN51: 47117 | BO51: 43731 | BP51: AVPC038 | BQ51: STD | BR51: Standard
B52: OK | D52: CREATE | E52: BIL-1007993 | F52: TESTME-FR03319FR-AVPC03802-GUAD> OPC Ext T1 P Caraïbes [3319_AVPC03802] | G52: TESTME-FR03319FR-AVPC03802-GUAD> OPC Ext T1 P Caraïbes [3319_AVPC03802] | H52: DRAFT | I52: EGIS BATIMENTS ILE DE FRANCE | J52: EGIS BATIMENTS ILE DE FRANCE | K52: SL-Buildings-CC-12-IDMI-01-Ile de France-BU-FR03305FR_EGIS BAT IDF | L52: SL-Buildings-CC-12-IDMI-01-Ile de France-BU-FR03305FR_EGIS BAT IDF | M52: EGIS BATIMENTS ILE DE FRANCE Billable E&SC Small Project | N52: EGIS BATIMENTS ILE DE FRANCE Billable E&SC Small Project | V52: EUR | X52: Corporate | Y52: T | Z52: FALSE | AA52: FALSE | AB52: TRUE | AC52: TRUE | AS52: Cedric.ARNAUD@egis-group.com | AT52: Project Manager | AU52: 45658 | BN52: 47117 | BO52: 43731 | BP52: AVPC038 | BQ52: STD | BR52: Standard
B53: OK | D53: CREATE | E53: BIL-1007994 | F53: TESTME-FR03319FR-BAOH12501-GUAD> Construction GS à Bois-Sec [3319_BAOH12501] | G53: TESTME-FR03319FR-BAOH12501-GUAD> Construction GS à Bois-Sec [3319_BAOH12501] | H53: DRAFT | I53: EGIS BATIMENTS ILE DE FRANCE | J53: EGIS BATIMENTS ILE DE FRANCE | K53: SL-Buildings-CC-12-IDMI-01-Ile de France-BU-FR03305FR_EGIS BAT IDF | L53: SL-Buildings-CC-12-IDMI-01-Ile de France-BU-FR03305FR_EGIS BAT IDF | M53: EGIS BATIMENTS ILE DE FRANCE Billable E&SC Small Project | N53: EGIS BATIMENTS ILE DE FRANCE Billable E&SC Small Project | V53: EUR | X53: Corporate | Y53: T | Z53: FALSE | AA53: FALSE | AB53: TRUE | AC53: TRUE | AD53: O - Offre | AE53: P01 | AG53: FINANCIAL | BN53: 46112 | BO53: 43346 | BP53: BAOH125 | BQ53: STD | BR53: Standard | CG53: 45657 | CH53: P01 | CI53: 43346 | CJ53: PJF_TASKS | CK53: FINANCIAL
B54: OK | D54: CREATE | E54: BIL-1007994 | F54: TESTME-FR03319FR-BAOH12501-GUAD> Construction GS à Bois-Sec [3319_BAOH12501] | G54: TESTME-FR03319FR-BAOH12501-GUAD> Construction GS à Bois-Sec [3319_BAOH12501] | H54: DRAFT | I54: EGIS BATIMENTS ILE DE FRANCE | J54: EGIS BATIMENTS ILE DE FRANCE | K54: SL-Buildings-CC-12-IDMI-01-Ile de France-BU-FR03305FR_EGIS BAT IDF | L54: SL-Buildings-CC-12-IDMI-01-Ile de France-BU-FR03305FR_EGIS BAT IDF | M54: EGIS BATIMENTS ILE DE FRANCE Billable E&SC Small Project | N54: EGIS BATIMENTS ILE DE FRANCE Billable E&SC Small Project | V54: EUR | X54: Corporate | Y54: T | Z54: FALSE | AA54: FALSE | AB54: TRUE | AC54: TRUE | AD54: E - Etudes | AE54: P02 | AG54: FINANCIAL | BN54: 46112 | BO54: 43346 | BP54: BAOH125 | BQ54: STD | BR54: Standard | CG54: 46112 | CH54: P02 | CI54: 43346 | CJ54: PJF_TASKS | CK54: FINANCIAL
B55: OK | D55: CREATE | E55: BIL-1007994 | F55: TESTME-FR03319FR-BAOH12501-GUAD> Construction GS à Bois-Sec [3319_BAOH12501] | G55: TESTME-FR03319FR-BAOH12501-GUAD> Construction GS à Bois-Sec [3319_BAOH12501] | H55: DRAFT | I55: EGIS BATIMENTS ILE DE FRANCE | J55: EGIS BATIMENTS ILE DE FRANCE | K55: SL-Buildings-CC-12-IDMI-01-Ile de France-BU-FR03305FR_EGIS BAT IDF | L55: SL-Buildings-CC-12-IDMI-01-Ile de France-BU-FR03305FR_EGIS BAT IDF | M55: EGIS BATIMENTS ILE DE FRANCE Billable E&SC Small Project | N55: EGIS BATIMENTS ILE DE FRANCE Billable E&SC Small Project | V55: EUR | X55: Corporate | Y55: T | Z55: FALSE | AA55: FALSE | AB55: TRUE | AC55: TRUE | AD55: T - Travaux | AE55: P03 | AG55: FINANCIAL | BN55: 46112 | BO55: 43346 | BP55: BAOH125 | BQ55: STD | BR55: Standard | CG55: 46112 | CH55: P03 | CI55: 43346 | CJ55: PJF_TASKS | CK55: FINANCIAL
B56: OK | D56: CREATE | E56: BIL-1007994 | F56: TESTME-FR03319FR-BAOH12501-GUAD> Construction GS à Bois-Sec [3319_BAOH12501] | G56: TESTME-FR03319FR-BAOH12501-GUAD> Construction GS à Bois-Sec [3319_BAOH12501] | H56: DRAFT | I56: EGIS BATIMENTS ILE DE FRANCE | J56: EGIS BATIMENTS ILE DE FRANCE | K56: SL-Buildings-CC-12-IDMI-01-Ile de France-BU-FR03305FR_EGIS BAT IDF | L56: SL-Buildings-CC-12-IDMI-01-Ile de France-BU-FR03305FR_EGIS BAT IDF | M56: EGIS BATIMENTS ILE DE FRANCE Billable E&SC Small Project | N56: EGIS BATIMENTS ILE DE FRANCE Billable E&SC Small Project | V56: EUR | X56: Corporate | Y56: T | Z56: FALSE | AA56: FALSE | AB56: TRUE | AC56: TRUE | AD56: Facturation Milestone Oracle 2025 | AE56: P97 | AG56: FINANCIAL | BN56: 46112 | BO56: 43346 | BP56: BAOH125 | BQ56: STD | BR56: Standard | CG56: 45747 | CH56: P97 | CI56: 43346 | CJ56: PJF_TASKS | CK56: FINANCIAL
B57: OK | D57: CREATE | E57: BIL-1007994 | F57: TESTME-FR03319FR-BAOH12501-GUAD> Construction GS à Bois-Sec [3319_BAOH12501] | G57: TESTME-FR03319FR-BAOH12501-GUAD> Construction GS à Bois-Sec [3319_BAOH12501] | H57: DRAFT | I57: EGIS BATIMENTS ILE DE FRANCE | J57: EGIS BATIMENTS ILE DE FRANCE | K57: SL-Buildings-CC-12-IDMI-01-Ile de France-BU-FR03305FR_EGIS BAT IDF | L57: SL-Buildings-CC-12-IDMI-01-Ile de France-BU-FR03305FR_EGIS BAT IDF | M57: EGIS BATIMENTS ILE DE FRANCE Billable E&SC Small Project | N57: EGIS BATIMENTS ILE DE FRANCE Billable E&SC Small Project | V57: EUR | X57: Corporate | Y57: T | Z57: FALSE | AA57: FALSE | AB57: TRUE | AC57: TRUE | AV57: Project Classification | AW57: Client Project | BN57: 46112 | BO57: 43346 | BP57: BAOH125 | BQ57: STD | BR57: Standard
B58: OK | D58: CREATE | E58: BIL-1007994 | F58: TESTME-FR03319FR-BAOH12501-GUAD> Construction GS à Bois-Sec [3319_BAOH12501] | G58: TESTME-FR03319FR-BAOH12501-GUAD> Construction GS à Bois-Sec [3319_BAOH12501] | H58: DRAFT | I58: EGIS BATIMENTS ILE DE FRANCE | J58: EGIS BATIMENTS ILE DE FRANCE | K58: SL-Buildings-CC-12-IDMI-01-Ile de France-BU-FR03305FR_EGIS BAT IDF | L58: SL-Buildings-CC-12-IDMI-01-Ile de France-BU-FR03305FR_EGIS BAT IDF | M58: EGIS BATIMENTS ILE DE FRANCE Billable E&SC Small Project | N58: EGIS BATIMENTS ILE DE FRANCE Billable E&SC Small Project | V58: EUR | X58: Corporate | Y58: T | Z58: FALSE | AA58: FALSE | AB58: TRUE | AC58: TRUE | AS58: Elie.ELIAS@egis-group.com | AT58: Project Manager | AU58: 43346 | BN58: 46112 | BO58: 43346 | BP58: BAOH125 | BQ58: STD | BR58: Standard
B59: OK | D59: CREATE | E59: BIL-1007994 | F59: TESTME-FR03319FR-BAOH12501-GUAD> Construction GS à Bois-Sec [3319_BAOH12501] | G59: TESTME-FR03319FR-BAOH12501-GUAD> Construction GS à Bois-Sec [3319_BAOH12501] | H59: DRAFT | I59: EGIS BATIMENTS ILE DE FRANCE | J59: EGIS BATIMENTS ILE DE FRANCE | K59: SL-Buildings-CC-12-IDMI-01-Ile de France-BU-FR03305FR_EGIS BAT IDF | L59: SL-Buildings-CC-12-IDMI-01-Ile de France-BU-FR03305FR_EGIS BAT IDF | M59: EGIS BATIMENTS ILE DE FRANCE Billable E&SC Small Project | N59: EGIS BATIMENTS ILE DE FRANCE Billable E&SC Small Project | V59: EUR | X59: Corporate | Y59: T | Z59: FALSE | AA59: FALSE | AB59: TRUE | AC59: TRUE | AS59: Rokhaya.NDIAYE@egis-group.com | AT59: Financial Controller | AU59: 43346 | BN59: 46112 | BO59: 43346 | BP59: BAOH125 | BQ59: STD | BR59: Standard
B60: OK | D60: CREATE | E60: BIL-1007994 | F60: TESTME-FR03319FR-BAOH12501-GUAD> Construction GS à Bois-Sec [3319_BAOH12501] | G60: TESTME-FR03319FR-BAOH12501-GUAD> Construction GS à Bois-Sec [3319_BAOH12501] | H60: DRAFT | I60: EGIS BATIMENTS ILE DE FRANCE | J60: EGIS BATIMENTS ILE DE FRANCE | K60: SL-Buildings-CC-12-IDMI-01-Ile de France-BU-FR03305FR_EGIS BAT IDF | L60: SL-Buildings-CC-12-IDMI-01-Ile de France-BU-FR03305FR_EGIS BAT IDF | M60: EGIS BATIMENTS ILE DE FRANCE Billable E&SC Small Project | N60: EGIS BATIMENTS ILE DE FRANCE Billable E&SC Small Project | V60: EUR | X60: Corporate | Y60: T | Z60: FALSE | AA60: FALSE | AB60: TRUE | AC60: TRUE | AS60: Sebastien.PLICHON@egis-group.com | AT60: RBLD | AU60: 43346 | BN60: 46112 | BO60: 43346 | BP60: BAOH125 | BQ60: STD | BR60: Standard
B61: OK | D61: CREATE | E61: BIL-1007994 | F61: TESTME-FR03319FR-BAOH12501-GUAD> Construction GS à Bois-Sec [3319_BAOH12501] | G61: TESTME-FR03319FR-BAOH12501-GUAD> Construction GS à Bois-Sec [3319_BAOH12501] | H61: DRAFT | I61: EGIS BATIMENTS ILE DE FRANCE | J61: EGIS BATIMENTS ILE DE FRANCE | K61: SL-Buildings-CC-12-IDMI-01-Ile de France-BU-FR03305FR_EGIS BAT IDF | L61: SL-Buildings-CC-12-IDMI-01-Ile de France-BU-FR03305FR_EGIS BAT IDF | M61: EGIS BATIMENTS ILE DE FRANCE Billable E&SC Small Project | N61: EGIS BATIMENTS ILE DE FRANCE Billable E&SC Small Project | V61: EUR | X61: Corporate | Y61: T | Z61: FALSE | AA61: FALSE | AB61: TRUE | AC61: TRUE | AS61: Cedric.ARNAUD@egis-group.com | AT61: Project Sponsor / RBLD Delegate | AU61: 45658 | BN61: 46112 | BO61: 43346 | BP61: BAOH125 | BQ61: STD | BR61: Standard
B62: OK | D62: CREATE | E62: BIL-1007994 | F62: TESTME-FR03319FR-BAOH12501-GUAD> Construction GS à Bois-Sec [3319_BAOH12501] | G62: TESTME-FR03319FR-BAOH12501-GUAD> Construction GS à Bois-Sec [3319_BAOH12501] | H62: DRAFT | I62: EGIS BATIMENTS ILE DE FRANCE | J62: EGIS BATIMENTS ILE DE FRANCE | K62: SL-Buildings-CC-12-IDMI-01-Ile de France-BU-FR03305FR_EGIS BAT IDF | L62: SL-Buildings-CC-12-IDMI-01-Ile de France-BU-FR03305FR_EGIS BAT IDF | M62: EGIS BATIMENTS ILE DE FRANCE Billable E&SC Small Project | N62: EGIS BATIMENTS ILE DE FRANCE Billable E&SC Small Project | V62: EUR | X62: Corporate | Y62: T | Z62: FALSE | AA62: FALSE | AB62: TRUE | AC62: TRUE | AS62: Cedric.ARNAUD@egis-group.com | AT62: Project Manager | AU62: 45658 | BN62: 46112 | BO62: 43346 | BP62: BAOH125 | BQ62: STD | BR62: Standard
E63: FR03319FR-BATA78801 | F63: GUAD>50 LGMTS MARLY STE ANNE [3319_BATA78801] | H63: ACTIVE | I63: EGIS BATIMENTS ANTILLES GUYANE | K63: SL-Buildings-CC-12-ANTI-01-Antilles Guyane-BU-FR03319FR_EGIS BAT ANT GUY | M63: EGIS BATIMENTS ANTILLES GUYANE Billable E&SC Small Project | V63: EUR | X63: Corporate | Y63: T | Z63: FALSE | AA63: FALSE | AB63: TRUE | AC63: TRUE | AD63: P01 - Phase Offre | AE63: P01 | AF63: FR03319FR-BATA78801 | AG63: FINANCIAL | BN63: 46386 | BO63: 45020 | BP63: BATA788 | BQ63: STD | BR63: Standard | CG63: 45657 | CH63: P01 | CI63: 45020 | CJ63: PJF_TASKS | CK63: FINANCIAL
E64: FR03319FR-BATA78801 | F64: GUAD>50 LGMTS MARLY STE ANNE [3319_BATA78801] | H64: ACTIVE | I64: EGIS BATIMENTS ANTILLES GUYANE | K64: SL-Buildings-CC-12-ANTI-01-Antilles Guyane-BU-FR03319FR_EGIS BAT ANT GUY | M64: EGIS BATIMENTS ANTILLES GUYANE Billable E&SC Small Project | V64: EUR | X64: Corporate | Y64: T | Z64: FALSE | AA64: FALSE | AB64: TRUE | AC64: TRUE | AD64: E - Etudes | AE64: P02 | AF64: FR03319FR-BATA78801 | AG64: FINANCIAL | BN64: 46386 | BO64: 45020 | BP64: BATA788 | BQ64: STD | BR64: Standard | CG64: 46386 | CH64: P02 | CI64: 45020 | CJ64: PJF_TASKS | CK64: FINANCIAL
E65: FR03319FR-BATA78801 | F65: GUAD>50 LGMTS MARLY STE ANNE [3319_BATA78801] | H65: ACTIVE | I65: EGIS BATIMENTS ANTILLES GUYANE | K65: SL-Buildings-CC-12-ANTI-01-Antilles Guyane-BU-FR03319FR_EGIS BAT ANT GUY | M65: EGIS BATIMENTS ANTILLES GUYANE Billable E&SC Small Project | V65: EUR | X65: Corporate | Y65: T | Z65: FALSE | AA65: FALSE | AB65: TRUE | AC65: TRUE | AD65: T - Travaux | AE65: P03 | AF65: FR03319FR-BATA78801 | AG65: FINANCIAL | BN65: 46386 | BO65: 45020 | BP65: BATA788 | BQ65: STD | BR65: Standard | CG65: 46386 | CH65: P03 | CI65: 45020 | CJ65: PJF_TASKS | CK65: FINANCIAL
E66: FR03319FR-BATA78801 | F66: GUAD>50 LGMTS MARLY STE ANNE [3319_BATA78801] | H66: ACTIVE | I66: EGIS BATIMENTS ANTILLES GUYANE | K66: SL-Buildings-CC-12-ANTI-01-Antilles Guyane-BU-FR03319FR_EGIS BAT ANT GUY | M66: EGIS BATIMENTS ANTILLES GUYANE Billable E&SC Small Project | V66: EUR | X66: Corporate | Y66: T | Z66: FALSE | AA66: FALSE | AB66: TRUE | AC66: TRUE | AD66: Facturation Milestone Oracle 2025 | AE66: P97 | AF66: FR03319FR-BATA78801 | AG66: FINANCIAL | BN66: 46386 | BO66: 45020 | BP66: BATA788 | BQ66: STD | BR66: Standard | CG66: 46386 | CH66: P97 | CI66: 45020 | CJ66: PJF_TASKS | CK66: FINANCIAL
E67: FR03319FR-BATA78801 | F67: GUAD>50 LGMTS MARLY STE ANNE [3319_BATA78801] | H67: ACTIVE | I67: EGIS BATIMENTS ANTILLES GUYANE | K67: SL-Buildings-CC-12-ANTI-01-Antilles Guyane-BU-FR03319FR_EGIS BAT ANT GUY | M67: EGIS BATIMENTS ANTILLES GUYANE Billable E&SC Small Project | V67: EUR | X67: Corporate | Y67: T | Z67: FALSE | AA67: FALSE | AB67: TRUE | AC67: TRUE | AV67: Project Classification | AW67: Client Project | BN67: 46386 | BO67: 45020 | BP67: BATA788 | BQ67: STD | BR67: Standard
E68: FR03319FR-BATA78801 | F68: GUAD>50 LGMTS MARLY STE ANNE [3319_BATA78801] | H68: ACTIVE | I68: EGIS BATIMENTS ANTILLES GUYANE | K68: SL-Buildings-CC-12-ANTI-01-Antilles Guyane-BU-FR03319FR_EGIS BAT ANT GUY | M68: EGIS BATIMENTS ANTILLES GUYANE Billable E&SC Small Project | V68: EUR | X68: Corporate | Y68: T | Z68: FALSE | AA68: FALSE | AB68: TRUE | AC68: TRUE | AS68: Elie.ELIAS@egis-group.com | AT68: Project Manager | AU68: 45020 | BN68: 46386 | BO68: 45020 | BP68: BATA788 | BQ68: STD | BR68: Standard
E69: FR03319FR-BATA78801 | F69: GUAD>50 LGMTS MARLY STE ANNE [3319_BATA78801] | H69: ACTIVE | I69: EGIS BATIMENTS ANTILLES GUYANE | K69: SL-Buildings-CC-12-ANTI-01-Antilles Guyane-BU-FR03319FR_EGIS BAT ANT GUY | M69: EGIS BATIMENTS ANTILLES GUYANE Billable E&SC Small Project | V69: EUR | X69: Corporate | Y69: T | Z69: FALSE | AA69: FALSE | AB69: TRUE | AC69: TRUE | AS69: Rokhaya.NDIAYE@egis-group.com | AT69: Financial Controller | AU69: 45020 | BN69: 46386 | BO69: 45020 | BP69: BATA788 | BQ69: STD | BR69: Standard
E70: FR03319FR-BATA78801 | F70: GUAD>50 LGMTS MARLY STE ANNE [3319_BATA78801] | H70: ACTIVE | I70: EGIS BATIMENTS ANTILLES GUYANE | K70: SL-Buildings-CC-12-ANTI-01-Antilles Guyane-BU-FR03319FR_EGIS BAT ANT GUY | M70: EGIS BATIMENTS ANTILLES GUYANE Billable E&SC Small Project | V70: EUR | X70: Corporate | Y70: T | Z70: FALSE | AA70: FALSE | AB70: TRUE | AC70: TRUE | AS70: Sebastien.PLICHON@egis-group.com | AT70: RBLD | AU70: 45020 | BN70: 46386 | BO70: 45020 | BP70: BATA788 | BQ70: STD | BR70: Standard
E71: FR03319FR-BATA78801 | F71: GUAD>50 LGMTS MARLY STE ANNE [3319_BATA78801] | H71: ACTIVE | I71: EGIS BATIMENTS ANTILLES GUYANE | K71: SL-Buildings-CC-12-ANTI-01-Antilles Guyane-BU-FR03319FR_EGIS BAT ANT GUY | M71: EGIS BATIMENTS ANTILLES GUYANE Billable E&SC Small Project | V71: EUR | X71: Corporate | Y71: T | Z71: FALSE | AA71: FALSE | AB71: TRUE | AC71: TRUE | AS71: Cedric.ARNAUD@egis-group.com | AT71: Project Sponsor / RBLD Delegate | AU71: 45658 | BN71: 46386 | BO71: 45020 | BP71: BATA788 | BQ71: STD | BR71: Standard
E72: FR03319FR-BATA78801 | F72: GUAD>50 LGMTS MARLY STE ANNE [3319_BATA78801] | H72: ACTIVE | I72: EGIS BATIMENTS ANTILLES GUYANE | K72: SL-Buildings-CC-12-ANTI-01-Antilles Guyane-BU-FR03319FR_EGIS BAT ANT GUY | M72: EGIS BATIMENTS ANTILLES GUYANE Billable E&SC Small Project | V72: EUR | X72: Corporate | Y72: T | Z72: FALSE | AA72: FALSE | AB72: TRUE | AC72: TRUE | AS72: Cedric.ARNAUD@egis-group.com | AT72: Project Manager | AU72: 45658 | BN72: 46386 | BO72: 45020 | BP72: BATA788 | BQ72: STD | BR72: Standard
E73: FR03319FR-BARF62701 | F73: GUAD>AMO EQUIPEMENTS CHU [3319_BARF62701] | H73: ACTIVE | I73: EGIS BATIMENTS ANTILLES GUYANE | K73: SL-Buildings-CC-12-ANTI-01-Antilles Guyane-BU-FR03319FR_EGIS BAT ANT GUY | M73: EGIS BATIMENTS ANTILLES GUYANE Billable E&SC Small Project | V73: EUR | X73: Corporate | Y73: T | Z73: FALSE | AA73: FALSE | AB73: TRUE | AC73: TRUE | AD73: P01 - Offre | AE73: P01 | AF73: FR03319FR-BARF62701 | AG73: FINANCIAL | BN73: 46295 | BO73: 44467 | BP73: BARF627 | BQ73: STD | BR73: Standard | CG73: 45657 | CH73: P01 | CI73: 44467 | CJ73: PJF_TASKS | CK73: FINANCIAL
E74: FR03319FR-BARF62701 | F74: GUAD>AMO EQUIPEMENTS CHU [3319_BARF62701] | H74: ACTIVE | I74: EGIS BATIMENTS ANTILLES GUYANE | K74: SL-Buildings-CC-12-ANTI-01-Antilles Guyane-BU-FR03319FR_EGIS BAT ANT GUY | M74: EGIS BATIMENTS ANTILLES GUYANE Billable E&SC Small Project | V74: EUR | X74: Corporate | Y74: T | Z74: FALSE | AA74: FALSE | AB74: TRUE | AC74: TRUE | AD74: P02 - Phase 02 | AE74: P02 | AF74: FR03319FR-BARF62701 | AG74: FINANCIAL | BN74: 46295 | BO74: 44467 | BP74: BARF627 | BQ74: STD | BR74: Standard | CG74: 46295 | CH74: P02 | CI74: 44467 | CJ74: PJF_TASKS | CK74: FINANCIAL
E75: FR03319FR-BARF62701 | F75: GUAD>AMO EQUIPEMENTS CHU [3319_BARF62701] | H75: ACTIVE | I75: EGIS BATIMENTS ANTILLES GUYANE | K75: SL-Buildings-CC-12-ANTI-01-Antilles Guyane-BU-FR03319FR_EGIS BAT ANT GUY | M75: EGIS BATIMENTS ANTILLES GUYANE Billable E&SC Small Project | V75: EUR | X75: Corporate | Y75: T | Z75: FALSE | AA75: FALSE | AB75: TRUE | AC75: TRUE | AD75: Facturation Milestone Oracle 2025 | AE75: P97 | AF75: FR03319FR-BARF62701 | AG75: FINANCIAL | BN75: 46295 | BO75: 44467 | BP75: BARF627 | BQ75: STD | BR75: Standard | CG75: 46295 | CH75: P97 | CI75: 44467 | CJ75: PJF_TASKS | CK75: FINANCIAL
E76: FR03319FR-BARF62701 | F76: GUAD>AMO EQUIPEMENTS CHU [3319_BARF62701] | H76: ACTIVE | I76: EGIS BATIMENTS ANTILLES GUYANE | K76: SL-Buildings-CC-12-ANTI-01-Antilles Guyane-BU-FR03319FR_EGIS BAT ANT GUY | M76: EGIS BATIMENTS ANTILLES GUYANE Billable E&SC Small Project | V76: EUR | X76: Corporate | Y76: T | Z76: FALSE | AA76: FALSE | AB76: TRUE | AC76: TRUE | AV76: Project Classification | AW76: Client Project | BN76: 46295 | BO76: 44467 | BP76: BARF627 | BQ76: STD | BR76: Standard
E77: FR03319FR-BARF62701 | F77: GUAD>AMO EQUIPEMENTS CHU [3319_BARF62701] | H77: ACTIVE | I77: EGIS BATIMENTS ANTILLES GUYANE | K77: SL-Buildings-CC-12-ANTI-01-Antilles Guyane-BU-FR03319FR_EGIS BAT ANT GUY | M77: EGIS BATIMENTS ANTILLES GUYANE Billable E&SC Small Project | V77: EUR | X77: Corporate | Y77: T | Z77: FALSE | AA77: FALSE | AB77: TRUE | AC77: TRUE | AS77: Regis.AUBERT@egis-group.com | AT77: Project Manager | AU77: 44502 | BN77: 46295 | BO77: 44467 | BP77: BARF627 | BQ77: STD | BR77: Standard
E78: FR03319FR-BARF62701 | F78: GUAD>AMO EQUIPEMENTS CHU [3319_BARF62701] | H78: ACTIVE | I78: EGIS BATIMENTS ANTILLES GUYANE | K78: SL-Buildings-CC-12-ANTI-01-Antilles Guyane-BU-FR03319FR_EGIS BAT ANT GUY | M78: EGIS BATIMENTS ANTILLES GUYANE Billable E&SC Small Project | V78: EUR | X78: Corporate | Y78: T | Z78: FALSE | AA78: FALSE | AB78: TRUE | AC78: TRUE | AS78: Rokhaya.NDIAYE@egis-group.com | AT78: Financial Controller | AU78: 44467 | BN78: 46295 | BO78: 44467 | BP78: BARF627 | BQ78: STD | BR78: Standard
E79: FR03319FR-BARF62701 | F79: GUAD>AMO EQUIPEMENTS CHU [3319_BARF62701] | H79: ACTIVE | I79: EGIS BATIMENTS ANTILLES GUYANE | K79: SL-Buildings-CC-12-ANTI-01-Antilles Guyane-BU-FR03319FR_EGIS BAT ANT GUY | M79: EGIS BATIMENTS ANTILLES GUYANE Billable E&SC Small Project | V79: EUR | X79: Corporate | Y79: T | Z79: FALSE | AA79: FALSE | AB79: TRUE | AC79: TRUE | AS79: Sebastien.PLICHON@egis-group.com | AT79: RBLD | AU79: 44467 | BN79: 46295 | BO79: 44467 | BP79: BARF627 | BQ79: STD | BR79: Standard
E80: FR03319FR-BARF62701 | F80: GUAD>AMO EQUIPEMENTS CHU [3319_BARF62701] | H80: ACTIVE | I80: EGIS BATIMENTS ANTILLES GUYANE | K80: SL-Buildings-CC-12-ANTI-01-Antilles Guyane-BU-FR03319FR_EGIS BAT ANT GUY | M80: EGIS BATIMENTS ANTILLES GUYANE Billable E&SC Small Project | V80: EUR | X80: Corporate | Y80: T | Z80: FALSE | AA80: FALSE | AB80: TRUE | AC80: TRUE | AS80: Cedric.ARNAUD@egis-group.com | AT80: Project Sponsor / RBLD Delegate | AU80: 45658 | BN80: 46295 | BO80: 44467 | BP80: BARF627 | BQ80: STD | BR80: Standard
E81: FR03319FR-BARF62701 | F81: GUAD>AMO EQUIPEMENTS CHU [3319_BARF62701] | H81: ACTIVE | I81: EGIS BATIMENTS ANTILLES GUYANE | K81: SL-Buildings-CC-12-ANTI-01-Antilles Guyane-BU-FR03319FR_EGIS BAT ANT GUY | M81: EGIS BATIMENTS ANTILLES GUYANE Billable E&SC Small Project | V81: EUR | X81: Corporate | Y81: T | Z81: FALSE | AA81: FALSE | AB81: TRUE | AC81: TRUE | AS81: Erwan.BOUKELLA@egis-group.com | AT81: Team Member | AU81: 45718 | BN81: 46295 | BO81: 44467 | BP81: BARF627 | BQ81: STD | BR81: Standard
E82: FR03319FR-BARF62701 | F82: GUAD>AMO EQUIPEMENTS CHU [3319_BARF62701] | H82: ACTIVE | I82: EGIS BATIMENTS ANTILLES GUYANE | K82: SL-Buildings-CC-12-ANTI-01-Antilles Guyane-BU-FR03319FR_EGIS BAT ANT GUY | M82: EGIS BATIMENTS ANTILLES GUYANE Billable E&SC Small Project | V82: EUR | X82: Corporate | Y82: T | Z82: FALSE | AA82: FALSE | AB82: TRUE | AC82: TRUE | AS82: Cedric.ARNAUD@egis-group.com | AT82: Project Manager | AU82: 45658 | BN82: 46295 | BO82: 44467 | BP82: BARF627 | BQ82: STD | BR82: Standard
E83: FR03319FR-BARE57401 | F83: GUAD>ATMO bloc opératoire CH Basse Terre [3319_BARE57401] | H83: ACTIVE | I83: EGIS BATIMENTS ANTILLES GUYANE | K83: SL-Buildings-CC-12-ANTI-01-Antilles Guyane-BU-FR03319FR_EGIS BAT ANT GUY | M83: EGIS BATIMENTS ANTILLES GUYANE Billable E&SC Small Project | V83: EUR | X83: Corporate | Y83: T | Z83: FALSE | AA83: FALSE | AB83: TRUE | AC83: TRUE | AD83: O - Offre | AE83: P01 | AF83: FR03319FR-BARE57401 | AG83: FINANCIAL | BN83: 46203 | BO83: 44410 | BP83: BARE574 | BQ83: STD | BR83: Standard | CG83: 45657 | CH83: P01 | CI83: 44410 | CJ83: PJF_TASKS | CK83: FINANCIAL
E84: FR03319FR-BARE57401 | F84: GUAD>ATMO bloc opératoire CH Basse Terre [3319_BARE57401] | H84: ACTIVE | I84: EGIS BATIMENTS ANTILLES GUYANE | K84: SL-Buildings-CC-12-ANTI-01-Antilles Guyane-BU-FR03319FR_EGIS BAT ANT GUY | M84: EGIS BATIMENTS ANTILLES GUYANE Billable E&SC Small Project | V84: EUR | X84: Corporate | Y84: T | Z84: FALSE | AA84: FALSE | AB84: TRUE | AC84: TRUE | AD84: T - Travaux | AE84: P02 | AF84: FR03319FR-BARE57401 | AG84: FINANCIAL | BN84: 46203 | BO84: 44410 | BP84: BARE574 | BQ84: STD | BR84: Standard | CG84: 46203 | CH84: P02 | CI84: 44410 | CJ84: PJF_TASKS | CK84: FINANCIAL
E85: FR03319FR-BARE57401 | F85: GUAD>ATMO bloc opératoire CH Basse Terre [3319_BARE57401] | H85: ACTIVE | I85: EGIS BATIMENTS ANTILLES GUYANE | K85: SL-Buildings-CC-12-ANTI-01-Antilles Guyane-BU-FR03319FR_EGIS BAT ANT GUY | M85: EGIS BATIMENTS ANTILLES GUYANE Billable E&SC Small Project | V85: EUR | X85: Corporate | Y85: T | Z85: FALSE | AA85: FALSE | AB85: TRUE | AC85: TRUE | AD85: Facturation Milestone Oracle 2025 | AE85: P97 | AF85: FR03319FR-BARE57401 | AG85: FINANCIAL | BN85: 46203 | BO85: 44410 | BP85: BARE574 | BQ85: STD | BR85: Standard | CG85: 46203 | CH85: P97 | CI85: 44410 | CJ85: PJF_TASKS | CK85: FINANCIAL
E86: FR03319FR-BARE57401 | F86: GUAD>ATMO bloc opératoire CH Basse Terre [3319_BARE57401] | H86: ACTIVE | I86: EGIS BATIMENTS ANTILLES GUYANE | K86: SL-Buildings-CC-12-ANTI-01-Antilles Guyane-BU-FR03319FR_EGIS BAT ANT GUY | M86: EGIS BATIMENTS ANTILLES GUYANE Billable E&SC Small Project | V86: EUR | X86: Corporate | Y86: T | Z86: FALSE | AA86: FALSE | AB86: TRUE | AC86: TRUE | AV86: Project Classification | AW86: Client Project | BN86: 46203 | BO86: 44410 | BP86: BARE574 | BQ86: STD | BR86: Standard
E87: FR03319FR-BARE57401 | F87: GUAD>ATMO bloc opératoire CH Basse Terre [3319_BARE57401] | H87: ACTIVE | I87: EGIS BATIMENTS ANTILLES GUYANE | K87: SL-Buildings-CC-12-ANTI-01-Antilles Guyane-BU-FR03319FR_EGIS BAT ANT GUY | M87: EGIS BATIMENTS ANTILLES GUYANE Billable E&SC Small Project | V87: EUR | X87: Corporate | Y87: T | Z87: FALSE | AA87: FALSE | AB87: TRUE | AC87: TRUE | AS87: Regis.AUBERT@egis-group.com | AT87: Project Manager | AU87: 44502 | BN87: 46203 | BO87: 44410 | BP87: BARE574 | BQ87: STD | BR87: Standard
E88: FR03319FR-BARE57401 | F88: GUAD>ATMO bloc opératoire CH Basse Terre [3319_BARE57401] | H88: ACTIVE | I88: EGIS BATIMENTS ANTILLES GUYANE | K88: SL-Buildings-CC-12-ANTI-01-Antilles Guyane-BU-FR03319FR_EGIS BAT ANT GUY | M88: EGIS BATIMENTS ANTILLES GUYANE Billable E&SC Small Project | V88: EUR | X88: Corporate | Y88: T | Z88: FALSE | AA88: FALSE | AB88: TRUE | AC88: TRUE | AS88: Rokhaya.NDIAYE@egis-group.com | AT88: Financial Controller | AU88: 44410 | BN88: 46203 | BO88: 44410 | BP88: BARE574 | BQ88: STD | BR88: Standard
E89: FR03319FR-BARE57401 | F89: GUAD>ATMO bloc opératoire CH Basse Terre [3319_BARE57401] | H89: ACTIVE | I89: EGIS BATIMENTS ANTILLES GUYANE | K89: SL-Buildings-CC-12-ANTI-01-Antilles Guyane-BU-FR03319FR_EGIS BAT ANT GUY | M89: EGIS BATIMENTS ANTILLES GUYANE Billable E&SC Small Project | V89: EUR | X89: Corporate | Y89: T | Z89: FALSE | AA89: FALSE | AB89: TRUE | AC89: TRUE | AS89: Sebastien.PLICHON@egis-group.com | AT89: RBLD | AU89: 44410 | BN89: 46203 | BO89: 44410 | BP89: BARE574 | BQ89: STD | BR89: Standard
E90: FR03319FR-BARE57401 | F90: GUAD>ATMO bloc opératoire CH Basse Terre [3319_BARE57401] | H90: ACTIVE | I90: EGIS BATIMENTS ANTILLES GUYANE | K90: SL-Buildings-CC-12-ANTI-01-Antilles Guyane-BU-FR03319FR_EGIS BAT ANT GUY | M90: EGIS BATIMENTS ANTILLES GUYANE Billable E&SC Small Project | V90: EUR | X90: Corporate | Y90: T | Z90: FALSE | AA90: FALSE | AB90: TRUE | AC90: TRUE | AS90: Cedric.ARNAUD@egis-group.com | AT90: Project Sponsor / RBLD Delegate | AU90: 45658 | BN90: 46203 | BO90: 44410 | BP90: BARE574 | BQ90: STD | BR90: Standard
E91: FR03319FR-BARE57401 | F91: GUAD>ATMO bloc opératoire CH Basse Terre [3319_BARE57401] | H91: ACTIVE | I91: EGIS BATIMENTS ANTILLES GUYANE | K91: SL-Buildings-CC-12-ANTI-01-Antilles Guyane-BU-FR03319FR_EGIS BAT ANT GUY | M91: EGIS BATIMENTS ANTILLES GUYANE Billable E&SC Small Project | V91: EUR | X91: Corporate | Y91: T | Z91: FALSE | AA91: FALSE | AB91: TRUE | AC91: TRUE | AS91: Julien.LECORNET@egis-group.com | AT91: Project Manager | AU91: 45727 | BN91: 46203 | BO91: 44410 | BP91: BARE574 | BQ91: STD | BR91: Standard
E92: FR03319FR-BARE57401 | F92: GUAD>ATMO bloc opératoire CH Basse Terre [3319_BARE57401] | H92: ACTIVE | I92: EGIS BATIMENTS ANTILLES GUYANE | K92: SL-Buildings-CC-12-ANTI-01-Antilles Guyane-BU-FR03319FR_EGIS BAT ANT GUY | M92: EGIS BATIMENTS ANTILLES GUYANE Billable E&SC Small Project | V92: EUR | X92: Corporate | Y92: T | Z92: FALSE | AA92: FALSE | AB92: TRUE | AC92: TRUE | AS92: Cedric.ARNAUD@egis-group.com | AT92: Project Manager | AU92: 45658 | BN92: 46203 | BO92: 44410 | BP92: BARE574 | BQ92: STD | BR92: Standard
E93: FR03319FR-BANL07401 | F93: GUAD>Habitation des Jésuites [3319_BANL07401] | H93: ACTIVE | I93: EGIS BATIMENTS ANTILLES GUYANE | K93: SL-Buildings-CC-12-ANTI-01-Antilles Guyane-BU-FR03319FR_EGIS BAT ANT GUY | M93: EGIS BATIMENTS ANTILLES GUYANE Billable E&SC Small Project | V93: EUR | X93: Corporate | Y93: T | Z93: FALSE | AA93: FALSE | AB93: TRUE | AC93: TRUE | AD93: P01 - Concours | AE93: P01 | AF93: FR03319FR-BANL07401 | AG93: FINANCIAL | BN93: 46386 | BO93: 43152 | BP93: BANL074 | BQ93: SCDP | BR93: Subcontractor Direct Payment | CG93: 45657 | CH93: P01 | CI93: 43152 | CJ93: PJF_TASKS | CK93: FINANCIAL
E94: FR03319FR-BANL07401 | F94: GUAD>Habitation des Jésuites [3319_BANL07401] | H94: ACTIVE | I94: EGIS BATIMENTS ANTILLES GUYANE | K94: SL-Buildings-CC-12-ANTI-01-Antilles Guyane-BU-FR03319FR_EGIS BAT ANT GUY | M94: EGIS BATIMENTS ANTILLES GUYANE Billable E&SC Small Project | V94: EUR | X94: Corporate | Y94: T | Z94: FALSE | AA94: FALSE | AB94: TRUE | AC94: TRUE | AD94: E - Etudes | AE94: P02 | AF94: FR03319FR-BANL07401 | AG94: FINANCIAL | BN94: 46386 | BO94: 43152 | BP94: BANL074 | BQ94: SCDP | BR94: Subcontractor Direct Payment | CG94: 46386 | CH94: P02 | CI94: 43152 | CJ94: PJF_TASKS | CK94: FINANCIAL
E95: FR03319FR-BANL07401 | F95: GUAD>Habitation des Jésuites [3319_BANL07401] | H95: ACTIVE | I95: EGIS BATIMENTS ANTILLES GUYANE | K95: SL-Buildings-CC-12-ANTI-01-Antilles Guyane-BU-FR03319FR_EGIS BAT ANT GUY | M95: EGIS BATIMENTS ANTILLES GUYANE Billable E&SC Small Project | V95: EUR | X95: Corporate | Y95: T | Z95: FALSE | AA95: FALSE | AB95: TRUE | AC95: TRUE | AD95: T - Travaux | AE95: P03 | AF95: FR03319FR-BANL07401 | AG95: FINANCIAL | BN95: 46386 | BO95: 43152 | BP95: BANL074 | BQ95: SCDP | BR95: Subcontractor Direct Payment | CG95: 46386 | CH95: P03 | CI95: 43152 | CJ95: PJF_TASKS | CK95: FINANCIAL
E96: FR03319FR-BANL07401 | F96: GUAD>Habitation des Jésuites [3319_BANL07401] | H96: ACTIVE | I96: EGIS BATIMENTS ANTILLES GUYANE | K96: SL-Buildings-CC-12-ANTI-01-Antilles Guyane-BU-FR03319FR_EGIS BAT ANT GUY | M96: EGIS BATIMENTS ANTILLES GUYANE Billable E&SC Small Project | V96: EUR | X96: Corporate | Y96: T | Z96: FALSE | AA96: FALSE | AB96: TRUE | AC96: TRUE | AD96: Facturation Milestone Oracle 2025 | AE96: P97 | AF96: FR03319FR-BANL07401 | AG96: FINANCIAL | BN96: 46386 | BO96: 43152 | BP96: BANL074 | BQ96: SCDP | BR96: Subcontractor Direct Payment | CG96: 46386 | CH96: P97 | CI96: 43152 | CJ96: PJF_TASKS | CK96: FINANCIAL
E97: FR03319FR-BANL07401 | F97: GUAD>Habitation des Jésuites [3319_BANL07401] | H97: ACTIVE | I97: EGIS BATIMENTS ANTILLES GUYANE | K97: SL-Buildings-CC-12-ANTI-01-Antilles Guyane-BU-FR03319FR_EGIS BAT ANT GUY | M97: EGIS BATIMENTS ANTILLES GUYANE Billable E&SC Small Project | V97: EUR | X97: Corporate | Y97: T | Z97: FALSE | AA97: FALSE | AB97: TRUE | AC97: TRUE | AV97: Project Classification | AW97: Client Project | BN97: 46386 | BO97: 43152 | BP97: BANL074 | BQ97: SCDP | BR97: Subcontractor Direct Payment
E98: FR03319FR-BANL07401 | F98: GUAD>Habitation des Jésuites [3319_BANL07401] | H98: ACTIVE | I98: EGIS BATIMENTS ANTILLES GUYANE | K98: SL-Buildings-CC-12-ANTI-01-Antilles Guyane-BU-FR03319FR_EGIS BAT ANT GUY | M98: EGIS BATIMENTS ANTILLES GUYANE Billable E&SC Small Project | V98: EUR | X98: Corporate | Y98: T | Z98: FALSE | AA98: FALSE | AB98: TRUE | AC98: TRUE | AS98: Regis.AUBERT@egis-group.com | AT98: Project Manager | AU98: 44502 | BN98: 46386 | BO98: 43152 | BP98: BANL074 | BQ98: SCDP | BR98: Subcontractor Direct Payment
E99: FR03319FR-BANL07401 | F99: GUAD>Habitation des Jésuites [3319_BANL07401] | H99: ACTIVE | I99: EGIS BATIMENTS ANTILLES GUYANE | K99: SL-Buildings-CC-12-ANTI-01-Antilles Guyane-BU-FR03319FR_EGIS BAT ANT GUY | M99: EGIS BATIMENTS ANTILLES GUYANE Billable E&SC Small Project | V99: EUR | X99: Corporate | Y99: T | Z99: FALSE | AA99: FALSE | AB99: TRUE | AC99: TRUE | AS99: Rokhaya.NDIAYE@egis-group.com | AT99: Financial Controller | AU99: 43152 | BN99: 46386 | BO99: 43152 | BP99: BANL074 | BQ99: SCDP | BR99: Subcontractor Direct Payment
E100: FR03319FR-BANL07401 | F100: GUAD>Habitation des Jésuites [3319_BANL07401] | H100: ACTIVE | I100: EGIS BATIMENTS ANTILLES GUYANE | K100: SL-Buildings-CC-12-ANTI-01-Antilles Guyane-BU-FR03319FR_EGIS BAT ANT GUY | M100: EGIS BATIMENTS ANTILLES GUYANE Billable E&SC Small Project | V100: EUR | X100: Corporate | Y100: T | Z100: FALSE | AA100: FALSE | AB100: TRUE | AC100: TRUE | AS100: Cedric.ARNAUD@egis-group.com | AT100: Project Sponsor / RBLD Delegate | AU100: 45352 | BN100: 46386 | BO100: 43152 | BP100: BANL074 | BQ100: SCDP | BR100: Subcontractor Direct Payment
...

Sheet Templateold
A1: Columns | B1: Status | C1: Error Message | D1: Action | E1: ProjectNumber | F1: ProjectName | H1: ProjectStatusCode | I1: LegalEntityName | K1: OwningOrganizationName | M1: SourceTemplateName | O1: AllowCapitalizedInterestFlag | P1: AssetAllocationMethodCode | Q1: BurdenScheduleName | R1: BurdenScheduleFixedDate | S1: CapitalEventProcessingMethodCode | T1: CIntRateSchName | U1: CIntStopDate | V1: ProjectCurrencyCode | W1: CurrencyConvDate | X1: CurrencyConvRateType | Y1: CurrencyConvDateTypeCode | Z1: IncludeNotesInKPINotificationsFlag | AA1: KPINotificationEnabledFlag | AB1: PlanningProjectFlag | AC1: AllowCrossChargeFlag | AD1: TaskName | AE1: ExternalTaskId | AF1: ExternalParentTaskId | AG1: ElementType | AH1: ExpenseResourceName | AI1: LaborResourceName | AJ1: LaborResourceEmail | AK1: LaborPrimaryResource | AL1: RuleNumber | AM1: Billable | AN1: Chargeable | AO1: ExternalPredecessorTaskId | AP1: ExternalTaskId | AQ1: Lag | AR1: DependencyType | AS1: PersonEmail | AT1: ProjectRole | AU1: StartDate | AV1: ClassCategory | AW1: ClassCode | AX1: CodePercentage | AY1: OpportunityNumber | AZ1: OpportunityName | BA1: OpportunityAmount | BB1: OpportunityCustomerName | BC1: OpportunityCustomerNumber | BD1: OpportunityStatus | BE1: OpportunityWinConfPercent | BF1: PartyName | BG1: PartyNumber | BH1: BusinessUnitName | BI1: CategoryName | BJ1: DatatypeCode | BK1: FileContents | BL1: Title | BM1: FileName | BN1: ProjectEndDate | BO1: ProjectStartDate | BP1: crmNumber | BQ1: supplierPaymentProcess | BR1: supplierPaymentProcess_Display | BS1: domain | BT1: marketSegment | BU1: domain_Display | BV1: marketSegment_Display | BW1: specificities | BX1: specificities_Display | BY1: fundingSource | BZ1: fundingSource_Display | CA1: subFundingSource | CB1: subFundingSource_Display | CC1: procedures | CD1: procedures_Display | CE1: countryDestinationView | CF1: stateOrProvince | CG1: TaskFinishDate | CH1: TaskNumber | CI1: TaskStartDate | CJ1: ObjectType | CK1: ElementType
A2: Status | B2: Technical | C2: Technical | D2: Action | E2: Header | F2: Header | H2: Header | I2: Header | K2: Header | M2: Header | O2: Header | P2: Header | Q2: Header | R2: Header | S2: Header | T2: Header | U2: Header | V2: Header | W2: Header | X2: Header | Y2: Header | Z2: Header | AA2: Header | AB2: Header | AC2: Header | AD2: Tasks | AE2: Tasks | AF2: Tasks | AG2: Tasks | AH2: ExpenseResourceAssignments | AI2: LaborResourceAssignments | AJ2: LaborResourceAssignments | AK2: LaborResourceAssignments | AL2: TaskTransactionControls | AM2: TaskTransactionControls | AN2: TaskTransactionControls | AO2: TaskDependencies | AP2: TaskDependencies | AQ2: TaskDependencies | AR2: TaskDependencies | AS2: ProjectTeamMembers | AT2: ProjectTeamMembers | AU2: ProjectTeamMembers | AV2: ProjectClassifications | AW2: ProjectClassifications | AX2: ProjectClassifications | AY2: ProjectOpportunities | AZ2: ProjectOpportunities | BA2: ProjectOpportunities | BB2: ProjectOpportunities | BC2: ProjectOpportunities | BD2: ProjectOpportunities | BE2: ProjectOpportunities | BF2: ProjectCustomers | BG2: ProjectCustomers | BH2: ProviderBusinessUnits | BI2: Attachments | BJ2: Attachments | BK2: Attachments | BL2: Attachments | BM2: Attachments | BN2: Header | BO2: Header | BP2: Header | BQ2: Header | BR2: Header | BS2: Header | BT2: Header | BU2: Header | BV2: Header | BW2: Header | BX2: Header | BY2: Header | BZ2: Header | CA2: Header | CB2: Header | CC2: Header | CD2: Header | CE2: Header | CF2: Header | CG2: Tasks | CH2: Tasks | CI2: Tasks | CJ2: Tasks | CK2: Tasks
A3: Type | B3: Standard | C3: Standard | D3: Standard | E3: Standard | F3: Standard | H3: Standard | I3: Standard | K3: Standard | M3: Standard | O3: Standard | P3: Standard | Q3: Standard | R3: Standard | S3: Standard | T3: Standard | U3: Standard | V3: Standard | W3: Standard | X3: Standard | Y3: Standard | Z3: Standard | AA3: Standard | AB3: Standard | AC3: Standard | AD3: Standard | AE3: Standard | AF3: Standard | AG3: Standard | AH3: Standard | AI3: Standard | AJ3: Standard | AK3: Standard | AL3: Standard | AM3: Standard | AN3: Standard | AO3: Standard | AP3: Standard | AQ3: Standard | AR3: Standard | AS3: Standard | AT3: Standard | AU3: Standard | AV3: Standard | AW3: Standard | AX3: Standard | AY3: Standard | AZ3: Standard | BA3: Standard | BB3: Standard | BC3: Standard | BD3: Standard | BE3: Standard | BF3: Standard | BG3: Standard | BH3: Standard | BI3: Standard | BJ3: Standard | BK3: Standard | BL3: Standard | BM3: Standard | BN3: Standard | BO3: Standard | BP3: ProjectDFF | BQ3: ProjectDFF | BR3: ProjectDFF | BS3: ProjectDFF | BT3: ProjectDFF | BU3: ProjectDFF | BV3: ProjectDFF | BW3: ProjectDFF | BX3: ProjectDFF | BY3: ProjectDFF | BZ3: ProjectDFF | CA3: ProjectDFF | CB3: ProjectDFF | CC3: ProjectDFF | CD3: ProjectDFF | CE3: ProjectDFF | CF3: ProjectDFF | CG3: Standard | CH3: Standard | CI3: Standard | CJ3: TasksDFF | CK3: TasksDFF
A4: Custom Labels | B4: Status | C4: Error Message | D4: Action | E4: Project Number | F4: Project Name | G4: ProjectName to migrate | H4: Project Status Code | I4: Legal Entity Name | J4: Legal Entity Name to migrate | K4: Owning Organization Name | L4: Owning Organization Name to migrate | M4: Source Template Name | N4: SourceTemplateName to migrate | O4: Allow Capitalized Interest Flag | P4: Asset Allocation Method Code | Q4: Burden Schedule Name | R4: Burden Schedule Fixed Date | S4: Capital Event Processing Method Code | T4: CIntRateSchName | U4: CIntStopDate | V4: Project Currency Code | W4: Currency Conv Date | X4: Currency Conv Rate Type | Y4: Currency Conv Date Type Code | Z4: Include Notes In KPI Notifications Flag | AA4: KPI Notification Enabled Flag | AB4: Planning Project lag | AC4: Allow cross-charge transactions from other business units | AD4: Task Name | AE4: External Task Id | AF4: External Parent Task Id | AG4: Element Type | AH4: Expense Resource Name | AI4: Labor Resource Name | AJ4: Labor Resource Email | AK4: Labor Primary Resource | AL4: Rule Number | AM4: Billable | AN4: Chargeable | AO4: External Predecessor Task Id | AP4: External Task Id | AQ4: Lag | AR4: Dependency Type | AS4: Person Email | AT4: Project Role | AU4: Start Date | AV4: Class Category | AW4: Class Code | AX4: Code Percentage | AY4: Opportunity Number | AZ4: Opportunity Name | BA4: Opportunity Amount | BB4: Opportunity Customer Name | BC4: Opportunity Customer Number | BD4: Opportunity Status | BE4: Opportunity Win Conf Percent | BF4: Party Name | BG4: Party Number | BH4: BusinessUnitName | BI4: Category Name | BJ4: Data type Code | BK4: File Contents | BL4: Title | BM4: File Name | BN4: Project Finish Date | BO4: Project Start Date | CG4: Task Finish Date | CH4: Task Number | CI4: Task Start Date
B5: OK | D5: CREATE | E5: BIL-1007342 | F5: TESTUK1 | G5: ETS-BIL-1007342-TESTUK1 | H5: DRAFT | I5: EGIS UK - CONSULTING AND ENGINEERING LIMITED | J5: =_xlfn.XLOOKUP(I5,LE!A:A,LE!F:F,,1) -> 0 | K5: SL-Nuclear SL-CC-12-NTAI-21-Nuclear Technical Assistance-BU-GB03958GB_EGIS UK | L5: =_xlfn.XLOOKUP(K5,'ORG name (PPM)'!A:A,'ORG name (PPM)'!G:G,,1) -> 0 | M5: EGIS UK - CONSULTING AND ENGINEERING LIMITED Billable | N5: =_xlfn.XLOOKUP(M5,'source template'!A:A,'source template'!I:I,,1) -> 0 | V5: GBP | X5: Corporate | Y5: T | Z5: FALSE | AA5: FALSE | AB5: TRUE | AD5: Tender Costs | AE5: P01 | AG5: FINANCIAL | BN5: 47848 | BO5: 44927 | BP5: ZZZZZ | BQ5: STD | BR5: Standard | CG5: 47848 | CH5: P01 | CI5: 44927 | CJ5: PJF_TASKS | CK5: FINANCIAL
B6: OK | D6: CREATE | E6: BIL-1007342 | F6: TESTUK1 | G6: ETS-BIL-1007342-TESTUK1 | H6: DRAFT | I6: EGIS UK - CONSULTING AND ENGINEERING LIMITED | J6: =_xlfn.XLOOKUP(I6,LE!A:A,LE!F:F,,1) -> 0 | K6: SL-Nuclear SL-CC-12-NTAI-21-Nuclear Technical Assistance-BU-GB03958GB_EGIS UK | L6: =_xlfn.XLOOKUP(K6,'ORG name (PPM)'!A:A,'ORG name (PPM)'!G:G,,1) -> 0 | M6: EGIS UK - CONSULTING AND ENGINEERING LIMITED Billable | N6: =_xlfn.XLOOKUP(M6,'source template'!A:A,'source template'!I:I,,1) -> 0 | V6: GBP | X6: Corporate | Y6: T | Z6: FALSE | AA6: FALSE | AB6: TRUE | AD6: Budget | AE6: P02 | AG6: FINANCIAL | BN6: 47848 | BO6: 44927 | BP6: ZZZZZ | BQ6: STD | BR6: Standard | CG6: 47848 | CH6: P02 | CI6: 44927 | CJ6: PJF_TASKS | CK6: FINANCIAL
B7: OK | D7: CREATE | E7: BIL-1007342 | F7: TESTUK1 | G7: ETS-BIL-1007342-TESTUK1 | H7: DRAFT | I7: EGIS UK - CONSULTING AND ENGINEERING LIMITED | J7: =_xlfn.XLOOKUP(I7,LE!A:A,LE!F:F,,1) -> 0 | K7: SL-Nuclear SL-CC-12-NTAI-21-Nuclear Technical Assistance-BU-GB03958GB_EGIS UK | L7: =_xlfn.XLOOKUP(K7,'ORG name (PPM)'!A:A,'ORG name (PPM)'!G:G,,1) -> 0 | M7: EGIS UK - CONSULTING AND ENGINEERING LIMITED Billable | N7: =_xlfn.XLOOKUP(M7,'source template'!A:A,'source template'!I:I,,1) -> 0 | V7: GBP | X7: Corporate | Y7: T | Z7: FALSE | AA7: FALSE | AB7: TRUE | AD7: Non charegable to client | AE7: P03 | AG7: FINANCIAL | BN7: 47848 | BO7: 44927 | BP7: ZZZZZ | BQ7: STD | BR7: Standard | CG7: 47848 | CH7: P03 | CI7: 44927 | CJ7: PJF_TASKS | CK7: FINANCIAL
B8: OK | D8: CREATE | E8: BIL-1007342 | F8: TESTUK1 | G8: ETS-BIL-1007342-TESTUK1 | H8: DRAFT | I8: EGIS UK - CONSULTING AND ENGINEERING LIMITED | J8: =_xlfn.XLOOKUP(I8,LE!A:A,LE!F:F,,1) -> 0 | K8: SL-Nuclear SL-CC-12-NTAI-21-Nuclear Technical Assistance-BU-GB03958GB_EGIS UK | L8: =_xlfn.XLOOKUP(K8,'ORG name (PPM)'!A:A,'ORG name (PPM)'!G:G,,1) -> 0 | M8: EGIS UK - CONSULTING AND ENGINEERING LIMITED Billable | N8: =_xlfn.XLOOKUP(M8,'source template'!A:A,'source template'!I:I,,1) -> 0 | V8: GBP | X8: Corporate | Y8: T | Z8: FALSE | AA8: FALSE | AB8: TRUE | AD8: 425770 - Egis Structures and Environment - CM | AE8: P04 | AG8: FINANCIAL | BN8: 47848 | BO8: 44927 | BP8: ZZZZZ | BQ8: STD | BR8: Standard | CG8: 47848 | CH8: P04 | CI8: 44927 | CJ8: PJF_TASKS | CK8: FINANCIAL
B9: OK | D9: CREATE | E9: BIL-1007342 | F9: TESTUK1 | G9: ETS-BIL-1007342-TESTUK1 | H9: DRAFT | I9: EGIS UK - CONSULTING AND ENGINEERING LIMITED | J9: =_xlfn.XLOOKUP(I9,LE!A:A,LE!F:F,,1) -> 0 | K9: SL-Nuclear SL-CC-12-NTAI-21-Nuclear Technical Assistance-BU-GB03958GB_EGIS UK | L9: =_xlfn.XLOOKUP(K9,'ORG name (PPM)'!A:A,'ORG name (PPM)'!G:G,,1) -> 0 | M9: EGIS UK - CONSULTING AND ENGINEERING LIMITED Billable | N9: =_xlfn.XLOOKUP(M9,'source template'!A:A,'source template'!I:I,,1) -> 0 | V9: GBP | X9: Corporate | Y9: T | Z9: FALSE | AA9: FALSE | AB9: TRUE | AD9: P05 - Phase 05 | AE9: P05 | AG9: FINANCIAL | BN9: 47848 | BO9: 44927 | BP9: ZZZZZ | BQ9: STD | BR9: Standard | CG9: 47848 | CH9: P05 | CI9: 44927 | CJ9: PJF_TASKS | CK9: FINANCIAL
E10: GB03952GB-IBESDIR1TC | F10: FRA > EGIS Structures and Environment [3952_IBESDIR1TC] | G10: ETS-GB03952GB-IBESDIR1TC-FRA > EGIS Structures and Environment [3952_IBESDIR1TC] | H10: ACTIVE | I10: EGIS TRANSPORT SOLUTIONS LIMITED | J10: =_xlfn.XLOOKUP(I10,LE!A:A,LE!F:F,,1) -> EGIS UK - CONSULTING AND ENGINEERING LIMITED | K10: SL-Advisory Direct-CC-19-AMAN-21-Asset Management Advisory-BU-GB03952GB_ETS | L10: =_xlfn.XLOOKUP(K10,'ORG name (PPM)'!A:A,'ORG name (PPM)'!G:G,,1) -> SL-Advisory Direct-CC-19-AMAN-21-Asset Management Advisory-BU-GB03958GB_EGIS UK | M10: EGIS TRANSPORT SOLUTIONS LIMITED Billable | N10: =_xlfn.XLOOKUP(M10,'source template'!A:A,'source template'!I:I,,1) -> EGIS UK - CONSULTING AND ENGINEERING LIMITED Billable | V10: GBP | X10: Corporate | Y10: T | Z10: FALSE | AA10: FALSE | AB10: TRUE | AS10: Jonathan.ANTHONY@egis-group.com | AT10: Project Manager | AU10: 45716 | BN10: 47848 | BO10: 44927 | BP10: ZZZZZ | BQ10: STD | BR10: Standard
E11: GB03952GB-IBESDIR1TC | F11: FRA > EGIS Structures and Environment [3952_IBESDIR1TC] | G11: GB03952GB-GB03952GB-IBESDIR1TC-FRA > EGIS Structures and Environment [3952_IBESDIR1TC] | H11: ACTIVE | I11: EGIS TRANSPORT SOLUTIONS LIMITED | J11: =_xlfn.XLOOKUP(I11,LE!A:A,LE!F:F,,1) -> EGIS UK - CONSULTING AND ENGINEERING LIMITED | K11: SL-Advisory Direct-CC-19-AMAN-21-Asset Management Advisory-BU-GB03952GB_ETS | L11: =_xlfn.XLOOKUP(K11,'ORG name (PPM)'!A:A,'ORG name (PPM)'!G:G,,1) -> SL-Advisory Direct-CC-19-AMAN-21-Asset Management Advisory-BU-GB03958GB_EGIS UK | M11: EGIS TRANSPORT SOLUTIONS LIMITED Billable | N11: =_xlfn.XLOOKUP(M11,'source template'!A:A,'source template'!I:I,,1) -> EGIS UK - CONSULTING AND ENGINEERING LIMITED Billable | V11: GBP | X11: Corporate | Y11: T | Z11: FALSE | AA11: FALSE | AB11: TRUE | AS11: Joy.WILLIAMS@egis-group.com | AT11: Team Member | AU11: 45790 | BN11: 47848 | BO11: 44927 | BP11: ZZZZZ | BQ11: STD | BR11: Standard
E12: BIL-1007981 | F12: GB03952GB-GB03952GB-PAVSAU1006-SAU > Matarat Asset Management Support [3952_PAVSAU1006] | G12: GB03952GB-PAVSAU1006-SAU > Matarat Asset Management Support [3952_PAVSAU1006] | H12: DRAFT | I12: EGIS UK - CONSULTING AND ENGINEERING LIMITED | J12: =_xlfn.XLOOKUP(I12,LE!A:A,LE!F:F,,1) -> 0 | K12: SL-Advisory Direct-CC-19-AMAN-21-Asset Management Advisory-BU-GB03958GB_EGIS UK | L12: =_xlfn.XLOOKUP(K12,'ORG name (PPM)'!A:A,'ORG name (PPM)'!G:G,,1) -> 0 | M12: EGIS UK - CONSULTING AND ENGINEERING LIMITED Billable | N12: =_xlfn.XLOOKUP(M12,'source template'!A:A,'source template'!I:I,,1) -> 0 | V12: GBP | X12: Corporate | Y12: T | Z12: FALSE | AA12: FALSE | AB12: TRUE | AC12: TRUE | AD12: Tender Costs | AE12: P01 | AG12: FINANCIAL | BN12: 47848 | BO12: 44927 | BP12: 952-000716 | BQ12: STD | BR12: Standard | CG12: 47848 | CH12: P01 | CI12: 44927 | CJ12: PJF_TASKS | CK12: FINANCIAL
E13: CRA-1000030 | F13: Cost Re-Allocation for FR03319FR_EGIS BAT ANT GUY | H13: ACTIVE | I13: EGIS BATIMENTS ANTILLES GUYANE | K13: SL-Shared Services FIN-CC-04-FINA-BL-Accounting BL-BU-FR03319FR_EGIS BAT ANT GUY | M13: EGIS BATIMENTS ANTILLES GUYANE Indirect | V13: EUR | X13: Corporate | Y13: T | Z13: FALSE | AA13: FALSE | AB13: TRUE | AC13: TRUE | AD13: Cost Re-Allocation | AE13: 1 | AF13: CRA-1000030 | AG13: FINANCIAL | BN13: 69763 | BO13: 45292 | BQ13: STD | BR13: Standard | CG13: 69763 | CH13: 1 | CI13: 45292 | CJ13: PJF_TASKS | CK13: FINANCIAL
E14: CRA-1000030 | F14: Cost Re-Allocation for FR03319FR_EGIS BAT ANT GUY | H14: ACTIVE | I14: EGIS BATIMENTS ANTILLES GUYANE | K14: SL-Shared Services FIN-CC-04-FINA-BL-Accounting BL-BU-FR03319FR_EGIS BAT ANT GUY | M14: EGIS BATIMENTS ANTILLES GUYANE Indirect | V14: EUR | X14: Corporate | Y14: T | Z14: FALSE | AA14: FALSE | AB14: TRUE | AC14: TRUE | AV14: Project Classification | AW14: Cost Re-Allocation | BN14: 69763 | BO14: 45292 | BQ14: STD | BR14: Standard
B15: OK | D15: CREATE | E15: BIL-1007983 | F15: TESTME-FR03319FR-4896-30 Logements Siguy [3319_4896] | G15: TESTME--TESTME-FR03319FR-4896-30 Logements Siguy [3319_4896] | H15: DRAFT | I15: EGIS BATIMENTS ILE DE FRANCE | J15: =_xlfn.XLOOKUP(I15,LE!A:A,LE!F:F,,1) -> 0 | K15: SL-Buildings-CC-12-IDMI-01-Ile de France-BU-FR03305FR_EGIS BAT IDF | L15: SL-Buildings-CC-12-IDMI-01-Ile de France-BU-FR03305FR_EGIS BAT IDF | M15: EGIS BATIMENTS ILE DE FRANCE Billable E&SC Small Project | N15: =_xlfn.XLOOKUP(M15,'source template'!A:A,'source template'!I:I,,1) -> 0 | V15: EUR | X15: Corporate | Y15: T | Z15: FALSE | AA15: FALSE | AB15: TRUE | AC15: TRUE | AD15: O | AE15: P01 | AG15: FINANCIAL | BN15: 46203 | BO15: 41275 | BP15: 319-000008 | BQ15: STD | BR15: Standard | CG15: 45657 | CH15: P01 | CI15: 41275 | CJ15: PJF_TASKS | CK15: FINANCIAL
B16: OK | D16: CREATE | E16: BIL-1007983 | F16: TESTME-FR03319FR-4896-30 Logements Siguy [3319_4896] | G16: TESTME--TESTME-FR03319FR-4896-30 Logements Siguy [3319_4896] | H16: DRAFT | I16: EGIS BATIMENTS ILE DE FRANCE | J16: =_xlfn.XLOOKUP(I16,LE!A:A,LE!F:F,,1) -> 0 | K16: SL-Buildings-CC-12-IDMI-01-Ile de France-BU-FR03305FR_EGIS BAT IDF | L16: SL-Buildings-CC-12-IDMI-01-Ile de France-BU-FR03305FR_EGIS BAT IDF | M16: EGIS BATIMENTS ILE DE FRANCE Billable E&SC Small Project | N16: =_xlfn.XLOOKUP(M16,'source template'!A:A,'source template'!I:I,,1) -> 0 | V16: EUR | X16: Corporate | Y16: T | Z16: FALSE | AA16: FALSE | AB16: TRUE | AC16: TRUE | AD16: E | AE16: P02 | AG16: FINANCIAL | BN16: 46203 | BO16: 41275 | BP16: 319-000008 | BQ16: STD | BR16: Standard | CG16: 45688 | CH16: P02 | CI16: 41275 | CJ16: PJF_TASKS | CK16: FINANCIAL
B17: OK | D17: CREATE | E17: BIL-1007983 | F17: TESTME-FR03319FR-4896-30 Logements Siguy [3319_4896] | G17: TESTME--TESTME-FR03319FR-4896-30 Logements Siguy [3319_4896] | H17: DRAFT | I17: EGIS BATIMENTS ILE DE FRANCE | J17: =_xlfn.XLOOKUP(I17,LE!A:A,LE!F:F,,1) -> 0 | K17: SL-Buildings-CC-12-IDMI-01-Ile de France-BU-FR03305FR_EGIS BAT IDF | L17: SL-Buildings-CC-12-IDMI-01-Ile de France-BU-FR03305FR_EGIS BAT IDF | M17: EGIS BATIMENTS ILE DE FRANCE Billable E&SC Small Project | N17: =_xlfn.XLOOKUP(M17,'source template'!A:A,'source template'!I:I,,1) -> 0 | V17: EUR | X17: Corporate | Y17: T | Z17: FALSE | AA17: FALSE | AB17: TRUE | AC17: TRUE | AD17: T | AE17: P03 | AG17: FINANCIAL | BN17: 46203 | BO17: 41275 | BP17: 319-000008 | BQ17: STD | BR17: Standard | CG17: 46203 | CH17: P03 | CI17: 41275 | CJ17: PJF_TASKS | CK17: FINANCIAL
B18: OK | D18: CREATE | E18: BIL-1007983 | F18: TESTME-FR03319FR-4896-30 Logements Siguy [3319_4896] | G18: TESTME--TESTME-FR03319FR-4896-30 Logements Siguy [3319_4896] | H18: DRAFT | I18: EGIS BATIMENTS ILE DE FRANCE | J18: =_xlfn.XLOOKUP(I18,LE!A:A,LE!F:F,,1) -> 0 | K18: SL-Buildings-CC-12-IDMI-01-Ile de France-BU-FR03305FR_EGIS BAT IDF | L18: SL-Buildings-CC-12-IDMI-01-Ile de France-BU-FR03305FR_EGIS BAT IDF | M18: EGIS BATIMENTS ILE DE FRANCE Billable E&SC Small Project | N18: =_xlfn.XLOOKUP(M18,'source template'!A:A,'source template'!I:I,,1) -> 0 | V18: EUR | X18: Corporate | Y18: T | Z18: FALSE | AA18: FALSE | AB18: TRUE | AC18: TRUE | AD18: Facturation Milestone Oracle 2025 | AE18: P97 | AG18: FINANCIAL | BN18: 46203 | BO18: 41275 | BP18: 319-000008 | BQ18: STD | BR18: Standard | CG18: 46022 | CH18: P97 | CI18: 41275 | CJ18: PJF_TASKS | CK18: FINANCIAL
B19: OK | D19: CREATE | E19: BIL-1007983 | F19: TESTME-FR03319FR-4896-30 Logements Siguy [3319_4896] | G19: TESTME--TESTME-FR03319FR-4896-30 Logements Siguy [3319_4896] | H19: DRAFT | I19: EGIS BATIMENTS ILE DE FRANCE | J19: =_xlfn.XLOOKUP(I19,LE!A:A,LE!F:F,,1) -> 0 | K19: SL-Buildings-CC-12-IDMI-01-Ile de France-BU-FR03305FR_EGIS BAT IDF | L19: SL-Buildings-CC-12-IDMI-01-Ile de France-BU-FR03305FR_EGIS BAT IDF | M19: EGIS BATIMENTS ILE DE FRANCE Billable E&SC Small Project | N19: =_xlfn.XLOOKUP(M19,'source template'!A:A,'source template'!I:I,,1) -> 0 | V19: EUR | X19: Corporate | Y19: T | Z19: FALSE | AA19: FALSE | AB19: TRUE | AC19: TRUE | AV19: Project Classification | AW19: Client Project | BN19: 46203 | BO19: 41275 | BP19: 319-000008 | BQ19: STD | BR19: Standard
B20: OK | D20: CREATE | E20: BIL-1007983 | F20: TESTME-FR03319FR-4896-30 Logements Siguy [3319_4896] | G20: TESTME--TESTME-FR03319FR-4896-30 Logements Siguy [3319_4896] | H20: DRAFT | I20: EGIS BATIMENTS ILE DE FRANCE | J20: =_xlfn.XLOOKUP(I20,LE!A:A,LE!F:F,,1) -> 0 | K20: SL-Buildings-CC-12-IDMI-01-Ile de France-BU-FR03305FR_EGIS BAT IDF | L20: SL-Buildings-CC-12-IDMI-01-Ile de France-BU-FR03305FR_EGIS BAT IDF | M20: EGIS BATIMENTS ILE DE FRANCE Billable E&SC Small Project | N20: =_xlfn.XLOOKUP(M20,'source template'!A:A,'source template'!I:I,,1) -> 0 | V20: EUR | X20: Corporate | Y20: T | Z20: FALSE | AA20: FALSE | AB20: TRUE | AC20: TRUE | AS20: Etienne.FERRER@egis-group.com | AT20: Project Manager | AU20: 43864 | BN20: 46203 | BO20: 41275 | BP20: 319-000008 | BQ20: STD | BR20: Standard
B21: OK | D21: CREATE | E21: BIL-1007983 | F21: TESTME-FR03319FR-4896-30 Logements Siguy [3319_4896] | G21: TESTME--TESTME-FR03319FR-4896-30 Logements Siguy [3319_4896] | H21: DRAFT | I21: EGIS BATIMENTS ILE DE FRANCE | J21: =_xlfn.XLOOKUP(I21,LE!A:A,LE!F:F,,1) -> 0 | K21: SL-Buildings-CC-12-IDMI-01-Ile de France-BU-FR03305FR_EGIS BAT IDF | L21: SL-Buildings-CC-12-IDMI-01-Ile de France-BU-FR03305FR_EGIS BAT IDF | M21: EGIS BATIMENTS ILE DE FRANCE Billable E&SC Small Project | N21: =_xlfn.XLOOKUP(M21,'source template'!A:A,'source template'!I:I,,1) -> 0 | V21: EUR | X21: Corporate | Y21: T | Z21: FALSE | AA21: FALSE | AB21: TRUE | AC21: TRUE | AS21: Rokhaya.NDIAYE@egis-group.com | AT21: Financial Controller | AU21: 41883 | BN21: 46203 | BO21: 41275 | BP21: 319-000008 | BQ21: STD | BR21: Standard
B22: OK | D22: CREATE | E22: BIL-1007983 | F22: TESTME-FR03319FR-4896-30 Logements Siguy [3319_4896] | G22: TESTME--TESTME-FR03319FR-4896-30 Logements Siguy [3319_4896] | H22: DRAFT | I22: EGIS BATIMENTS ILE DE FRANCE | J22: =_xlfn.XLOOKUP(I22,LE!A:A,LE!F:F,,1) -> 0 | K22: SL-Buildings-CC-12-IDMI-01-Ile de France-BU-FR03305FR_EGIS BAT IDF | L22: SL-Buildings-CC-12-IDMI-01-Ile de France-BU-FR03305FR_EGIS BAT IDF | M22: EGIS BATIMENTS ILE DE FRANCE Billable E&SC Small Project | N22: =_xlfn.XLOOKUP(M22,'source template'!A:A,'source template'!I:I,,1) -> 0 | V22: EUR | X22: Corporate | Y22: T | Z22: FALSE | AA22: FALSE | AB22: TRUE | AC22: TRUE | AS22: Sebastien.PLICHON@egis-group.com | AT22: RBLD | AU22: 42736 | BN22: 46203 | BO22: 41275 | BP22: 319-000008 | BQ22: STD | BR22: Standard
B23: OK | D23: CREATE | E23: BIL-1007983 | F23: TESTME-FR03319FR-4896-30 Logements Siguy [3319_4896] | G23: TESTME--TESTME-FR03319FR-4896-30 Logements Siguy [3319_4896] | H23: DRAFT | I23: EGIS BATIMENTS ILE DE FRANCE | J23: =_xlfn.XLOOKUP(I23,LE!A:A,LE!F:F,,1) -> 0 | K23: SL-Buildings-CC-12-IDMI-01-Ile de France-BU-FR03305FR_EGIS BAT IDF | L23: SL-Buildings-CC-12-IDMI-01-Ile de France-BU-FR03305FR_EGIS BAT IDF | M23: EGIS BATIMENTS ILE DE FRANCE Billable E&SC Small Project | N23: =_xlfn.XLOOKUP(M23,'source template'!A:A,'source template'!I:I,,1) -> 0 | V23: EUR | X23: Corporate | Y23: T | Z23: FALSE | AA23: FALSE | AB23: TRUE | AC23: TRUE | AS23: Cedric.ARNAUD@egis-group.com | AT23: Project Sponsor / RBLD Delegate | AU23: 45680 | BN23: 46203 | BO23: 41275 | BP23: 319-000008 | BQ23: STD | BR23: Standard
B24: OK | D24: CREATE | E24: BIL-1007983 | F24: TESTME-FR03319FR-4896-30 Logements Siguy [3319_4896] | G24: TESTME--TESTME-FR03319FR-4896-30 Logements Siguy [3319_4896] | H24: DRAFT | I24: EGIS BATIMENTS ILE DE FRANCE | J24: =_xlfn.XLOOKUP(I24,LE!A:A,LE!F:F,,1) -> 0 | K24: SL-Buildings-CC-12-IDMI-01-Ile de France-BU-FR03305FR_EGIS BAT IDF | L24: SL-Buildings-CC-12-IDMI-01-Ile de France-BU-FR03305FR_EGIS BAT IDF | M24: EGIS BATIMENTS ILE DE FRANCE Billable E&SC Small Project | N24: =_xlfn.XLOOKUP(M24,'source template'!A:A,'source template'!I:I,,1) -> 0 | V24: EUR | X24: Corporate | Y24: T | Z24: FALSE | AA24: FALSE | AB24: TRUE | AC24: TRUE | AS24: Benoit.THERON@egis-group.com | AT24: Project Manager | AU24: 45804 | BN24: 46203 | BO24: 41275 | BP24: 319-000008 | BQ24: STD | BR24: Standard
B25: OK | D25: CREATE | E25: BIL-1007983 | F25: TESTME-FR03319FR-4896-30 Logements Siguy [3319_4896] | G25: TESTME--TESTME-FR03319FR-4896-30 Logements Siguy [3319_4896] | H25: DRAFT | I25: EGIS BATIMENTS ILE DE FRANCE | J25: =_xlfn.XLOOKUP(I25,LE!A:A,LE!F:F,,1) -> 0 | K25: SL-Buildings-CC-12-IDMI-01-Ile de France-BU-FR03305FR_EGIS BAT IDF | L25: SL-Buildings-CC-12-IDMI-01-Ile de France-BU-FR03305FR_EGIS BAT IDF | M25: EGIS BATIMENTS ILE DE FRANCE Billable E&SC Small Project | N25: =_xlfn.XLOOKUP(M25,'source template'!A:A,'source template'!I:I,,1) -> 0 | V25: EUR | X25: Corporate | Y25: T | Z25: FALSE | AA25: FALSE | AB25: TRUE | AC25: TRUE | AS25: Cedric.ARNAUD@egis-group.com | AT25: Project Manager | AU25: 45658 | BN25: 46203 | BO25: 41275 | BP25: 319-000008 | BQ25: STD | BR25: Standard
B26: OK | D26: CREATE | E26: BIL-1007982 | F26: TESTME-FR03319FR-4858-Grande Savane [3319_4858] | G26: TESTME--TESTME-FR03319FR-4858-Grande Savane [3319_4858] | H26: DRAFT | I26: EGIS BATIMENTS ILE DE FRANCE | J26: =_xlfn.XLOOKUP(I26,LE!A:A,LE!F:F,,1) -> 0 | K26: SL-Buildings-CC-12-IDMI-01-Ile de France-BU-FR03305FR_EGIS BAT IDF | L26: SL-Buildings-CC-12-IDMI-01-Ile de France-BU-FR03305FR_EGIS BAT IDF | M26: EGIS BATIMENTS ILE DE FRANCE Billable E&SC Small Project | N26: =_xlfn.XLOOKUP(M26,'source template'!A:A,'source template'!I:I,,1) -> 0 | V26: EUR | X26: Corporate | Y26: T | Z26: FALSE | AA26: FALSE | AB26: TRUE | AC26: TRUE | AD26: O | AE26: P01 | AG26: FINANCIAL | BN26: 45657 | BO26: 40544 | BP26: 319-000003 | BQ26: STD | BR26: Standard | CG26: 45657 | CH26: P01 | CI26: 40544 | CJ26: PJF_TASKS | CK26: FINANCIAL
B27: OK | D27: CREATE | E27: BIL-1007982 | F27: TESTME-FR03319FR-4858-Grande Savane [3319_4858] | G27: TESTME--TESTME-FR03319FR-4858-Grande Savane [3319_4858] | H27: DRAFT | I27: EGIS BATIMENTS ILE DE FRANCE | J27: =_xlfn.XLOOKUP(I27,LE!A:A,LE!F:F,,1) -> 0 | K27: SL-Buildings-CC-12-IDMI-01-Ile de France-BU-FR03305FR_EGIS BAT IDF | L27: SL-Buildings-CC-12-IDMI-01-Ile de France-BU-FR03305FR_EGIS BAT IDF | M27: EGIS BATIMENTS ILE DE FRANCE Billable E&SC Small Project | N27: =_xlfn.XLOOKUP(M27,'source template'!A:A,'source template'!I:I,,1) -> 0 | V27: EUR | X27: Corporate | Y27: T | Z27: FALSE | AA27: FALSE | AB27: TRUE | AC27: TRUE | AD27: E | AE27: P02 | AG27: FINANCIAL | BN27: 45657 | BO27: 40544 | BP27: 319-000003 | BQ27: STD | BR27: Standard | CG27: 45657 | CH27: P02 | CI27: 40544 | CJ27: PJF_TASKS | CK27: FINANCIAL
B28: OK | D28: CREATE | E28: BIL-1007982 | F28: TESTME-FR03319FR-4858-Grande Savane [3319_4858] | G28: TESTME--TESTME-FR03319FR-4858-Grande Savane [3319_4858] | H28: DRAFT | I28: EGIS BATIMENTS ILE DE FRANCE | J28: =_xlfn.XLOOKUP(I28,LE!A:A,LE!F:F,,1) -> 0 | K28: SL-Buildings-CC-12-IDMI-01-Ile de France-BU-FR03305FR_EGIS BAT IDF | L28: SL-Buildings-CC-12-IDMI-01-Ile de France-BU-FR03305FR_EGIS BAT IDF | M28: EGIS BATIMENTS ILE DE FRANCE Billable E&SC Small Project | N28: =_xlfn.XLOOKUP(M28,'source template'!A:A,'source template'!I:I,,1) -> 0 | V28: EUR | X28: Corporate | Y28: T | Z28: FALSE | AA28: FALSE | AB28: TRUE | AC28: TRUE | AD28: T - Travaux | AE28: P03 | AG28: FINANCIAL | BN28: 45657 | BO28: 40544 | BP28: 319-000003 | BQ28: STD | BR28: Standard | CG28: 45657 | CH28: P03 | CI28: 40544 | CJ28: PJF_TASKS | CK28: FINANCIAL
B29: OK | D29: CREATE | E29: BIL-1007982 | F29: TESTME-FR03319FR-4858-Grande Savane [3319_4858] | G29: TESTME--TESTME-FR03319FR-4858-Grande Savane [3319_4858] | H29: DRAFT | I29: EGIS BATIMENTS ILE DE FRANCE | J29: =_xlfn.XLOOKUP(I29,LE!A:A,LE!F:F,,1) -> 0 | K29: SL-Buildings-CC-12-IDMI-01-Ile de France-BU-FR03305FR_EGIS BAT IDF | L29: SL-Buildings-CC-12-IDMI-01-Ile de France-BU-FR03305FR_EGIS BAT IDF | M29: EGIS BATIMENTS ILE DE FRANCE Billable E&SC Small Project | N29: =_xlfn.XLOOKUP(M29,'source template'!A:A,'source template'!I:I,,1) -> 0 | V29: EUR | X29: Corporate | Y29: T | Z29: FALSE | AA29: FALSE | AB29: TRUE | AC29: TRUE | AD29: Facturation Milestone Oracle 2025 | AE29: P97 | AG29: FINANCIAL | BN29: 45657 | BO29: 40544 | BP29: 319-000003 | BQ29: STD | BR29: Standard | CG29: 45657 | CH29: P97 | CI29: 40544 | CJ29: PJF_TASKS | CK29: FINANCIAL
B30: OK | D30: CREATE | E30: BIL-1007982 | F30: TESTME-FR03319FR-4858-Grande Savane [3319_4858] | G30: TESTME--TESTME-FR03319FR-4858-Grande Savane [3319_4858] | H30: DRAFT | I30: EGIS BATIMENTS ILE DE FRANCE | J30: =_xlfn.XLOOKUP(I30,LE!A:A,LE!F:F,,1) -> 0 | K30: SL-Buildings-CC-12-IDMI-01-Ile de France-BU-FR03305FR_EGIS BAT IDF | L30: SL-Buildings-CC-12-IDMI-01-Ile de France-BU-FR03305FR_EGIS BAT IDF | M30: EGIS BATIMENTS ILE DE FRANCE Billable E&SC Small Project | N30: =_xlfn.XLOOKUP(M30,'source template'!A:A,'source template'!I:I,,1) -> 0 | V30: EUR | X30: Corporate | Y30: T | Z30: FALSE | AA30: FALSE | AB30: TRUE | AC30: TRUE | AV30: Project Classification | AW30: Client Project | BN30: 45657 | BO30: 40544 | BP30: 319-000003 | BQ30: STD | BR30: Standard
B31: OK | D31: CREATE | E31: BIL-1007982 | F31: TESTME-FR03319FR-4858-Grande Savane [3319_4858] | G31: TESTME--TESTME-FR03319FR-4858-Grande Savane [3319_4858] | H31: DRAFT | I31: EGIS BATIMENTS ILE DE FRANCE | J31: =_xlfn.XLOOKUP(I31,LE!A:A,LE!F:F,,1) -> 0 | K31: SL-Buildings-CC-12-IDMI-01-Ile de France-BU-FR03305FR_EGIS BAT IDF | L31: SL-Buildings-CC-12-IDMI-01-Ile de France-BU-FR03305FR_EGIS BAT IDF | M31: EGIS BATIMENTS ILE DE FRANCE Billable E&SC Small Project | N31: =_xlfn.XLOOKUP(M31,'source template'!A:A,'source template'!I:I,,1) -> 0 | V31: EUR | X31: Corporate | Y31: T | Z31: FALSE | AA31: FALSE | AB31: TRUE | AC31: TRUE | AS31: Daniel.SCHACHINGER@egis-group.com | AT31: Project Manager | AU31: 41640 | BN31: 45657 | BO31: 40544 | BP31: 319-000003 | BQ31: STD | BR31: Standard
B32: OK | D32: CREATE | E32: BIL-1007982 | F32: TESTME-FR03319FR-4858-Grande Savane [3319_4858] | G32: TESTME--TESTME-FR03319FR-4858-Grande Savane [3319_4858] | H32: DRAFT | I32: EGIS BATIMENTS ILE DE FRANCE | J32: =_xlfn.XLOOKUP(I32,LE!A:A,LE!F:F,,1) -> 0 | K32: SL-Buildings-CC-12-IDMI-01-Ile de France-BU-FR03305FR_EGIS BAT IDF | L32: SL-Buildings-CC-12-IDMI-01-Ile de France-BU-FR03305FR_EGIS BAT IDF | M32: EGIS BATIMENTS ILE DE FRANCE Billable E&SC Small Project | N32: =_xlfn.XLOOKUP(M32,'source template'!A:A,'source template'!I:I,,1) -> 0 | V32: EUR | X32: Corporate | Y32: T | Z32: FALSE | AA32: FALSE | AB32: TRUE | AC32: TRUE | AS32: Rokhaya.NDIAYE@egis-group.com | AT32: Financial Controller | AU32: 41883 | BN32: 45657 | BO32: 40544 | BP32: 319-000003 | BQ32: STD | BR32: Standard
B33: OK | D33: CREATE | E33: BIL-1007982 | F33: TESTME-FR03319FR-4858-Grande Savane [3319_4858] | G33: TESTME--TESTME-FR03319FR-4858-Grande Savane [3319_4858] | H33: DRAFT | I33: EGIS BATIMENTS ILE DE FRANCE | J33: =_xlfn.XLOOKUP(I33,LE!A:A,LE!F:F,,1) -> 0 | K33: SL-Buildings-CC-12-IDMI-01-Ile de France-BU-FR03305FR_EGIS BAT IDF | L33: SL-Buildings-CC-12-IDMI-01-Ile de France-BU-FR03305FR_EGIS BAT IDF | M33: EGIS BATIMENTS ILE DE FRANCE Billable E&SC Small Project | N33: =_xlfn.XLOOKUP(M33,'source template'!A:A,'source template'!I:I,,1) -> 0 | V33: EUR | X33: Corporate | Y33: T | Z33: FALSE | AA33: FALSE | AB33: TRUE | AC33: TRUE | AS33: Sebastien.PLICHON@egis-group.com | AT33: RBLD | AU33: 42736 | BN33: 45657 | BO33: 40544 | BP33: 319-000003 | BQ33: STD | BR33: Standard
B34: OK | D34: CREATE | E34: BIL-1007982 | F34: TESTME-FR03319FR-4858-Grande Savane [3319_4858] | G34: TESTME--TESTME-FR03319FR-4858-Grande Savane [3319_4858] | H34: DRAFT | I34: EGIS BATIMENTS ILE DE FRANCE | J34: =_xlfn.XLOOKUP(I34,LE!A:A,LE!F:F,,1) -> 0 | K34: SL-Buildings-CC-12-IDMI-01-Ile de France-BU-FR03305FR_EGIS BAT IDF | L34: SL-Buildings-CC-12-IDMI-01-Ile de France-BU-FR03305FR_EGIS BAT IDF | M34: EGIS BATIMENTS ILE DE FRANCE Billable E&SC Small Project | N34: =_xlfn.XLOOKUP(M34,'source template'!A:A,'source template'!I:I,,1) -> 0 | V34: EUR | X34: Corporate | Y34: T | Z34: FALSE | AA34: FALSE | AB34: TRUE | AC34: TRUE | AS34: Cedric.ARNAUD@egis-group.com | AT34: Project Sponsor / RBLD Delegate | AU34: 45658 | BN34: 45657 | BO34: 40544 | BP34: 319-000003 | BQ34: STD | BR34: Standard
B35: OK | D35: CREATE | E35: BIL-1007982 | F35: TESTME-FR03319FR-4858-Grande Savane [3319_4858] | G35: TESTME--TESTME-FR03319FR-4858-Grande Savane [3319_4858] | H35: DRAFT | I35: EGIS BATIMENTS ILE DE FRANCE | J35: =_xlfn.XLOOKUP(I35,LE!A:A,LE!F:F,,1) -> 0 | K35: SL-Buildings-CC-12-IDMI-01-Ile de France-BU-FR03305FR_EGIS BAT IDF | L35: SL-Buildings-CC-12-IDMI-01-Ile de France-BU-FR03305FR_EGIS BAT IDF | M35: EGIS BATIMENTS ILE DE FRANCE Billable E&SC Small Project | N35: =_xlfn.XLOOKUP(M35,'source template'!A:A,'source template'!I:I,,1) -> 0 | V35: EUR | X35: Corporate | Y35: T | Z35: FALSE | AA35: FALSE | AB35: TRUE | AC35: TRUE | AS35: Cedric.ARNAUD@egis-group.com | AT35: Project Manager | AU35: 45658 | BN35: 45657 | BO35: 40544 | BP35: 319-000003 | BQ35: STD | BR35: Standard
B36: OK | D36: CREATE | E36: BIL-1007989 | F36: TESTME-FR03319FR-BARE57401-GUAD>ATMO bloc opératoire CH Basse Terre [3319_BARE57401] | G36: TESTME-FR03319FR-BARE57401-GUAD>ATMO bloc opératoire CH Basse Terre [3319_BARE57401] | H36: DRAFT | I36: EGIS BATIMENTS ILE DE FRANCE | J36: EGIS BATIMENTS ILE DE FRANCE | K36: SL-Buildings-CC-12-IDMI-01-Ile de France-BU-FR03305FR_EGIS BAT IDF | L36: SL-Buildings-CC-12-IDMI-01-Ile de France-BU-FR03305FR_EGIS BAT IDF | M36: EGIS BATIMENTS ILE DE FRANCE Billable E&SC Small Project | N36: EGIS BATIMENTS ILE DE FRANCE Billable E&SC Small Project | V36: EUR | X36: Corporate | Y36: T | Z36: FALSE | AA36: FALSE | AB36: TRUE | AC36: TRUE | AD36: O - Offre | AE36: P01 | AG36: FINANCIAL | BN36: 46203 | BO36: 44410 | BP36: BARE574 | BQ36: STD | BR36: Standard | CG36: 45657 | CH36: P01 | CI36: 44410 | CJ36: PJF_TASKS | CK36: FINANCIAL
B37: OK | D37: CREATE | E37: BIL-1007989 | F37: TESTME-FR03319FR-BARE57401-GUAD>ATMO bloc opératoire CH Basse Terre [3319_BARE57401] | G37: TESTME-FR03319FR-BARE57401-GUAD>ATMO bloc opératoire CH Basse Terre [3319_BARE57401] | H37: DRAFT | I37: EGIS BATIMENTS ILE DE FRANCE | J37: EGIS BATIMENTS ILE DE FRANCE | K37: SL-Buildings-CC-12-IDMI-01-Ile de France-BU-FR03305FR_EGIS BAT IDF | L37: SL-Buildings-CC-12-IDMI-01-Ile de France-BU-FR03305FR_EGIS BAT IDF | M37: EGIS BATIMENTS ILE DE FRANCE Billable E&SC Small Project | N37: EGIS BATIMENTS ILE DE FRANCE Billable E&SC Small Project | V37: EUR | X37: Corporate | Y37: T | Z37: FALSE | AA37: FALSE | AB37: TRUE | AC37: TRUE | AD37: T - Travaux | AE37: P02 | AG37: FINANCIAL | BN37: 46203 | BO37: 44410 | BP37: BARE574 | BQ37: STD | BR37: Standard | CG37: 46203 | CH37: P02 | CI37: 44410 | CJ37: PJF_TASKS | CK37: FINANCIAL
B38: OK | D38: CREATE | E38: BIL-1007989 | F38: TESTME-FR03319FR-BARE57401-GUAD>ATMO bloc opératoire CH Basse Terre [3319_BARE57401] | G38: TESTME-FR03319FR-BARE57401-GUAD>ATMO bloc opératoire CH Basse Terre [3319_BARE57401] | H38: DRAFT | I38: EGIS BATIMENTS ILE DE FRANCE | J38: EGIS BATIMENTS ILE DE FRANCE | K38: SL-Buildings-CC-12-IDMI-01-Ile de France-BU-FR03305FR_EGIS BAT IDF | L38: SL-Buildings-CC-12-IDMI-01-Ile de France-BU-FR03305FR_EGIS BAT IDF | M38: EGIS BATIMENTS ILE DE FRANCE Billable E&SC Small Project | N38: EGIS BATIMENTS ILE DE FRANCE Billable E&SC Small Project | V38: EUR | X38: Corporate | Y38: T | Z38: FALSE | AA38: FALSE | AB38: TRUE | AC38: TRUE | AD38: Facturation Milestone Oracle 2025 | AE38: P97 | AG38: FINANCIAL | BN38: 46203 | BO38: 44410 | BP38: BARE574 | BQ38: STD | BR38: Standard | CG38: 46203 | CH38: P97 | CI38: 44410 | CJ38: PJF_TASKS | CK38: FINANCIAL
B39: OK | D39: CREATE | E39: BIL-1007989 | F39: TESTME-FR03319FR-BARE57401-GUAD>ATMO bloc opératoire CH Basse Terre [3319_BARE57401] | G39: TESTME-FR03319FR-BARE57401-GUAD>ATMO bloc opératoire CH Basse Terre [3319_BARE57401] | H39: DRAFT | I39: EGIS BATIMENTS ILE DE FRANCE | J39: EGIS BATIMENTS ILE DE FRANCE | K39: SL-Buildings-CC-12-IDMI-01-Ile de France-BU-FR03305FR_EGIS BAT IDF | L39: SL-Buildings-CC-12-IDMI-01-Ile de France-BU-FR03305FR_EGIS BAT IDF | M39: EGIS BATIMENTS ILE DE FRANCE Billable E&SC Small Project | N39: EGIS BATIMENTS ILE DE FRANCE Billable E&SC Small Project | V39: EUR | X39: Corporate | Y39: T | Z39: FALSE | AA39: FALSE | AB39: TRUE | AC39: TRUE | AV39: Project Classification | AW39: Client Project | BN39: 46203 | BO39: 44410 | BP39: BARE574 | BQ39: STD | BR39: Standard
B40: OK | D40: CREATE | E40: BIL-1007989 | F40: TESTME-FR03319FR-BARE57401-GUAD>ATMO bloc opératoire CH Basse Terre [3319_BARE57401] | G40: TESTME-FR03319FR-BARE57401-GUAD>ATMO bloc opératoire CH Basse Terre [3319_BARE57401] | H40: DRAFT | I40: EGIS BATIMENTS ILE DE FRANCE | J40: EGIS BATIMENTS ILE DE FRANCE | K40: SL-Buildings-CC-12-IDMI-01-Ile de France-BU-FR03305FR_EGIS BAT IDF | L40: SL-Buildings-CC-12-IDMI-01-Ile de France-BU-FR03305FR_EGIS BAT IDF | M40: EGIS BATIMENTS ILE DE FRANCE Billable E&SC Small Project | N40: EGIS BATIMENTS ILE DE FRANCE Billable E&SC Small Project | V40: EUR | X40: Corporate | Y40: T | Z40: FALSE | AA40: FALSE | AB40: TRUE | AC40: TRUE | AS40: Regis.AUBERT@egis-group.com | AT40: Project Manager | AU40: 44502 | BN40: 46203 | BO40: 44410 | BP40: BARE574 | BQ40: STD | BR40: Standard
B41: OK | D41: CREATE | E41: BIL-1007989 | F41: TESTME-FR03319FR-BARE57401-GUAD>ATMO bloc opératoire CH Basse Terre [3319_BARE57401] | G41: TESTME-FR03319FR-BARE57401-GUAD>ATMO bloc opératoire CH Basse Terre [3319_BARE57401] | H41: DRAFT | I41: EGIS BATIMENTS ILE DE FRANCE | J41: EGIS BATIMENTS ILE DE FRANCE | K41: SL-Buildings-CC-12-IDMI-01-Ile de France-BU-FR03305FR_EGIS BAT IDF | L41: SL-Buildings-CC-12-IDMI-01-Ile de France-BU-FR03305FR_EGIS BAT IDF | M41: EGIS BATIMENTS ILE DE FRANCE Billable E&SC Small Project | N41: EGIS BATIMENTS ILE DE FRANCE Billable E&SC Small Project | V41: EUR | X41: Corporate | Y41: T | Z41: FALSE | AA41: FALSE | AB41: TRUE | AC41: TRUE | AS41: Rokhaya.NDIAYE@egis-group.com | AT41: Financial Controller | AU41: 44410 | BN41: 46203 | BO41: 44410 | BP41: BARE574 | BQ41: STD | BR41: Standard
B42: OK | D42: CREATE | E42: BIL-1007989 | F42: TESTME-FR03319FR-BARE57401-GUAD>ATMO bloc opératoire CH Basse Terre [3319_BARE57401] | G42: TESTME-FR03319FR-BARE57401-GUAD>ATMO bloc opératoire CH Basse Terre [3319_BARE57401] | H42: DRAFT | I42: EGIS BATIMENTS ILE DE FRANCE | J42: EGIS BATIMENTS ILE DE FRANCE | K42: SL-Buildings-CC-12-IDMI-01-Ile de France-BU-FR03305FR_EGIS BAT IDF | L42: SL-Buildings-CC-12-IDMI-01-Ile de France-BU-FR03305FR_EGIS BAT IDF | M42: EGIS BATIMENTS ILE DE FRANCE Billable E&SC Small Project | N42: EGIS BATIMENTS ILE DE FRANCE Billable E&SC Small Project | V42: EUR | X42: Corporate | Y42: T | Z42: FALSE | AA42: FALSE | AB42: TRUE | AC42: TRUE | AS42: Sebastien.PLICHON@egis-group.com | AT42: RBLD | AU42: 44410 | BN42: 46203 | BO42: 44410 | BP42: BARE574 | BQ42: STD | BR42: Standard
B43: OK | D43: CREATE | E43: BIL-1007989 | F43: TESTME-FR03319FR-BARE57401-GUAD>ATMO bloc opératoire CH Basse Terre [3319_BARE57401] | G43: TESTME-FR03319FR-BARE57401-GUAD>ATMO bloc opératoire CH Basse Terre [3319_BARE57401] | H43: DRAFT | I43: EGIS BATIMENTS ILE DE FRANCE | J43: EGIS BATIMENTS ILE DE FRANCE | K43: SL-Buildings-CC-12-IDMI-01-Ile de France-BU-FR03305FR_EGIS BAT IDF | L43: SL-Buildings-CC-12-IDMI-01-Ile de France-BU-FR03305FR_EGIS BAT IDF | M43: EGIS BATIMENTS ILE DE FRANCE Billable E&SC Small Project | N43: EGIS BATIMENTS ILE DE FRANCE Billable E&SC Small Project | V43: EUR | X43: Corporate | Y43: T | Z43: FALSE | AA43: FALSE | AB43: TRUE | AC43: TRUE | AS43: Cedric.ARNAUD@egis-group.com | AT43: Project Sponsor / RBLD Delegate | AU43: 45658 | BN43: 46203 | BO43: 44410 | BP43: BARE574 | BQ43: STD | BR43: Standard
B44: OK | D44: CREATE | E44: BIL-1007989 | F44: TESTME-FR03319FR-BARE57401-GUAD>ATMO bloc opératoire CH Basse Terre [3319_BARE57401] | G44: TESTME-FR03319FR-BARE57401-GUAD>ATMO bloc opératoire CH Basse Terre [3319_BARE57401] | H44: DRAFT | I44: EGIS BATIMENTS ILE DE FRANCE | J44: EGIS BATIMENTS ILE DE FRANCE | K44: SL-Buildings-CC-12-IDMI-01-Ile de France-BU-FR03305FR_EGIS BAT IDF | L44: SL-Buildings-CC-12-IDMI-01-Ile de France-BU-FR03305FR_EGIS BAT IDF | M44: EGIS BATIMENTS ILE DE FRANCE Billable E&SC Small Project | N44: EGIS BATIMENTS ILE DE FRANCE Billable E&SC Small Project | V44: EUR | X44: Corporate | Y44: T | Z44: FALSE | AA44: FALSE | AB44: TRUE | AC44: TRUE | AS44: Julien.LECORNET@egis-group.com | AT44: Project Manager | AU44: 45727 | BN44: 46203 | BO44: 44410 | BP44: BARE574 | BQ44: STD | BR44: Standard
B45: OK | D45: CREATE | E45: BIL-1007989 | F45: TESTME-FR03319FR-BARE57401-GUAD>ATMO bloc opératoire CH Basse Terre [3319_BARE57401] | G45: TESTME-FR03319FR-BARE57401-GUAD>ATMO bloc opératoire CH Basse Terre [3319_BARE57401] | H45: DRAFT | I45: EGIS BATIMENTS ILE DE FRANCE | J45: EGIS BATIMENTS ILE DE FRANCE | K45: SL-Buildings-CC-12-IDMI-01-Ile de France-BU-FR03305FR_EGIS BAT IDF | L45: SL-Buildings-CC-12-IDMI-01-Ile de France-BU-FR03305FR_EGIS BAT IDF | M45: EGIS BATIMENTS ILE DE FRANCE Billable E&SC Small Project | N45: EGIS BATIMENTS ILE DE FRANCE Billable E&SC Small Project | V45: EUR | X45: Corporate | Y45: T | Z45: FALSE | AA45: FALSE | AB45: TRUE | AC45: TRUE | AS45: Cedric.ARNAUD@egis-group.com | AT45: Project Manager | AU45: 45658 | BN45: 46203 | BO45: 44410 | BP45: BARE574 | BQ45: STD | BR45: Standard
B46: OK | D46: CREATE | E46: BIL-1007986 | F46: TESTME-FR03319FR-BANL07401-GUAD>Habitation des Jésuites [3319_BANL07401] | G46: TESTME-FR03319FR-BANL07401-GUAD>Habitation des Jésuites [3319_BANL07401] | H46: DRAFT | I46: EGIS BATIMENTS ILE DE FRANCE | J46: EGIS BATIMENTS ILE DE FRANCE | K46: SL-Buildings-CC-12-IDMI-01-Ile de France-BU-FR03305FR_EGIS BAT IDF | L46: SL-Buildings-CC-12-IDMI-01-Ile de France-BU-FR03305FR_EGIS BAT IDF | M46: EGIS BATIMENTS ILE DE FRANCE Billable E&SC Small Project | N46: EGIS BATIMENTS ILE DE FRANCE Billable E&SC Small Project | V46: EUR | X46: Corporate | Y46: T | Z46: FALSE | AA46: FALSE | AB46: TRUE | AC46: TRUE | AD46: P01 - Concours | AE46: P01 | AG46: FINANCIAL | BN46: 46386 | BO46: 43152 | BP46: BANL074 | BQ46: SCDP | BR46: Subcontractor Direct Payment | CG46: 45657 | CH46: P01 | CI46: 43152 | CJ46: PJF_TASKS | CK46: FINANCIAL
B47: OK | D47: CREATE | E47: BIL-1007986 | F47: TESTME-FR03319FR-BANL07401-GUAD>Habitation des Jésuites [3319_BANL07401] | G47: TESTME-FR03319FR-BANL07401-GUAD>Habitation des Jésuites [3319_BANL07401] | H47: DRAFT | I47: EGIS BATIMENTS ILE DE FRANCE | J47: EGIS BATIMENTS ILE DE FRANCE | K47: SL-Buildings-CC-12-IDMI-01-Ile de France-BU-FR03305FR_EGIS BAT IDF | L47: SL-Buildings-CC-12-IDMI-01-Ile de France-BU-FR03305FR_EGIS BAT IDF | M47: EGIS BATIMENTS ILE DE FRANCE Billable E&SC Small Project | N47: EGIS BATIMENTS ILE DE FRANCE Billable E&SC Small Project | V47: EUR | X47: Corporate | Y47: T | Z47: FALSE | AA47: FALSE | AB47: TRUE | AC47: TRUE | AD47: E - Etudes | AE47: P02 | AG47: FINANCIAL | BN47: 46386 | BO47: 43152 | BP47: BANL074 | BQ47: SCDP | BR47: Subcontractor Direct Payment | CG47: 46386 | CH47: P02 | CI47: 43152 | CJ47: PJF_TASKS | CK47: FINANCIAL
B48: OK | D48: CREATE | E48: BIL-1007986 | F48: TESTME-FR03319FR-BANL07401-GUAD>Habitation des Jésuites [3319_BANL07401] | G48: TESTME-FR03319FR-BANL07401-GUAD>Habitation des Jésuites [3319_BANL07401] | H48: DRAFT | I48: EGIS BATIMENTS ILE DE FRANCE | J48: EGIS BATIMENTS ILE DE FRANCE | K48: SL-Buildings-CC-12-IDMI-01-Ile de France-BU-FR03305FR_EGIS BAT IDF | L48: SL-Buildings-CC-12-IDMI-01-Ile de France-BU-FR03305FR_EGIS BAT IDF | M48: EGIS BATIMENTS ILE DE FRANCE Billable E&SC Small Project | N48: EGIS BATIMENTS ILE DE FRANCE Billable E&SC Small Project | V48: EUR | X48: Corporate | Y48: T | Z48: FALSE | AA48: FALSE | AB48: TRUE | AC48: TRUE | AD48: T - Travaux | AE48: P03 | AG48: FINANCIAL | BN48: 46386 | BO48: 43152 | BP48: BANL074 | BQ48: SCDP | BR48: Subcontractor Direct Payment | CG48: 46386 | CH48: P03 | CI48: 43152 | CJ48: PJF_TASKS | CK48: FINANCIAL
B49: OK | D49: CREATE | E49: BIL-1007986 | F49: TESTME-FR03319FR-BANL07401-GUAD>Habitation des Jésuites [3319_BANL07401] | G49: TESTME-FR03319FR-BANL07401-GUAD>Habitation des Jésuites [3319_BANL07401] | H49: DRAFT | I49: EGIS BATIMENTS ILE DE FRANCE | J49: EGIS BATIMENTS ILE DE FRANCE | K49: SL-Buildings-CC-12-IDMI-01-Ile de France-BU-FR03305FR_EGIS BAT IDF | L49: SL-Buildings-CC-12-IDMI-01-Ile de France-BU-FR03305FR_EGIS BAT IDF | M49: EGIS BATIMENTS ILE DE FRANCE Billable E&SC Small Project | N49: EGIS BATIMENTS ILE DE FRANCE Billable E&SC Small Project | V49: EUR | X49: Corporate | Y49: T | Z49: FALSE | AA49: FALSE | AB49: TRUE | AC49: TRUE | AD49: Facturation Milestone Oracle 2025 | AE49: P97 | AG49: FINANCIAL | BN49: 46386 | BO49: 43152 | BP49: BANL074 | BQ49: SCDP | BR49: Subcontractor Direct Payment | CG49: 46386 | CH49: P97 | CI49: 43152 | CJ49: PJF_TASKS | CK49: FINANCIAL
B50: OK | D50: CREATE | E50: BIL-1007986 | F50: TESTME-FR03319FR-BANL07401-GUAD>Habitation des Jésuites [3319_BANL07401] | G50: TESTME-FR03319FR-BANL07401-GUAD>Habitation des Jésuites [3319_BANL07401] | H50: DRAFT | I50: EGIS BATIMENTS ILE DE FRANCE | J50: EGIS BATIMENTS ILE DE FRANCE | K50: SL-Buildings-CC-12-IDMI-01-Ile de France-BU-FR03305FR_EGIS BAT IDF | L50: SL-Buildings-CC-12-IDMI-01-Ile de France-BU-FR03305FR_EGIS BAT IDF | M50: EGIS BATIMENTS ILE DE FRANCE Billable E&SC Small Project | N50: EGIS BATIMENTS ILE DE FRANCE Billable E&SC Small Project | V50: EUR | X50: Corporate | Y50: T | Z50: FALSE | AA50: FALSE | AB50: TRUE | AC50: TRUE | AV50: Project Classification | AW50: Client Project | BN50: 46386 | BO50: 43152 | BP50: BANL074 | BQ50: SCDP | BR50: Subcontractor Direct Payment
B51: OK | D51: CREATE | E51: BIL-1007986 | F51: TESTME-FR03319FR-BANL07401-GUAD>Habitation des Jésuites [3319_BANL07401] | G51: TESTME-FR03319FR-BANL07401-GUAD>Habitation des Jésuites [3319_BANL07401] | H51: DRAFT | I51: EGIS BATIMENTS ILE DE FRANCE | J51: EGIS BATIMENTS ILE DE FRANCE | K51: SL-Buildings-CC-12-IDMI-01-Ile de France-BU-FR03305FR_EGIS BAT IDF | L51: SL-Buildings-CC-12-IDMI-01-Ile de France-BU-FR03305FR_EGIS BAT IDF | M51: EGIS BATIMENTS ILE DE FRANCE Billable E&SC Small Project | N51: EGIS BATIMENTS ILE DE FRANCE Billable E&SC Small Project | V51: EUR | X51: Corporate | Y51: T | Z51: FALSE | AA51: FALSE | AB51: TRUE | AC51: TRUE | AS51: Regis.AUBERT@egis-group.com | AT51: Project Manager | AU51: 44502 | BN51: 46386 | BO51: 43152 | BP51: BANL074 | BQ51: SCDP | BR51: Subcontractor Direct Payment
B52: OK | D52: CREATE | E52: BIL-1007986 | F52: TESTME-FR03319FR-BANL07401-GUAD>Habitation des Jésuites [3319_BANL07401] | G52: TESTME-FR03319FR-BANL07401-GUAD>Habitation des Jésuites [3319_BANL07401] | H52: DRAFT | I52: EGIS BATIMENTS ILE DE FRANCE | J52: EGIS BATIMENTS ILE DE FRANCE | K52: SL-Buildings-CC-12-IDMI-01-Ile de France-BU-FR03305FR_EGIS BAT IDF | L52: SL-Buildings-CC-12-IDMI-01-Ile de France-BU-FR03305FR_EGIS BAT IDF | M52: EGIS BATIMENTS ILE DE FRANCE Billable E&SC Small Project | N52: EGIS BATIMENTS ILE DE FRANCE Billable E&SC Small Project | V52: EUR | X52: Corporate | Y52: T | Z52: FALSE | AA52: FALSE | AB52: TRUE | AC52: TRUE | AS52: Rokhaya.NDIAYE@egis-group.com | AT52: Financial Controller | AU52: 43152 | BN52: 46386 | BO52: 43152 | BP52: BANL074 | BQ52: SCDP | BR52: Subcontractor Direct Payment
B53: OK | D53: CREATE | E53: BIL-1007986 | F53: TESTME-FR03319FR-BANL07401-GUAD>Habitation des Jésuites [3319_BANL07401] | G53: TESTME-FR03319FR-BANL07401-GUAD>Habitation des Jésuites [3319_BANL07401] | H53: DRAFT | I53: EGIS BATIMENTS ILE DE FRANCE | J53: EGIS BATIMENTS ILE DE FRANCE | K53: SL-Buildings-CC-12-IDMI-01-Ile de France-BU-FR03305FR_EGIS BAT IDF | L53: SL-Buildings-CC-12-IDMI-01-Ile de France-BU-FR03305FR_EGIS BAT IDF | M53: EGIS BATIMENTS ILE DE FRANCE Billable E&SC Small Project | N53: EGIS BATIMENTS ILE DE FRANCE Billable E&SC Small Project | V53: EUR | X53: Corporate | Y53: T | Z53: FALSE | AA53: FALSE | AB53: TRUE | AC53: TRUE | AS53: Cedric.ARNAUD@egis-group.com | AT53: Project Sponsor / RBLD Delegate | AU53: 45352 | BN53: 46386 | BO53: 43152 | BP53: BANL074 | BQ53: SCDP | BR53: Subcontractor Direct Payment
B54: OK | D54: CREATE | E54: BIL-1007986 | F54: TESTME-FR03319FR-BANL07401-GUAD>Habitation des Jésuites [3319_BANL07401] | G54: TESTME-FR03319FR-BANL07401-GUAD>Habitation des Jésuites [3319_BANL07401] | H54: DRAFT | I54: EGIS BATIMENTS ILE DE FRANCE | J54: EGIS BATIMENTS ILE DE FRANCE | K54: SL-Buildings-CC-12-IDMI-01-Ile de France-BU-FR03305FR_EGIS BAT IDF | L54: SL-Buildings-CC-12-IDMI-01-Ile de France-BU-FR03305FR_EGIS BAT IDF | M54: EGIS BATIMENTS ILE DE FRANCE Billable E&SC Small Project | N54: EGIS BATIMENTS ILE DE FRANCE Billable E&SC Small Project | V54: EUR | X54: Corporate | Y54: T | Z54: FALSE | AA54: FALSE | AB54: TRUE | AC54: TRUE | AS54: Sebastien.PLICHON@egis-group.com | AT54: RBLD | AU54: 43152 | BN54: 46386 | BO54: 43152 | BP54: BANL074 | BQ54: SCDP | BR54: Subcontractor Direct Payment
B55: OK | D55: CREATE | E55: BIL-1007986 | F55: TESTME-FR03319FR-BANL07401-GUAD>Habitation des Jésuites [3319_BANL07401] | G55: TESTME-FR03319FR-BANL07401-GUAD>Habitation des Jésuites [3319_BANL07401] | H55: DRAFT | I55: EGIS BATIMENTS ILE DE FRANCE | J55: EGIS BATIMENTS ILE DE FRANCE | K55: SL-Buildings-CC-12-IDMI-01-Ile de France-BU-FR03305FR_EGIS BAT IDF | L55: SL-Buildings-CC-12-IDMI-01-Ile de France-BU-FR03305FR_EGIS BAT IDF | M55: EGIS BATIMENTS ILE DE FRANCE Billable E&SC Small Project | N55: EGIS BATIMENTS ILE DE FRANCE Billable E&SC Small Project | V55: EUR | X55: Corporate | Y55: T | Z55: FALSE | AA55: FALSE | AB55: TRUE | AC55: TRUE | AS55: Julien.LECORNET@egis-group.com | AT55: Project Manager | AU55: 45727 | BN55: 46386 | BO55: 43152 | BP55: BANL074 | BQ55: SCDP | BR55: Subcontractor Direct Payment
B56: OK | D56: CREATE | E56: BIL-1007986 | F56: TESTME-FR03319FR-BANL07401-GUAD>Habitation des Jésuites [3319_BANL07401] | G56: TESTME-FR03319FR-BANL07401-GUAD>Habitation des Jésuites [3319_BANL07401] | H56: DRAFT | I56: EGIS BATIMENTS ILE DE FRANCE | J56: EGIS BATIMENTS ILE DE FRANCE | K56: SL-Buildings-CC-12-IDMI-01-Ile de France-BU-FR03305FR_EGIS BAT IDF | L56: SL-Buildings-CC-12-IDMI-01-Ile de France-BU-FR03305FR_EGIS BAT IDF | M56: EGIS BATIMENTS ILE DE FRANCE Billable E&SC Small Project | N56: EGIS BATIMENTS ILE DE FRANCE Billable E&SC Small Project | V56: EUR | X56: Corporate | Y56: T | Z56: FALSE | AA56: FALSE | AB56: TRUE | AC56: TRUE | AS56: Cedric.ARNAUD@egis-group.com | AT56: Project Manager | AU56: 45658 | BN56: 46386 | BO56: 43152 | BP56: BANL074 | BQ56: SCDP | BR56: Subcontractor Direct Payment
B57: OK | D57: CREATE | E57: BIL-1007987 | F57: TESTME-FR03319FR-BAQL20501-GUAD>Hôtel 4 * ATHLETIC [3319_BAQL20501] | G57: TESTME-FR03319FR-BAQL20501-GUAD>Hôtel 4 * ATHLETIC [3319_BAQL20501] | H57: DRAFT | I57: EGIS BATIMENTS ILE DE FRANCE | J57: EGIS BATIMENTS ILE DE FRANCE | K57: SL-Buildings-CC-12-IDMI-01-Ile de France-BU-FR03305FR_EGIS BAT IDF | L57: SL-Buildings-CC-12-IDMI-01-Ile de France-BU-FR03305FR_EGIS BAT IDF | M57: EGIS BATIMENTS ILE DE FRANCE Billable E&SC Small Project | N57: EGIS BATIMENTS ILE DE FRANCE Billable E&SC Small Project | V57: EUR | X57: Corporate | Y57: T | Z57: FALSE | AA57: FALSE | AB57: TRUE | AC57: TRUE | AD57: P01 - Offre | AE57: P01 | AG57: FINANCIAL | BN57: 46752 | BO57: 44273 | BP57: BAQL205 | BQ57: STD | BR57: Standard | CG57: 45657 | CH57: P01 | CI57: 44273 | CJ57: PJF_TASKS | CK57: FINANCIAL
B58: OK | D58: CREATE | E58: BIL-1007987 | F58: TESTME-FR03319FR-BAQL20501-GUAD>Hôtel 4 * ATHLETIC [3319_BAQL20501] | G58: TESTME-FR03319FR-BAQL20501-GUAD>Hôtel 4 * ATHLETIC [3319_BAQL20501] | H58: DRAFT | I58: EGIS BATIMENTS ILE DE FRANCE | J58: EGIS BATIMENTS ILE DE FRANCE | K58: SL-Buildings-CC-12-IDMI-01-Ile de France-BU-FR03305FR_EGIS BAT IDF | L58: SL-Buildings-CC-12-IDMI-01-Ile de France-BU-FR03305FR_EGIS BAT IDF | M58: EGIS BATIMENTS ILE DE FRANCE Billable E&SC Small Project | N58: EGIS BATIMENTS ILE DE FRANCE Billable E&SC Small Project | V58: EUR | X58: Corporate | Y58: T | Z58: FALSE | AA58: FALSE | AB58: TRUE | AC58: TRUE | AD58: P02 - Phase E (ESQ/APS/APD) | AE58: P02 | AG58: FINANCIAL | BN58: 46752 | BO58: 44273 | BP58: BAQL205 | BQ58: STD | BR58: Standard | CG58: 46752 | CH58: P02 | CI58: 44273 | CJ58: PJF_TASKS | CK58: FINANCIAL
B59: OK | D59: CREATE | E59: BIL-1007987 | F59: TESTME-FR03319FR-BAQL20501-GUAD>Hôtel 4 * ATHLETIC [3319_BAQL20501] | G59: TESTME-FR03319FR-BAQL20501-GUAD>Hôtel 4 * ATHLETIC [3319_BAQL20501] | H59: DRAFT | I59: EGIS BATIMENTS ILE DE FRANCE | J59: EGIS BATIMENTS ILE DE FRANCE | K59: SL-Buildings-CC-12-IDMI-01-Ile de France-BU-FR03305FR_EGIS BAT IDF | L59: SL-Buildings-CC-12-IDMI-01-Ile de France-BU-FR03305FR_EGIS BAT IDF | M59: EGIS BATIMENTS ILE DE FRANCE Billable E&SC Small Project | N59: EGIS BATIMENTS ILE DE FRANCE Billable E&SC Small Project | V59: EUR | X59: Corporate | Y59: T | Z59: FALSE | AA59: FALSE | AB59: TRUE | AC59: TRUE | AD59: P03 - Phase J PRO | AE59: P03 | AG59: FINANCIAL | BN59: 46752 | BO59: 44273 | BP59: BAQL205 | BQ59: STD | BR59: Standard | CG59: 46752 | CH59: P03 | CI59: 44273 | CJ59: PJF_TASKS | CK59: FINANCIAL
B60: OK | D60: CREATE | E60: BIL-1007987 | F60: TESTME-FR03319FR-BAQL20501-GUAD>Hôtel 4 * ATHLETIC [3319_BAQL20501] | G60: TESTME-FR03319FR-BAQL20501-GUAD>Hôtel 4 * ATHLETIC [3319_BAQL20501] | H60: DRAFT | I60: EGIS BATIMENTS ILE DE FRANCE | J60: EGIS BATIMENTS ILE DE FRANCE | K60: SL-Buildings-CC-12-IDMI-01-Ile de France-BU-FR03305FR_EGIS BAT IDF | L60: SL-Buildings-CC-12-IDMI-01-Ile de France-BU-FR03305FR_EGIS BAT IDF | M60: EGIS BATIMENTS ILE DE FRANCE Billable E&SC Small Project | N60: EGIS BATIMENTS ILE DE FRANCE Billable E&SC Small Project | V60: EUR | X60: Corporate | Y60: T | Z60: FALSE | AA60: FALSE | AB60: TRUE | AC60: TRUE | AD60: P04 - Phase M (AMT/ACT) | AE60: P04 | AG60: FINANCIAL | BN60: 46752 | BO60: 44273 | BP60: BAQL205 | BQ60: STD | BR60: Standard | CG60: 46752 | CH60: P04 | CI60: 44273 | CJ60: PJF_TASKS | CK60: FINANCIAL
B61: OK | D61: CREATE | E61: BIL-1007987 | F61: TESTME-FR03319FR-BAQL20501-GUAD>Hôtel 4 * ATHLETIC [3319_BAQL20501] | G61: TESTME-FR03319FR-BAQL20501-GUAD>Hôtel 4 * ATHLETIC [3319_BAQL20501] | H61: DRAFT | I61: EGIS BATIMENTS ILE DE FRANCE | J61: EGIS BATIMENTS ILE DE FRANCE | K61: SL-Buildings-CC-12-IDMI-01-Ile de France-BU-FR03305FR_EGIS BAT IDF | L61: SL-Buildings-CC-12-IDMI-01-Ile de France-BU-FR03305FR_EGIS BAT IDF | M61: EGIS BATIMENTS ILE DE FRANCE Billable E&SC Small Project | N61: EGIS BATIMENTS ILE DE FRANCE Billable E&SC Small Project | V61: EUR | X61: Corporate | Y61: T | Z61: FALSE | AA61: FALSE | AB61: TRUE | AC61: TRUE | AD61: P05 - Phase T (VISA OPC) | AE61: P05 | AG61: FINANCIAL | BN61: 46752 | BO61: 44273 | BP61: BAQL205 | BQ61: STD | BR61: Standard | CG61: 46752 | CH61: P05 | CI61: 44273 | CJ61: PJF_TASKS | CK61: FINANCIAL
B62: OK | D62: CREATE | E62: BIL-1007987 | F62: TESTME-FR03319FR-BAQL20501-GUAD>Hôtel 4 * ATHLETIC [3319_BAQL20501] | G62: TESTME-FR03319FR-BAQL20501-GUAD>Hôtel 4 * ATHLETIC [3319_BAQL20501] | H62: DRAFT | I62: EGIS BATIMENTS ILE DE FRANCE | J62: EGIS BATIMENTS ILE DE FRANCE | K62: SL-Buildings-CC-12-IDMI-01-Ile de France-BU-FR03305FR_EGIS BAT IDF | L62: SL-Buildings-CC-12-IDMI-01-Ile de France-BU-FR03305FR_EGIS BAT IDF | M62: EGIS BATIMENTS ILE DE FRANCE Billable E&SC Small Project | N62: EGIS BATIMENTS ILE DE FRANCE Billable E&SC Small Project | V62: EUR | X62: Corporate | Y62: T | Z62: FALSE | AA62: FALSE | AB62: TRUE | AC62: TRUE | AD62: Facturation Milestone Oracle 2025 | AE62: P97 | AG62: FINANCIAL | BN62: 46752 | BO62: 44273 | BP62: BAQL205 | BQ62: STD | BR62: Standard | CG62: 46752 | CH62: P97 | CI62: 44273 | CJ62: PJF_TASKS | CK62: FINANCIAL
B63: OK | D63: CREATE | E63: BIL-1007987 | F63: TESTME-FR03319FR-BAQL20501-GUAD>Hôtel 4 * ATHLETIC [3319_BAQL20501] | G63: TESTME-FR03319FR-BAQL20501-GUAD>Hôtel 4 * ATHLETIC [3319_BAQL20501] | H63: DRAFT | I63: EGIS BATIMENTS ILE DE FRANCE | J63: EGIS BATIMENTS ILE DE FRANCE | K63: SL-Buildings-CC-12-IDMI-01-Ile de France-BU-FR03305FR_EGIS BAT IDF | L63: SL-Buildings-CC-12-IDMI-01-Ile de France-BU-FR03305FR_EGIS BAT IDF | M63: EGIS BATIMENTS ILE DE FRANCE Billable E&SC Small Project | N63: EGIS BATIMENTS ILE DE FRANCE Billable E&SC Small Project | V63: EUR | X63: Corporate | Y63: T | Z63: FALSE | AA63: FALSE | AB63: TRUE | AC63: TRUE | AD63: Facturation Intragroupe | AE63: P98 | AG63: FINANCIAL | BN63: 46752 | BO63: 44273 | BP63: BAQL205 | BQ63: STD | BR63: Standard | CG63: 46752 | CH63: P98 | CI63: 44273 | CJ63: PJF_TASKS | CK63: FINANCIAL
B64: OK | D64: CREATE | E64: BIL-1007987 | F64: TESTME-FR03319FR-BAQL20501-GUAD>Hôtel 4 * ATHLETIC [3319_BAQL20501] | G64: TESTME-FR03319FR-BAQL20501-GUAD>Hôtel 4 * ATHLETIC [3319_BAQL20501] | H64: DRAFT | I64: EGIS BATIMENTS ILE DE FRANCE | J64: EGIS BATIMENTS ILE DE FRANCE | K64: SL-Buildings-CC-12-IDMI-01-Ile de France-BU-FR03305FR_EGIS BAT IDF | L64: SL-Buildings-CC-12-IDMI-01-Ile de France-BU-FR03305FR_EGIS BAT IDF | M64: EGIS BATIMENTS ILE DE FRANCE Billable E&SC Small Project | N64: EGIS BATIMENTS ILE DE FRANCE Billable E&SC Small Project | V64: EUR | X64: Corporate | Y64: T | Z64: FALSE | AA64: FALSE | AB64: TRUE | AC64: TRUE | AV64: Project Classification | AW64: Client Project | BN64: 46752 | BO64: 44273 | BP64: BAQL205 | BQ64: STD | BR64: Standard
B65: OK | D65: CREATE | E65: BIL-1007987 | F65: TESTME-FR03319FR-BAQL20501-GUAD>Hôtel 4 * ATHLETIC [3319_BAQL20501] | G65: TESTME-FR03319FR-BAQL20501-GUAD>Hôtel 4 * ATHLETIC [3319_BAQL20501] | H65: DRAFT | I65: EGIS BATIMENTS ILE DE FRANCE | J65: EGIS BATIMENTS ILE DE FRANCE | K65: SL-Buildings-CC-12-IDMI-01-Ile de France-BU-FR03305FR_EGIS BAT IDF | L65: SL-Buildings-CC-12-IDMI-01-Ile de France-BU-FR03305FR_EGIS BAT IDF | M65: EGIS BATIMENTS ILE DE FRANCE Billable E&SC Small Project | N65: EGIS BATIMENTS ILE DE FRANCE Billable E&SC Small Project | V65: EUR | X65: Corporate | Y65: T | Z65: FALSE | AA65: FALSE | AB65: TRUE | AC65: TRUE | AS65: Elie.ELIAS@egis-group.com | AT65: Project Manager | AU65: 44273 | BN65: 46752 | BO65: 44273 | BP65: BAQL205 | BQ65: STD | BR65: Standard
B66: OK | D66: CREATE | E66: BIL-1007987 | F66: TESTME-FR03319FR-BAQL20501-GUAD>Hôtel 4 * ATHLETIC [3319_BAQL20501] | G66: TESTME-FR03319FR-BAQL20501-GUAD>Hôtel 4 * ATHLETIC [3319_BAQL20501] | H66: DRAFT | I66: EGIS BATIMENTS ILE DE FRANCE | J66: EGIS BATIMENTS ILE DE FRANCE | K66: SL-Buildings-CC-12-IDMI-01-Ile de France-BU-FR03305FR_EGIS BAT IDF | L66: SL-Buildings-CC-12-IDMI-01-Ile de France-BU-FR03305FR_EGIS BAT IDF | M66: EGIS BATIMENTS ILE DE FRANCE Billable E&SC Small Project | N66: EGIS BATIMENTS ILE DE FRANCE Billable E&SC Small Project | V66: EUR | X66: Corporate | Y66: T | Z66: FALSE | AA66: FALSE | AB66: TRUE | AC66: TRUE | AS66: Rokhaya.NDIAYE@egis-group.com | AT66: Financial Controller | AU66: 44273 | BN66: 46752 | BO66: 44273 | BP66: BAQL205 | BQ66: STD | BR66: Standard
B67: OK | D67: CREATE | E67: BIL-1007987 | F67: TESTME-FR03319FR-BAQL20501-GUAD>Hôtel 4 * ATHLETIC [3319_BAQL20501] | G67: TESTME-FR03319FR-BAQL20501-GUAD>Hôtel 4 * ATHLETIC [3319_BAQL20501] | H67: DRAFT | I67: EGIS BATIMENTS ILE DE FRANCE | J67: EGIS BATIMENTS ILE DE FRANCE | K67: SL-Buildings-CC-12-IDMI-01-Ile de France-BU-FR03305FR_EGIS BAT IDF | L67: SL-Buildings-CC-12-IDMI-01-Ile de France-BU-FR03305FR_EGIS BAT IDF | M67: EGIS BATIMENTS ILE DE FRANCE Billable E&SC Small Project | N67: EGIS BATIMENTS ILE DE FRANCE Billable E&SC Small Project | V67: EUR | X67: Corporate | Y67: T | Z67: FALSE | AA67: FALSE | AB67: TRUE | AC67: TRUE | AS67: Sebastien.PLICHON@egis-group.com | AT67: RBLD | AU67: 44273 | BN67: 46752 | BO67: 44273 | BP67: BAQL205 | BQ67: STD | BR67: Standard
B68: OK | D68: CREATE | E68: BIL-1007987 | F68: TESTME-FR03319FR-BAQL20501-GUAD>Hôtel 4 * ATHLETIC [3319_BAQL20501] | G68: TESTME-FR03319FR-BAQL20501-GUAD>Hôtel 4 * ATHLETIC [3319_BAQL20501] | H68: DRAFT | I68: EGIS BATIMENTS ILE DE FRANCE | J68: EGIS BATIMENTS ILE DE FRANCE | K68: SL-Buildings-CC-12-IDMI-01-Ile de France-BU-FR03305FR_EGIS BAT IDF | L68: SL-Buildings-CC-12-IDMI-01-Ile de France-BU-FR03305FR_EGIS BAT IDF | M68: EGIS BATIMENTS ILE DE FRANCE Billable E&SC Small Project | N68: EGIS BATIMENTS ILE DE FRANCE Billable E&SC Small Project | V68: EUR | X68: Corporate | Y68: T | Z68: FALSE | AA68: FALSE | AB68: TRUE | AC68: TRUE | AS68: Cedric.ARNAUD@egis-group.com | AT68: Project Sponsor / RBLD Delegate | AU68: 45658 | BN68: 46752 | BO68: 44273 | BP68: BAQL205 | BQ68: STD | BR68: Standard
B69: OK | D69: CREATE | E69: BIL-1007987 | F69: TESTME-FR03319FR-BAQL20501-GUAD>Hôtel 4 * ATHLETIC [3319_BAQL20501] | G69: TESTME-FR03319FR-BAQL20501-GUAD>Hôtel 4 * ATHLETIC [3319_BAQL20501] | H69: DRAFT | I69: EGIS BATIMENTS ILE DE FRANCE | J69: EGIS BATIMENTS ILE DE FRANCE | K69: SL-Buildings-CC-12-IDMI-01-Ile de France-BU-FR03305FR_EGIS BAT IDF | L69: SL-Buildings-CC-12-IDMI-01-Ile de France-BU-FR03305FR_EGIS BAT IDF | M69: EGIS BATIMENTS ILE DE FRANCE Billable E&SC Small Project | N69: EGIS BATIMENTS ILE DE FRANCE Billable E&SC Small Project | V69: EUR | X69: Corporate | Y69: T | Z69: FALSE | AA69: FALSE | AB69: TRUE | AC69: TRUE | AS69: Cedric.ARNAUD@egis-group.com | AT69: Project Manager | AU69: 45658 | BN69: 46752 | BO69: 44273 | BP69: BAQL205 | BQ69: STD | BR69: Standard
B70: OK | D70: CREATE | E70: BIL-1007988 | F70: TESTME-FR03319FR-BARD30601-GUAD>OPC COMMISSARIAT B/TERRE [3319_BARD30601] | G70: TESTME-FR03319FR-BARD30601-GUAD>OPC COMMISSARIAT B/TERRE [3319_BARD30601] | H70: DRAFT | I70: EGIS BATIMENTS ILE DE FRANCE | J70: EGIS BATIMENTS ILE DE FRANCE | K70: SL-Buildings-CC-12-IDMI-01-Ile de France-BU-FR03305FR_EGIS BAT IDF | L70: SL-Buildings-CC-12-IDMI-01-Ile de France-BU-FR03305FR_EGIS BAT IDF | M70: EGIS BATIMENTS ILE DE FRANCE Billable E&SC Small Project | N70: EGIS BATIMENTS ILE DE FRANCE Billable E&SC Small Project | V70: EUR | X70: Corporate | Y70: T | Z70: FALSE | AA70: FALSE | AB70: TRUE | AC70: TRUE | AD70: P01 - Offre | AE70: P01 | AG70: FINANCIAL | BN70: 46295 | BO70: 44490 | BP70: BARD306 | BQ70: STD | BR70: Standard | CG70: 45657 | CH70: P01 | CI70: 44490 | CJ70: PJF_TASKS | CK70: FINANCIAL
B71: OK | D71: CREATE | E71: BIL-1007988 | F71: TESTME-FR03319FR-BARD30601-GUAD>OPC COMMISSARIAT B/TERRE [3319_BARD30601] | G71: TESTME-FR03319FR-BARD30601-GUAD>OPC COMMISSARIAT B/TERRE [3319_BARD30601] | H71: DRAFT | I71: EGIS BATIMENTS ILE DE FRANCE | J71: EGIS BATIMENTS ILE DE FRANCE | K71: SL-Buildings-CC-12-IDMI-01-Ile de France-BU-FR03305FR_EGIS BAT IDF | L71: SL-Buildings-CC-12-IDMI-01-Ile de France-BU-FR03305FR_EGIS BAT IDF | M71: EGIS BATIMENTS ILE DE FRANCE Billable E&SC Small Project | N71: EGIS BATIMENTS ILE DE FRANCE Billable E&SC Small Project | V71: EUR | X71: Corporate | Y71: T | Z71: FALSE | AA71: FALSE | AB71: TRUE | AC71: TRUE | AD71: P02 - Phase 02 | AE71: P02 | AG71: FINANCIAL | BN71: 46295 | BO71: 44490 | BP71: BARD306 | BQ71: STD | BR71: Standard | CG71: 46295 | CH71: P02 | CI71: 44490 | CJ71: PJF_TASKS | CK71: FINANCIAL
B72: OK | D72: CREATE | E72: BIL-1007988 | F72: TESTME-FR03319FR-BARD30601-GUAD>OPC COMMISSARIAT B/TERRE [3319_BARD30601] | G72: TESTME-FR03319FR-BARD30601-GUAD>OPC COMMISSARIAT B/TERRE [3319_BARD30601] | H72: DRAFT | I72: EGIS BATIMENTS ILE DE FRANCE | J72: EGIS BATIMENTS ILE DE FRANCE | K72: SL-Buildings-CC-12-IDMI-01-Ile de France-BU-FR03305FR_EGIS BAT IDF | L72: SL-Buildings-CC-12-IDMI-01-Ile de France-BU-FR03305FR_EGIS BAT IDF | M72: EGIS BATIMENTS ILE DE FRANCE Billable E&SC Small Project | N72: EGIS BATIMENTS ILE DE FRANCE Billable E&SC Small Project | V72: EUR | X72: Corporate | Y72: T | Z72: FALSE | AA72: FALSE | AB72: TRUE | AC72: TRUE | AD72: Facturation Milestone Oracle 2025 | AE72: P97 | AG72: FINANCIAL | BN72: 46295 | BO72: 44490 | BP72: BARD306 | BQ72: STD | BR72: Standard | CG72: 46295 | CH72: P97 | CI72: 44490 | CJ72: PJF_TASKS | CK72: FINANCIAL
B73: OK | D73: CREATE | E73: BIL-1007988 | F73: TESTME-FR03319FR-BARD30601-GUAD>OPC COMMISSARIAT B/TERRE [3319_BARD30601] | G73: TESTME-FR03319FR-BARD30601-GUAD>OPC COMMISSARIAT B/TERRE [3319_BARD30601] | H73: DRAFT | I73: EGIS BATIMENTS ILE DE FRANCE | J73: EGIS BATIMENTS ILE DE FRANCE | K73: SL-Buildings-CC-12-IDMI-01-Ile de France-BU-FR03305FR_EGIS BAT IDF | L73: SL-Buildings-CC-12-IDMI-01-Ile de France-BU-FR03305FR_EGIS BAT IDF | M73: EGIS BATIMENTS ILE DE FRANCE Billable E&SC Small Project | N73: EGIS BATIMENTS ILE DE FRANCE Billable E&SC Small Project | V73: EUR | X73: Corporate | Y73: T | Z73: FALSE | AA73: FALSE | AB73: TRUE | AC73: TRUE | AV73: Project Classification | AW73: Client Project | BN73: 46295 | BO73: 44490 | BP73: BARD306 | BQ73: STD | BR73: Standard
B74: OK | D74: CREATE | E74: BIL-1007988 | F74: TESTME-FR03319FR-BARD30601-GUAD>OPC COMMISSARIAT B/TERRE [3319_BARD30601] | G74: TESTME-FR03319FR-BARD30601-GUAD>OPC COMMISSARIAT B/TERRE [3319_BARD30601] | H74: DRAFT | I74: EGIS BATIMENTS ILE DE FRANCE | J74: EGIS BATIMENTS ILE DE FRANCE | K74: SL-Buildings-CC-12-IDMI-01-Ile de France-BU-FR03305FR_EGIS BAT IDF | L74: SL-Buildings-CC-12-IDMI-01-Ile de France-BU-FR03305FR_EGIS BAT IDF | M74: EGIS BATIMENTS ILE DE FRANCE Billable E&SC Small Project | N74: EGIS BATIMENTS ILE DE FRANCE Billable E&SC Small Project | V74: EUR | X74: Corporate | Y74: T | Z74: FALSE | AA74: FALSE | AB74: TRUE | AC74: TRUE | AS74: Regis.AUBERT@egis-group.com | AT74: Project Manager | AU74: 44502 | BN74: 46295 | BO74: 44490 | BP74: BARD306 | BQ74: STD | BR74: Standard
B75: OK | D75: CREATE | E75: BIL-1007988 | F75: TESTME-FR03319FR-BARD30601-GUAD>OPC COMMISSARIAT B/TERRE [3319_BARD30601] | G75: TESTME-FR03319FR-BARD30601-GUAD>OPC COMMISSARIAT B/TERRE [3319_BARD30601] | H75: DRAFT | I75: EGIS BATIMENTS ILE DE FRANCE | J75: EGIS BATIMENTS ILE DE FRANCE | K75: SL-Buildings-CC-12-IDMI-01-Ile de France-BU-FR03305FR_EGIS BAT IDF | L75: SL-Buildings-CC-12-IDMI-01-Ile de France-BU-FR03305FR_EGIS BAT IDF | M75: EGIS BATIMENTS ILE DE FRANCE Billable E&SC Small Project | N75: EGIS BATIMENTS ILE DE FRANCE Billable E&SC Small Project | V75: EUR | X75: Corporate | Y75: T | Z75: FALSE | AA75: FALSE | AB75: TRUE | AC75: TRUE | AS75: Rokhaya.NDIAYE@egis-group.com | AT75: Financial Controller | AU75: 44490 | BN75: 46295 | BO75: 44490 | BP75: BARD306 | BQ75: STD | BR75: Standard
B76: OK | D76: CREATE | E76: BIL-1007988 | F76: TESTME-FR03319FR-BARD30601-GUAD>OPC COMMISSARIAT B/TERRE [3319_BARD30601] | G76: TESTME-FR03319FR-BARD30601-GUAD>OPC COMMISSARIAT B/TERRE [3319_BARD30601] | H76: DRAFT | I76: EGIS BATIMENTS ILE DE FRANCE | J76: EGIS BATIMENTS ILE DE FRANCE | K76: SL-Buildings-CC-12-IDMI-01-Ile de France-BU-FR03305FR_EGIS BAT IDF | L76: SL-Buildings-CC-12-IDMI-01-Ile de France-BU-FR03305FR_EGIS BAT IDF | M76: EGIS BATIMENTS ILE DE FRANCE Billable E&SC Small Project | N76: EGIS BATIMENTS ILE DE FRANCE Billable E&SC Small Project | V76: EUR | X76: Corporate | Y76: T | Z76: FALSE | AA76: FALSE | AB76: TRUE | AC76: TRUE | AS76: Sebastien.PLICHON@egis-group.com | AT76: RBLD | AU76: 44490 | BN76: 46295 | BO76: 44490 | BP76: BARD306 | BQ76: STD | BR76: Standard
B77: OK | D77: CREATE | E77: BIL-1007988 | F77: TESTME-FR03319FR-BARD30601-GUAD>OPC COMMISSARIAT B/TERRE [3319_BARD30601] | G77: TESTME-FR03319FR-BARD30601-GUAD>OPC COMMISSARIAT B/TERRE [3319_BARD30601] | H77: DRAFT | I77: EGIS BATIMENTS ILE DE FRANCE | J77: EGIS BATIMENTS ILE DE FRANCE | K77: SL-Buildings-CC-12-IDMI-01-Ile de France-BU-FR03305FR_EGIS BAT IDF | L77: SL-Buildings-CC-12-IDMI-01-Ile de France-BU-FR03305FR_EGIS BAT IDF | M77: EGIS BATIMENTS ILE DE FRANCE Billable E&SC Small Project | N77: EGIS BATIMENTS ILE DE FRANCE Billable E&SC Small Project | V77: EUR | X77: Corporate | Y77: T | Z77: FALSE | AA77: FALSE | AB77: TRUE | AC77: TRUE | AS77: Cedric.ARNAUD@egis-group.com | AT77: Project Sponsor / RBLD Delegate | AU77: 45658 | BN77: 46295 | BO77: 44490 | BP77: BARD306 | BQ77: STD | BR77: Standard
B78: OK | D78: CREATE | E78: BIL-1007988 | F78: TESTME-FR03319FR-BARD30601-GUAD>OPC COMMISSARIAT B/TERRE [3319_BARD30601] | G78: TESTME-FR03319FR-BARD30601-GUAD>OPC COMMISSARIAT B/TERRE [3319_BARD30601] | H78: DRAFT | I78: EGIS BATIMENTS ILE DE FRANCE | J78: EGIS BATIMENTS ILE DE FRANCE | K78: SL-Buildings-CC-12-IDMI-01-Ile de France-BU-FR03305FR_EGIS BAT IDF | L78: SL-Buildings-CC-12-IDMI-01-Ile de France-BU-FR03305FR_EGIS BAT IDF | M78: EGIS BATIMENTS ILE DE FRANCE Billable E&SC Small Project | N78: EGIS BATIMENTS ILE DE FRANCE Billable E&SC Small Project | V78: EUR | X78: Corporate | Y78: T | Z78: FALSE | AA78: FALSE | AB78: TRUE | AC78: TRUE | AS78: Julien.LECORNET@egis-group.com | AT78: Project Manager | AU78: 45727 | BN78: 46295 | BO78: 44490 | BP78: BARD306 | BQ78: STD | BR78: Standard
E79: FR03319FR-BARD30601 | F79: TESTME-FR03319FR-BARD30601-GUAD>OPC COMMISSARIAT B/TERRE [3319_BARD30601] | G79: TESTME-FR03319FR-BARD30601-GUAD>OPC COMMISSARIAT B/TERRE [3319_BARD30601] | H79: ACTIVE | I79: EGIS BATIMENTS ILE DE FRANCE | J79: EGIS BATIMENTS ILE DE FRANCE | K79: SL-Buildings-CC-12-IDMI-01-Ile de France-BU-FR03305FR_EGIS BAT IDF | L79: SL-Buildings-CC-12-IDMI-01-Ile de France-BU-FR03305FR_EGIS BAT IDF | M79: EGIS BATIMENTS ILE DE FRANCE Billable E&SC Small Project | N79: EGIS BATIMENTS ILE DE FRANCE Billable E&SC Small Project | V79: EUR | X79: Corporate | Y79: T | Z79: FALSE | AA79: FALSE | AB79: TRUE | AC79: TRUE | AS79: Cedric.ARNAUD@egis-group.com | AT79: Project Manager | AU79: 45658 | BN79: 46295 | BO79: 44490 | BP79: BARD306 | BQ79: STD | BR79: Standard
E80: FR03319FR-BAOF02401 | F80: GUAD>OPC nouveau CHU de Pointe-à-Pitre [3319_BAOF02401] | H80: ACTIVE | I80: EGIS BATIMENTS ANTILLES GUYANE | K80: SL-Buildings-CC-12-ANTI-01-Antilles Guyane-BU-FR03319FR_EGIS BAT ANT GUY | M80: EGIS BATIMENTS ANTILLES GUYANE Billable E&SC Small Project | V80: EUR | X80: Corporate | Y80: T | Z80: FALSE | AA80: FALSE | AB80: TRUE | AC80: TRUE | AD80: O - Offre | AE80: P01 | AF80: FR03319FR-BAOF02401 | AG80: FINANCIAL | BN80: 46295 | BO80: 43346 | BP80: BAOF024 | BQ80: STD | BR80: Standard | CG80: 46295 | CH80: P01 | CI80: 43346 | CJ80: PJF_TASKS | CK80: FINANCIAL
E81: FR03319FR-BAOF02401 | F81: GUAD>OPC nouveau CHU de Pointe-à-Pitre [3319_BAOF02401] | H81: ACTIVE | I81: EGIS BATIMENTS ANTILLES GUYANE | K81: SL-Buildings-CC-12-ANTI-01-Antilles Guyane-BU-FR03319FR_EGIS BAT ANT GUY | M81: EGIS BATIMENTS ANTILLES GUYANE Billable E&SC Small Project | V81: EUR | X81: Corporate | Y81: T | Z81: FALSE | AA81: FALSE | AB81: TRUE | AC81: TRUE | AD81: T- Travaux | AE81: P02 | AF81: FR03319FR-BAOF02401 | AG81: FINANCIAL | BN81: 46295 | BO81: 43346 | BP81: BAOF024 | BQ81: STD | BR81: Standard | CG81: 46295 | CH81: P02 | CI81: 43346 | CJ81: PJF_TASKS | CK81: FINANCIAL
E82: FR03319FR-BAOF02401 | F82: GUAD>OPC nouveau CHU de Pointe-à-Pitre [3319_BAOF02401] | H82: ACTIVE | I82: EGIS BATIMENTS ANTILLES GUYANE | K82: SL-Buildings-CC-12-ANTI-01-Antilles Guyane-BU-FR03319FR_EGIS BAT ANT GUY | M82: EGIS BATIMENTS ANTILLES GUYANE Billable E&SC Small Project | V82: EUR | X82: Corporate | Y82: T | Z82: FALSE | AA82: FALSE | AB82: TRUE | AC82: TRUE | AD82: Facturation Milestone Oracle 2025 | AE82: P97 | AF82: FR03319FR-BAOF02401 | AG82: FINANCIAL | BN82: 46295 | BO82: 43346 | BP82: BAOF024 | BQ82: STD | BR82: Standard | CG82: 46295 | CH82: P97 | CI82: 43346 | CJ82: PJF_TASKS | CK82: FINANCIAL
E83: FR03319FR-BAOF02401 | F83: GUAD>OPC nouveau CHU de Pointe-à-Pitre [3319_BAOF02401] | H83: ACTIVE | I83: EGIS BATIMENTS ANTILLES GUYANE | K83: SL-Buildings-CC-12-ANTI-01-Antilles Guyane-BU-FR03319FR_EGIS BAT ANT GUY | M83: EGIS BATIMENTS ANTILLES GUYANE Billable E&SC Small Project | V83: EUR | X83: Corporate | Y83: T | Z83: FALSE | AA83: FALSE | AB83: TRUE | AC83: TRUE | AV83: Project Classification | AW83: Client Project | BN83: 46295 | BO83: 43346 | BP83: BAOF024 | BQ83: STD | BR83: Standard
E84: FR03319FR-BAOF02401 | F84: GUAD>OPC nouveau CHU de Pointe-à-Pitre [3319_BAOF02401] | H84: ACTIVE | I84: EGIS BATIMENTS ANTILLES GUYANE | K84: SL-Buildings-CC-12-ANTI-01-Antilles Guyane-BU-FR03319FR_EGIS BAT ANT GUY | M84: EGIS BATIMENTS ANTILLES GUYANE Billable E&SC Small Project | V84: EUR | X84: Corporate | Y84: T | Z84: FALSE | AA84: FALSE | AB84: TRUE | AC84: TRUE | AS84: Jacqueline.JEAN-LOUIS@egis-group.com | AT84: Project Manager | AU84: 43346 | BN84: 46295 | BO84: 43346 | BP84: BAOF024 | BQ84: STD | BR84: Standard
E85: FR03319FR-BAOF02401 | F85: GUAD>OPC nouveau CHU de Pointe-à-Pitre [3319_BAOF02401] | H85: ACTIVE | I85: EGIS BATIMENTS ANTILLES GUYANE | K85: SL-Buildings-CC-12-ANTI-01-Antilles Guyane-BU-FR03319FR_EGIS BAT ANT GUY | M85: EGIS BATIMENTS ANTILLES GUYANE Billable E&SC Small Project | V85: EUR | X85: Corporate | Y85: T | Z85: FALSE | AA85: FALSE | AB85: TRUE | AC85: TRUE | AS85: Rokhaya.NDIAYE@egis-group.com | AT85: Financial Controller | AU85: 43346 | BN85: 46295 | BO85: 43346 | BP85: BAOF024 | BQ85: STD | BR85: Standard
E86: FR03319FR-BAOF02401 | F86: GUAD>OPC nouveau CHU de Pointe-à-Pitre [3319_BAOF02401] | H86: ACTIVE | I86: EGIS BATIMENTS ANTILLES GUYANE | K86: SL-Buildings-CC-12-ANTI-01-Antilles Guyane-BU-FR03319FR_EGIS BAT ANT GUY | M86: EGIS BATIMENTS ANTILLES GUYANE Billable E&SC Small Project | V86: EUR | X86: Corporate | Y86: T | Z86: FALSE | AA86: FALSE | AB86: TRUE | AC86: TRUE | AS86: Sebastien.PLICHON@egis-group.com | AT86: RBLD | AU86: 43346 | BN86: 46295 | BO86: 43346 | BP86: BAOF024 | BQ86: STD | BR86: Standard
E87: FR03319FR-BAOF02401 | F87: GUAD>OPC nouveau CHU de Pointe-à-Pitre [3319_BAOF02401] | H87: ACTIVE | I87: EGIS BATIMENTS ANTILLES GUYANE | K87: SL-Buildings-CC-12-ANTI-01-Antilles Guyane-BU-FR03319FR_EGIS BAT ANT GUY | M87: EGIS BATIMENTS ANTILLES GUYANE Billable E&SC Small Project | V87: EUR | X87: Corporate | Y87: T | Z87: FALSE | AA87: FALSE | AB87: TRUE | AC87: TRUE | AS87: Cedric.ARNAUD@egis-group.com | AT87: Project Sponsor / RBLD Delegate | AU87: 45658 | BN87: 46295 | BO87: 43346 | BP87: BAOF024 | BQ87: STD | BR87: Standard
E88: FR03319FR-BAOF02401 | F88: GUAD>OPC nouveau CHU de Pointe-à-Pitre [3319_BAOF02401] | H88: ACTIVE | I88: EGIS BATIMENTS ANTILLES GUYANE | K88: SL-Buildings-CC-12-ANTI-01-Antilles Guyane-BU-FR03319FR_EGIS BAT ANT GUY | M88: EGIS BATIMENTS ANTILLES GUYANE Billable E&SC Small Project | V88: EUR | X88: Corporate | Y88: T | Z88: FALSE | AA88: FALSE | AB88: TRUE | AC88: TRUE | AS88: Regis.AUBERT@egis-group.com | AT88: Project Manager | AU88: 45600 | BN88: 46295 | BO88: 43346 | BP88: BAOF024 | BQ88: STD | BR88: Standard
E89: FR03319FR-BAOF02401 | F89: GUAD>OPC nouveau CHU de Pointe-à-Pitre [3319_BAOF02401] | H89: ACTIVE | I89: EGIS BATIMENTS ANTILLES GUYANE | K89: SL-Buildings-CC-12-ANTI-01-Antilles Guyane-BU-FR03319FR_EGIS BAT ANT GUY | M89: EGIS BATIMENTS ANTILLES GUYANE Billable E&SC Small Project | V89: EUR | X89: Corporate | Y89: T | Z89: FALSE | AA89: FALSE | AB89: TRUE | AC89: TRUE | AS89: Cedric.ARNAUD@egis-group.com | AT89: Project Manager | AU89: 45658 | BN89: 46295 | BO89: 43346 | BP89: BAOF024 | BQ89: STD | BR89: Standard
E90: FR03319FR-BASK63401 | F90: GUAD>Réhab 206 LGMTS SIKOA PAP [3319_BASK63401] | H90: ACTIVE | I90: EGIS BATIMENTS ANTILLES GUYANE | K90: SL-Buildings-CC-12-ANTI-01-Antilles Guyane-BU-FR03319FR_EGIS BAT ANT GUY | M90: EGIS BATIMENTS ANTILLES GUYANE Billable E&SC Small Project | V90: EUR | X90: Corporate | Y90: T | Z90: FALSE | AA90: FALSE | AB90: TRUE | AC90: TRUE | AD90: P01 - Offre | AE90: P01 | AF90: FR03319FR-BASK63401 | AG90: FINANCIAL | BN90: 46751 | BO90: 44957 | BP90: BASK634 | BQ90: STD | BR90: Standard | CG90: 45657 | CH90: P01 | CI90: 44957 | CJ90: PJF_TASKS | CK90: FINANCIAL
E91: FR03319FR-BASK63401 | F91: GUAD>Réhab 206 LGMTS SIKOA PAP [3319_BASK63401] | H91: ACTIVE | I91: EGIS BATIMENTS ANTILLES GUYANE | K91: SL-Buildings-CC-12-ANTI-01-Antilles Guyane-BU-FR03319FR_EGIS BAT ANT GUY | M91: EGIS BATIMENTS ANTILLES GUYANE Billable E&SC Small Project | V91: EUR | X91: Corporate | Y91: T | Z91: FALSE | AA91: FALSE | AB91: TRUE | AC91: TRUE | AD91: P02 - Phase Etudes | AE91: P02 | AF91: FR03319FR-BASK63401 | AG91: FINANCIAL | BN91: 46751 | BO91: 44957 | BP91: BASK634 | BQ91: STD | BR91: Standard | CG91: 46386 | CH91: P02 | CI91: 44957 | CJ91: PJF_TASKS | CK91: FINANCIAL
E92: FR03319FR-BASK63401 | F92: GUAD>Réhab 206 LGMTS SIKOA PAP [3319_BASK63401] | H92: ACTIVE | I92: EGIS BATIMENTS ANTILLES GUYANE | K92: SL-Buildings-CC-12-ANTI-01-Antilles Guyane-BU-FR03319FR_EGIS BAT ANT GUY | M92: EGIS BATIMENTS ANTILLES GUYANE Billable E&SC Small Project | V92: EUR | X92: Corporate | Y92: T | Z92: FALSE | AA92: FALSE | AB92: TRUE | AC92: TRUE | AD92: P03 - Phase Travaux | AE92: P03 | AF92: FR03319FR-BASK63401 | AG92: FINANCIAL | BN92: 46751 | BO92: 44957 | BP92: BASK634 | BQ92: STD | BR92: Standard | CG92: 46751 | CH92: P03 | CI92: 44957 | CJ92: PJF_TASKS | CK92: FINANCIAL
E93: FR03319FR-BASK63401 | F93: GUAD>Réhab 206 LGMTS SIKOA PAP [3319_BASK63401] | H93: ACTIVE | I93: EGIS BATIMENTS ANTILLES GUYANE | K93: SL-Buildings-CC-12-ANTI-01-Antilles Guyane-BU-FR03319FR_EGIS BAT ANT GUY | M93: EGIS BATIMENTS ANTILLES GUYANE Billable E&SC Small Project | V93: EUR | X93: Corporate | Y93: T | Z93: FALSE | AA93: FALSE | AB93: TRUE | AC93: TRUE | AD93: Facturation Milestone Oracle 2025 | AE93: P97 | AF93: FR03319FR-BASK63401 | AG93: FINANCIAL | BN93: 46751 | BO93: 44957 | BP93: BASK634 | BQ93: STD | BR93: Standard | CG93: 46751 | CH93: P97 | CI93: 44957 | CJ93: PJF_TASKS | CK93: FINANCIAL
E94: FR03319FR-BASK63401 | F94: GUAD>Réhab 206 LGMTS SIKOA PAP [3319_BASK63401] | H94: ACTIVE | I94: EGIS BATIMENTS ANTILLES GUYANE | K94: SL-Buildings-CC-12-ANTI-01-Antilles Guyane-BU-FR03319FR_EGIS BAT ANT GUY | M94: EGIS BATIMENTS ANTILLES GUYANE Billable E&SC Small Project | V94: EUR | X94: Corporate | Y94: T | Z94: FALSE | AA94: FALSE | AB94: TRUE | AC94: TRUE | AV94: Project Classification | AW94: Client Project | BN94: 46751 | BO94: 44957 | BP94: BASK634 | BQ94: STD | BR94: Standard
E95: FR03319FR-BASK63401 | F95: GUAD>Réhab 206 LGMTS SIKOA PAP [3319_BASK63401] | H95: ACTIVE | I95: EGIS BATIMENTS ANTILLES GUYANE | K95: SL-Buildings-CC-12-ANTI-01-Antilles Guyane-BU-FR03319FR_EGIS BAT ANT GUY | M95: EGIS BATIMENTS ANTILLES GUYANE Billable E&SC Small Project | V95: EUR | X95: Corporate | Y95: T | Z95: FALSE | AA95: FALSE | AB95: TRUE | AC95: TRUE | AS95: Elie.ELIAS@egis-group.com | AT95: Project Manager | AU95: 44957 | BN95: 46751 | BO95: 44957 | BP95: BASK634 | BQ95: STD | BR95: Standard
E96: FR03319FR-BASK63401 | F96: GUAD>Réhab 206 LGMTS SIKOA PAP [3319_BASK63401] | H96: ACTIVE | I96: EGIS BATIMENTS ANTILLES GUYANE | K96: SL-Buildings-CC-12-ANTI-01-Antilles Guyane-BU-FR03319FR_EGIS BAT ANT GUY | M96: EGIS BATIMENTS ANTILLES GUYANE Billable E&SC Small Project | V96: EUR | X96: Corporate | Y96: T | Z96: FALSE | AA96: FALSE | AB96: TRUE | AC96: TRUE | AS96: Rokhaya.NDIAYE@egis-group.com | AT96: Financial Controller | AU96: 44957 | BN96: 46751 | BO96: 44957 | BP96: BASK634 | BQ96: STD | BR96: Standard
E97: FR03319FR-BASK63401 | F97: GUAD>Réhab 206 LGMTS SIKOA PAP [3319_BASK63401] | H97: ACTIVE | I97: EGIS BATIMENTS ANTILLES GUYANE | K97: SL-Buildings-CC-12-ANTI-01-Antilles Guyane-BU-FR03319FR_EGIS BAT ANT GUY | M97: EGIS BATIMENTS ANTILLES GUYANE Billable E&SC Small Project | V97: EUR | X97: Corporate | Y97: T | Z97: FALSE | AA97: FALSE | AB97: TRUE | AC97: TRUE | AS97: Sebastien.PLICHON@egis-group.com | AT97: RBLD | AU97: 44957 | BN97: 46751 | BO97: 44957 | BP97: BASK634 | BQ97: STD | BR97: Standard
E98: FR03319FR-BASK63401 | F98: GUAD>Réhab 206 LGMTS SIKOA PAP [3319_BASK63401] | H98: ACTIVE | I98: EGIS BATIMENTS ANTILLES GUYANE | K98: SL-Buildings-CC-12-ANTI-01-Antilles Guyane-BU-FR03319FR_EGIS BAT ANT GUY | M98: EGIS BATIMENTS ANTILLES GUYANE Billable E&SC Small Project | V98: EUR | X98: Corporate | Y98: T | Z98: FALSE | AA98: FALSE | AB98: TRUE | AC98: TRUE | AS98: Cedric.ARNAUD@egis-group.com | AT98: Project Sponsor / RBLD Delegate | AU98: 45658 | BN98: 46751 | BO98: 44957 | BP98: BASK634 | BQ98: STD | BR98: Standard
E99: FR03319FR-BASK63401 | F99: GUAD>Réhab 206 LGMTS SIKOA PAP [3319_BASK63401] | H99: ACTIVE | I99: EGIS BATIMENTS ANTILLES GUYANE | K99: SL-Buildings-CC-12-ANTI-01-Antilles Guyane-BU-FR03319FR_EGIS BAT ANT GUY | M99: EGIS BATIMENTS ANTILLES GUYANE Billable E&SC Small Project | V99: EUR | X99: Corporate | Y99: T | Z99: FALSE | AA99: FALSE | AB99: TRUE | AC99: TRUE | AS99: Cedric.ARNAUD@egis-group.com | AT99: Project Manager | AU99: 45658 | BN99: 46751 | BO99: 44957 | BP99: BASK634 | BQ99: STD | BR99: Standard
E100: FR03319FR-BAPJ49301 | F100: GUY - Réa et Extens Locaux S Tech CHAR [3319_BAPJ49301] | H100: ACTIVE | I100: EGIS BATIMENTS ANTILLES GUYANE | K100: SL-Buildings-CC-12-ANTI-01-Antilles Guyane-BU-FR03319FR_EGIS BAT ANT GUY | M100: EGIS BATIMENTS ANTILLES GUYANE Billable E&SC Small Project | V100: EUR | X100: Corporate | Y100: T | Z100: FALSE | AA100: FALSE | AB100: TRUE | AC100: TRUE | AD100: O - Offre | AE100: P01 | AF100: FR03319FR-BAPJ49301 | AG100: FINANCIAL | BN100: 46325 | BO100: 43816 | BP100: BAPJ493 | BQ100: STD | BR100: Standard | CG100: 45657 | CH100: P01 | CI100: 43816 | CJ100: PJF_TASKS | CK100: FINANCIAL
...

Sheet MAPPING
A1: Column Name | B1: Source | C1: Target
A2: ProjectNumber | C2: Empty (will be automatically populated) Do you need to preserve the old number ? Where do you need to stock the old number project (DFF or prefix the project name ?)
A3: ProjectName | C3: prefix-original name (Proposition : bu-old project number-project name)
A4: ProjectStatusCode | C4: Empty (will be automatically populated to DRAFT)
A5: Legal Entity Name | B5: EGIS BATIMENTS ANTILLES GUYANE check the LE tab | C5: EGIS BATIMENTS ILE DE FRANCE check the LE tab
A6: OwningOrganizationName | B6: check the ORG name (PPM) tab | C6: Mapping to new value check the ORG name (PPM) tab
A7: SourceTemplateName | B7: EGIS BATIMENTS ANTILLES GUYANE Billable E&SC MOE EGIS BATIMENTS ANTILLES GUYANE Capital EGIS BATIMENTS ANTILLES GUYANE Billable E&SC Small Project EGIS BATIMENTS ANTILLES GUYANE Indirect EGIS BATIMENTS ANTILLES GUYANE Billable E&SC Progress EGIS BATIMENTS ANTILLES GUYANE Billable E&SC Milestone | C7: check the source template tab EGIS BATIMENTS ILE DE FRANCE Billable E&SC MOE EGIS BATIMENTS ILE DE FRANCE Capital EGIS BATIMENTS ILE DE FRANCE Billable E&SC Small Project EGIS BATIMENTS ILE DE FRANCE Indirect EGIS BATIMENTS ILE DE FRANCE Billable E&SC Progress EGIS BATIMENTS ILE DE FRANCE Billable E&SC Milestone
A8: ExternalParentTaskId | C8: Empty (will be automatically populated)

Sheet mappingprojectoldvsnew

Sheet LE
A1: Name | B1: Country | C1: Legal Entity Identifier | D1: Address | E1: Legal Entity ID | F1: MAP TO
A2: 10 DESIGN ASIA PTE LIMITED | B2: Singapore | C2: SG03367SG | D2: 41 Duxton Hill/Singapore 089619 | E2: 300000003551076
A3: 10 DESIGN USA INC. | B3: United States | C3: US03365US | D3: 9 E Loockerman Street, Suite 311/DOVER, DE 19901 | E3: 300000003341941
A4: 10 EUROPE LIMITED | B4: United Kingdom | C4: GB03362GB | D4: 132 Princes Street 1st Floor/EDINBURGH/EH2 4AH/UNITED KINGDOM | E4: 300000003274747
A5: ACOUSTB | B5: France | C5: FR03258FR | D5: 24 rue Joseph Fourier/38400 SAINT MARTIN D HERES/FRANCE | E5: 300000003012948
A6: AD INGE | B6: France | C6: FR03086FR | D6: 103 avenue Henri Fréville/35200 RENNES/FRANCE | E6: 300000003012821
A7: ATR INGENIERIE | B7: France | C7: FR03133FR | D7: 119 boulevard de la Bataille de Stalingrad/69100 VILLEURBANNE/FRANCE | E7: 300000003274425
A8: ATRIX | B8: France | C8: FR03126FR | D8: 119 boulevard de la Bataille de Stalingrad/69100 VILLEURBANNE/FRANCE | E8: 300000003274411
A9: AUDITSAFE | B9: France | C9: FR03238FR | D9: 15 Avenue du Centre CS 20538 - Guyancourt/78286 SAINT-QUENTIN-EN-YVELINES/FRANCE | E9: 300000003274537
A10: AUDITSAFE SA DE CV | B10: Mexico | C10: MX03821MX | D10: Av. Paseo de la Reforma 243, Piso 22, Col. Renacimiento, Cuauhtémoc/06500 CIUDAD DE MÉXICO, MEXICO/MEXICO | E10: 300000003341532
A11: AUTOBAHNPLUS SERVICES GMBH | B11: Germany | C11: DE03158DE | D11: Neulwirth 2/86453 DASING/GERMANY | E11: 300000005408005
A12: BEMRA ENGINEERING LIMITED | B12: Ireland | C12: IE03111IE | D12: Classon House, Dundrum Business Park/DUBLIN 14 D14 T9T0/IRELAND | E12: 300000003341264
A13: BL UKRAINA LIMITED | B13: Ukraine | C13: UA03135UA | D13: 78280 Guyancourt/78280 KIEV/UKRAINE | E13: 300000004967078
... A38: EGIS AVIA | B38: Belgium | C38: FR03728BE | D38: Place E. De Neckere/7700 MOUSCRON/BELGIUM | E38: 300000003012680
A39: EGIS BATIMENTS ANTILLES GUYANE | B39: France | C39: FR03319FR | D39: 4 rue Dolorès Ibarruri/93100 MONTREUIL-SOUS-BOIS/FRANCE | E39: 300000003274032 | F39: EGIS BATIMENTS ILE DE FRANCE
A40: EGIS BATIMENTS CENTRE OUEST | B40: France | C40: FR03338FR | D40: ZAC de la Courrouze Secteur des Dominos 3, rue Louis Braille/35136 SAINT JACQUES DE LA LANDE/FRANCE | E40: 300000003274144
A41: EGIS BATIMENTS ILE DE FRANCE | B41: France | C41: FR03305FR | D41: 4 rue Dolorès Ibarruri/93100 MONTREUIL-SOUS-BOIS/FRANCE | E41: 300000003012990
A42: EGIS BATIMENTS INTERNATIONAL | B42: Luxembourg | C42: FR03342LU | D42: 51 boulevard Grande Duchesse Charlotte/L-1331 Luxembourg | E42: 300000012494197
A43: EGIS BATIMENTS INTERNATIONAL | B43: Peru | C43: FR03342PE | D43: AV. PERSHING NRO. 465 INT. 1002 URB. COUNTRY CLUB (CENTRO EMPRESARIAL PERSHING TOWER)/MAGDALENA DEL MAR LIMA/PERU | E43: 300000003349506
A44: EGIS BATIMENTS INTERNATIONAL | B44: France | C44: FR03342FR | D44: 4 rue Dolorès Ibarruri/93100 MONTREUIL-SOUS-BOIS/FRANCE | E44: 300000003274186
A45: EGIS BATIMENTS NORD EST | B45: France | C45: FR03339FR | D45: 8-10 Avenue Pierre Mendès France/67300 SCHILTIGHEIM/FRANCE | E45: 300000003274158
A46: EGIS BATIMENTS OCEAN INDIEN | B46: France | C46: FR03320FR | D46: 4 rue Dolorès Ibarruri/93100 MONTREUIL-SOUS-BOIS/FRANCE | E46: 300000003274046
A47: EGIS BATIMENTS RHONE ALPES | B47: France | C47: FR03329FR | D47: 168-170 avenue Thiers/69006 LYON/FRANCE | E47: 300000003274102
A48: EGIS BATIMENTS SUD | B48: France | C48: FR03331FR | D48: 33-43, boulevard Georges Pompidou Héliopôle - Bâtiment D/31130 BALMA/FRANCE | E48: 300000003274116
A49: EGIS BLN CONSULTING USA LLC | B49: United States | C49: US03121US | D49: 8320 Craig St./INDIANAPOLIS, IN 46250 | E49: 300000003341969
A50: EGIS BLN PR LLC | B50: United States | C50: US03122US | D50: 8320 Craig St./INDIANAPOLIS, IN 46250 | E50: 300000003341983
A51: EGIS BLN USA INC | B51: United States | C51: US03120US | D51: 8320 Craig St./INDIANAPOLIS, IN 46250 | E51: 300000003341955
... A233: EGIS SURVEYING INC. | B233: Canada | C233: CA03117CA | D233: 2 Carlton Street, Suite 1700/PERTH WESTERN AUSTRALIA ON K7H 3C0/CANADA | E233: 300000003282769
A234: EGIS TRANSPORT SOLUTIONS LIMITED | B234: United Kingdom | C234: GB03952GB | D234: 3 Valentine Place, Southwark England/LONDON/SE1 8QH/UNITED KINGDOM | E234: 300000003274705 | F234: EGIS UK - CONSULTING AND ENGINEERING LIMITED
A235: EGIS TRANSPORTATION (THAILAND) COMPANY LIMITED | B235: Thailand | C235: TH03947TH | D235: Vanit Building II (24th floor), 1126/2 New Petchburi Road Makkasan, Ratchathewi/BANGKOK/10400 | E235: 300000003282111
A236: EGIS TUNEL ISLETMECILIGI ANONIM SIRKETI | B236: Türkiye | C236: TR03036TR | D236: Büyükdere Cad.Yapi Kredi Plaza C Bl.K17 N.40-41, Of.N.Do-02, Levent / Besiktas/ISTANBUL 34330/TÜRKIYE | E236: 300000003282139
A237: EGIS UK - CONSULTING AND ENGINEERING LIMITED | B237: United Kingdom | C237: GB03958GB | D237: 3 Valentine Place, Southwark England/LONDON/SE1 8QH/UNITED KINGDOM | E237: 300000003274719
A238: EGIS UKRAINA LLC | B238: Ukraine | C238: UA03059UA | D238: 29 Antonovycha Street, 5th floor/KIEV 1033/UKRAINE | E238: 300000003341883
A239: EGIS VILLES ET TRANSPORTS | B239: France | C239: FR03250FR | D239: 168-170 avenue Thiers/69006 LYON/FRANCE | E239: 300000003012877
A240: EGIS VILLES ET TRANSPORTS | B240: New Caledonia | C240: FR03250NC | D240: Chez KPMG/NOUMEA CEDEX 98846/NEW CALEDONIA | E240: 300000003551298
A241: EGIS VILLES ET TRANSPORTS | B241: India | C241: FR03250IN | D241: T-305, TF, Tirupati Plaza, Sector-XI, (MLU) PKT-4, Plot No. 11, Dwarka, Dwarka Sec-6, South West Delhi/DELHI-110075/INDIA | E241: 300000004967159
A242: EGIS VILLES ET TRANSPORTS | B242: Peru | C242: FR03250PE | D242: AV. CANAVAL Y MOREYRA NRO. 480 INT. 801A/SAN ISIDRO LIMA/PERU | E242: 300000003349492
A243: EGIS VILLES ET TRANSPORTS | B243: French Polynesia | C243: FR03250PF | D243: BP 60 154/FAA'A 98702/FRENCH POLYNESIA | E243: 300000003551312
A244: EGIS VOLTERE | B244: France | C244: FR03309FR | D244: 6 rue Dunois/75013 PARIS/FRANCE | E244: 300000003274018
A245: EGIS VOLTERE AFRIQUE | B245: Cote d'Ivoire | C245: CI03325CI | D245: Abidjan Marcory Zone - 4e rue du Canal Immeuble Amoryan - 12ème étage - 01, BP 3916/ABIDJAN/COTE D'IVOIRE | E245: 300000003349380
A246: EGIS WATER AND MARITIME | B246: France | C246: FR03257FR | D246: 15 Avenue du Centre CS 20538 - Guyancourt/78286 SAINT-QUENTIN-EN-YVELINES/FRANCE | E246: 300000003012934
... A340: test | B340: United States | C340: test | D340: 8320 Craig St./INDIANAPOLIS, IN 46250 | E340: 300000003918170

Sheet ORG name (PPM)
A1: Name | B1: Organization ID | C1: Classification | D1: Status | E1: From Date | F1: To Date | G1: MAP TO
A2: SL-04-Shared service Legal-CPC-04-INSP-Shared Service Insurance-BU-BR03062BR_EGIS BRASIL | B2: 300000181470513 | C2: Department | D2: Active | E2: 18629 | F2: 1027428
A3: SL-04-Shared service Legal-CPC-04-INSP-Shared Service Insurance-BU-CO03061CO_EGIS COLOMBIA | B3: 300000181475407 | C3: Department | D3: Active | E3: 18629 | F3: 1027428
A4: SL-04-Shared service Legal-CPC-04-INSP-Shared Service Insurance-BU-CO03070CO_EGIS CONSULTORIA | B4: 300000181475230 | C4: Department | D4: Active | E4: 18629 | F4: 1027428
A5: SL-04-Shared service Legal-CPC-04-INSP-Shared Service Insurance-BU-CO03073CO_PAYC | B5: 300000181465998 | C5: Department | D5: Active | E5: 18629 | F5: 1027428
A6: SL-04-Shared service Legal-CPC-04-INSP-Shared Service Insurance-BU-MX03032MX_EGIS INFRAESTRUCTURA | B6: 300000181470408 | C6: Department | D6: Active | E6: 18629 | F6: 1027428
A7: SL-04-Shared service Legal-CPC-04-INSP-Shared Service Insurance-BU-MX03067MX_EGISMEX | B7: 300000181475549 | C7: Department | D7: Active | E7: 18629 | F7: 1027428
A8: SL-04-Shared service Legal-CPC-04-INSP-Shared Service Insurance-BU-PE03079PE_EGIS PERU | B8: 300000181475274 | C8: Department | D8: Active | E8: 18629 | F8: 1027428
A9: SL-12-SL Building operational indirect-Whole SL-CC-12-TRAB-01-SL Building operational indirect-BU-FR03253FR_ESE | B9: 300000406486948 | C9: Department | D9: Active | E9: 18629 | F9: 1027428
A10: SL-12-SL Building operational indirect-Whole SL-CC-12-TRAB-01-SL Building operational indirect-BU-FR03301FR_EGIS HOLDING BAT | B10: 300000406486937 | C10: Department | D10: Active | E10: 18629 | F10: 1027428
A11: SL-12-SL Environment and Energy-Operational Indirect-Whole SL-CPC-12-TRAE-Transversal ENV-BU-FR03789QA2_EGIS INTERNATIONAL | B11: 300000369278391 | C11: Department | D11: Active | E11: 18629 | F11: 1027428
A12: SL-19-CnO Operational Indirect -CC-20-TENU-01-OnM Tender Unit-BU-FR03739FR_EGIS PROJECTS | B12: 300000400478362 | C12: Department | D12: Active | E12: 18629 | F12: 1027428
A13: SL-19-CnO Operational Indirect -CC-20-TENU-01-OnM Tender Unit-BU-FR03798FR_EGIS OPERATIONS | B13: 300000400478420 | C13: Department | D13: Active | E13: 18629 | F13: 1027428
A14: SL-Advisory Direct-CC-19-AMAN-01-Asset Management Advisory-BU-GB03958GB_EGIS UK | B14: 300000428333082 | C14: Department | D14: Active | E14: 18629 | F14: 1027428
A15: SL-Advisory Direct-CC-19-AMAN-21-Asset Management Advisory-BU-GB03952GB_ETS | B15: 300000023444342 | C15: Department | D15: Active | E15: 45748 | F15: 1027428 | G15: SL-Advisory Direct-CC-19-AMAN-21-Asset Management Advisory-BU-GB03958GB_EGIS UK
A16: SL-Advisory Direct-CC-19-AMAN-21-Asset Management Advisory-BU-GB03958GB_EGIS UK | B16: 300000307463476 | C16: Department | D16: Active | E16: 18629 | F16: 1027428
A17: SL-Advisory Direct-CC-19-BSPI-01-Advisory Building-BU-FR03207FR_EGIS CONSEIL | B17: 300000023433447 | C17: Department | D17: Active | E17: 18629 | F17: 1027428
A18: SL-Advisory Direct-CC-19-BSPI-01-Advisory Building-BU-FR03207PF_EGIS CONSEIL | B18: 300000023431305 | C18: Department | D18: Active | E18: 18629 | F18: 1027428
A19: SL-Advisory Direct-CC-19-BSPI-01-Advisory Building-BU-FR03302FR_EGIS DATA SOLUTIONS | B19: 300000024079683 | C19: Department | D19: Active | E19: 18629 | F19: 1027428
A20: SL-Advisory Direct-CC-19-BSPI-01-Advisory Building-BU-GB03139GB_THOMAS ADAMSON INTER | B20: 300000019337975 | C20: Department | D20: Active | E20: 45748 | F20: 1027428
A21: SL-Advisory Direct-CC-19-BSPI-01-Advisory Building-BU-PH03221PH_EGIS PROJECTS | B21: 300000365089185 | C21: Department | D21: Active | E21: 18629 | F21: 1027428
A22: SL-Advisory Direct-CC-19-CSCT-01-Advisory Sust Cities n Territories-BU-FR03207FR_EGIS CONSEIL | B22: 300000023432655 | C22: Department | D22: Active | E22: 18629 | F22: 1027428
A23: SL-Advisory Direct-CC-19-DIGI-01-Advisory DnS-BU-FR03302FR_EGIS DATA SOLUTIONS | B23: 300000024079705 | C23: Department | D23: Active | E23: 18629 | F23: 1027428
A24: SL-Advisory Direct-CC-19-IMOB-01-Advisory Infra n Mobilities-BU-AU03096AU_EGIS CONSULTING | B24: 300000181159365 | C24: Department | D24: Active | E24: 18629 | F24: 1027428
A25: SL-Advisory Direct-CC-19-IMOB-01-Advisory Infra n Mobilities-BU-AU03617AU_EGIS AUSTRALIA | B25: 300000181172265 | C25: Department | D25: Active | E25: 18629 | F25: 1027428
A26: SL-Advisory Direct-CC-19-IMOB-01-Advisory Infra n Mobilities-BU-FR03207FR_EGIS CONSEIL | B26: 300000023432754 | C26: Department | D26: Active | E26: 18629 | F26: 1027428
A27: SL-Advisory Direct-CC-19-IMOB-01-Advisory Infra n Mobilities-BU-GB03958GB_EGIS UK | B27: 300000307463705 | C27: Department | D27: Active | E27: 18629 | F27: 1027428
... A186: SL-Buildings-CC-12-ANTI-01-Antilles Guyane-BU-FR03301FR_EGIS HOLDING BAT | B186: 300000023420884 | C186: Department | D186: Active | E186: 18629 | F186: 1027428
A187: SL-Buildings-CC-12-ANTI-01-Antilles Guyane-BU-FR03319FR_EGIS BAT ANT GUY | B187: 300000023432590 | C187: Department | D187: Active | E187: 18629 | F187: 1027428 | G187: SL-Buildings-CC-12-IDMI-01-Ile de France-BU-FR03305FR_EGIS BAT IDF
A188: SL-Buildings-CC-12-BLGA-01-Engineering General Activities-BU-FR03301FR_EGIS HOLDING BAT | B188: 300000023431040 | C188: Department | D188: Active | E188: 18629 | F188: 1027428
A189: SL-Buildings-CC-12-BLGA-01-Engineering General Activities-BU-FR03342FR_EGIS BAT. INTER. | B189: 300000023431747 | C189: Department | D189: Active | E189: 18629 | F189: 1027428
A190: SL-Buildings-CC-12-BLGA-01-Engineering General Activities-BU-HK03093HK_EGIS M AND E | B190: 300000005404713 | C190: Department | D190: Active | E190: 45748 | F190: 1027428
A191: SL-Buildings-CC-12-BLGA-01-Engineering General Activities-BU-IE03109IE_ENGINEERING IRELAND | B191: 300000005436293 | C191: Department | D191: Active | E191: 45748 | F191: 1027428
A192: SL-Buildings-CC-12-BLGA-01-Engineering General Activities-BU-PL03243PL_EGIS POLAND | B192: 300000005405465 | C192: Department | D192: Active | E192: 45748 | F192: 1027428
A193: SL-Buildings-CC-12-BLGA-AU-Building Structures-BU-AU03096AU_EGIS CONSULTING | B193: 300000023552510 | C193: Department | D193: Active | E193: 45748 | F193: 1027428
A194: SL-Buildings-CC-12-BLGA-AU-Building Structures-BU-AU03096AU_EGIS CONSULTING | B194: 300000023541669 | C194: Department | D194: Active | E194: 45748 | F194: 1027428
A195: SL-Buildings-CC-12-BLGA-NZ-Building Structures-NZ-BU-NZ03100NZ_EGIS NZ | B195: 300000023552246 | C195: Department | D195: Active | E195: 45748 | F195: 1027428
A196: SL-Buildings-CC-12-BLZA-01-Blezat-BU-FR03132FR_BLEZAT | B196: 300000189348187 | C196: Department | D196: Active | E196: 18629 | F196: 1027428
A197: SL-Buildings-CC-12-CTOI-01-Centre-Ouest-BU-FR03207FR_EGIS CONSEIL | B197: 300000023434233 | C197: Department | D197: Active | E197: 18629 | F197: 1027428
A198: SL-Buildings-CC-12-CTOI-01-Centre-Ouest-BU-FR03301FR_EGIS HOLDING BAT | B198: 300000023420780 | C198: Department | D198: Active | E198: 18629 | F198: 1027428
A199: SL-Buildings-CC-12-CTOI-01-Centre-Ouest-BU-FR03338FR_EGIS BAT CENTR OUEST | B199: 300000023433216 | C199: Department | D199: Active | E199: 18629 | F199: 1027428
... A1018: SL-Inter - Urban Transport-CC-11-RAIL-01-Rail-BU-TH03947TH_EGIS RAIL | B1018: 300000365086968 | C1018: Department | D1018: Active | E1018: 18629 | F1018: 1027428
A1019: SL-Inter - Urban Transport-CC-11-RAIL-21-Rail-BU-GB03952GB_ETS | B1019: 300000023444408 | C1019: Department | D1019: Active | E1019: 45748 | F1019: 1027428 | G1019: SL-Inter - Urban Transport-CC-11-RAIL-21-Rail-BU-GB03958GB_EGIS UK
A1020: SL-Inter - Urban Transport-CC-11-RAIL-21-Rail-BU-GB03958GB_EGIS UK | B1020: 300000023444452 | C1020: Department | D1020: Active | E1020: 45748 | F1020: 1027428
A1021: SL-Inter - Urban Transport-CC-11-RAIL-AU-Rail-BU-AU03954AU_EGIS OCEANIA | B1021: 300000023541823 | C1021: Department | D1021: Active | E1021: 45748 | F1021: 1027428
A1022: SL-Inter - Urban Transport-CC-11-ROAD-01-Road - Egis Villes and Transports-BU-FR03250FR_EVT | B1022: 300000023431268 | C1022: Department | D1022: Active | E1022: 18629 | F1022: 1027428
A1023: SL-Inter - Urban Transport-CC-11-ROAD-01-Road-BU-IE03109IE_ENGINEERING IRELAND | B1023: 300000005433840 | C1023: Department | D1023: Active | E1023: 45748 | F1023: 1027428
A1024: SL-Inter - Urban Transport-CC-11-ROAD-01-Road-BU-PL03243PL_EGIS POLAND | B1024: 300000005405172 | C1024: Department | D1024: Active | E1024: 45748 | F1024: 1027428
A1025: SL-Inter - Urban Transport-CC-11-ROAD-01-Road-BU-RO03780RO_EGIS ROMANIA | B1025: 300000005404249 | C1025: Department | D1025: Active | E1025: 45748 | F1025: 1027428
A1026: SL-Inter - Urban Transport-CC-11-ROAD-01-Road-BU-SG03945SG_EGIS RAIL | B1026: 300000005405249 | C1026: Department | D1026: Active | E1026: 45748 | F1026: 1027428
A1027: SL-Inter - Urban Transport-CC-11-ROAD-01-Road-BU-TH03212TH_JMI PACIFIC | B1027: 300000365086832 | C1027: Department | D1027: Active | E1027: 18629 | F1027: 1027428
A1028: SL-Inter - Urban Transport-CC-11-ROAD-01-Road-BU-TH03947TH_EGIS RAIL | B1028: 300000365089673 | C1028: Department | D1028: Active | E1028: 18629 | F1028: 1027428
A1029: SL-Inter - Urban Transport-CC-11-ROAD-01-Road-BU-UA03059UA_EGIS UKRAINA | B1029: 300000005416438 | C1029: Department | D1029: Active | E1029: 45748 | F1029: 1027428
A1030: SL-Inter - Urban Transport-CC-11-ROAD-AU-Roads-BU-AU03096AU_EGIS CONSULTING | B1030: 300000023552235 | C1030: Department | D1030: Active | E1030: 45748 | F1030: 1027428
A1031: SL-Inter - Urban Transport-CC-11-ROAD-NZ-Roads-NZ-BU-NZ03100NZ_EGIS NZ | B1031: 300000023552158 | C1031: Department | D1031: Active | E1031: 45748 | F1031: 1027428
... A1876: SL-Shared Services FIN-CC-04-FINA-BL-Accounting BL-BU-FR03305FR_EGIS BAT IDF | B1876: 300000023420802 | C1876: Department | D1876: Active | E1876: 18629 | F1876: 1027428
A1877: SL-Shared Services FIN-CC-04-FINA-BL-Accounting BL-BU-FR03319FR_EGIS BAT ANT GUY | B1877: 300000023431786 | C1877: Department | D1877: Active | E1877: 18629 | F1877: 1027428 | G1877: SL-Shared Services FIN-CC-04-FINA-BL-Accounting BL-BU-FR03305FR_EGIS BAT IDF
A1878: SL-Shared Services FIN-CC-04-FINA-BL-Accounting BL-BU-FR03331FR_EGIS BATIMENTS SUD | B1878: 300000023420844 | C1878: Department | D1878: Active | E1878: 18629 | F1878: 1027428
A1879: SL-Shared Services FIN-CC-04-FINA-BL-Accounting BL-BU-FR03342FR_EGIS BAT. INTER. | B1879: 300000023434317 | C1879: Department | D1879: Active | E1879: 18629 | F1879: 1027428
A1880: SL-Shared Services FIN-CC-04-FINA-BL-Accounting BL-BU-FR03728FR_EGIS AVIA | B1880: 300000023434339 | C1880: Department | D1880: Active | E1880: 18629 | F1880: 1027428
A1881: SL-Shared Services FIN-CC-04-FINA-BL-Accounting BL-BU-FR03739FR_EGIS PROJECTS | B1881: 300000023427737 | C1881: Department | D1881: Active | E1881: 18629 | F1881: 1027428
A1882: SL-Shared Services FIN-CC-04-FINA-BL-Accounting BL-BU-FR03936FR_EGIS RAIL | B1882: 300000023427692 | C1882: Department | D1882: Active | E1882: 18629 | F1882: 1027428
A1883: SL-Shared Services FIN-CC-04-FINA-GL-General Accounting-BU-AU03096AU_EGIS CONSULTING | B1883: 300000260536660 | C1883: Department | D1883: Active | E1883: 18629 | F1883: 1027428
A1884: SL-Shared Services FIN-CC-04-FINA-GL-General Accounting-BU-AU03373AU_INHABIT AUSTRALASIA | B1884: 300000023552312 | C1884: Department | D1884: Active | E1884: 45748 | F1884: 1027428
A1885: SL-Shared Services FIN-CC-04-FINA-GL-General Accounting-BU-AU03617AU_EGIS AUSTRALIA | B1885: 300000023552202 | C1885: Department | D1885: Active | E1885: 45748 | F1885: 1027428
A1886: SL-Shared Services FIN-CC-04-FINA-GL-General Accounting-BU-FR03072FR_EGIS SA | B1886: 300000023431961 | C1886: Department | D1886: Active | E1886: 18629 | F1886: 1027428
A1887: SL-Shared Services FIN-CC-04-FINA-GL-General Accounting-BU-FR03207FR_EGIS CONSEIL | B1887: 300000023431243 | C1887: Department | D1887: Active | E1887: 18629 | F1887: 1027428
A1888: SL-Shared Services FIN-CC-04-FINA-GL-General Accounting-BU-FR03253FR_ESE | B1888: 300000023420892 | C1888: Department | D1888: Active | E1888: 18629 | F1888: 1027428
A1889: SL-Shared Services FIN-CC-04-FINA-GL-General Accounting-BU-NZ03100NZ_EGIS NZ | B1889: 300000023552532 | C1889: Department | D1889: Active | E1889: 45748 | F1889: 1027428
... A2651: SL-Transportation Management TRE-CC-11-RMAN-01-TnT Management-BU-FR03936FR_EGIS RAIL | B2651: 300000268741487 | C2651: Department | D2651: Active | E2651: 18629 | F2651: 1027428
A2652: SL-Transportation Management TRE-CC-11-RMAN-01-TnT Management-BU-GB03952GB_ETS | B2652: 300000181172165 | C2652: Department | D2652: Active | E2652: 18629 | F2652: 1027428 | G2652: SL-Transportation Management TRE-CC-11-RMAN-01-TnT Management-BU-GB03958GB_EGIS UK
A2653: SL-Transportation Management TRE-CC-11-RMAN-01-TnT Management-BU-GB03958GB_EGIS UK | B2653: 300000428333031 | C2653: Department | D2653: Active | E2653: 18629 | F2653: 1027428
A2654: SL-Transportation Management TRE-CC-11-RMAN-01-TnT Management-BU-PL03243PL_EGIS POLAND | B2654: 300000365089514 | C2654: Department | D2654: Active | E2654: 18629 | F2654: 1027428
A2655: SL-Transportation Management TRE-CC-11-RMEA-01-Transportation Regional Management x EURA-BU-GB03958GB_EGIS UK | B2655: 300000428333071 | C2655: Department | D2655: Active | E2655: 18629 | F2655: 1027428
A2656: SL-Transportation Management TRE-CC-11-RMEA-21-Transportation Regional Management x EURA-BU-FR03250FR_EVT | B2656: 300000191520644 | C2656: Department | D2656: Active | E2656: 18629 | F2656: 1027428
A2657: SL-Transportation Management TRE-CC-11-RMEA-21-Transportation Regional Management x EURA-BU-GB03952GB_ETS | B2657: 300000023444562 | C2657: Department | D2657: Active | E2657: 45748 | F2657: 1027428
A2658: SL-Transportation Management TRE-CPC-11-RMAN-TnT Management-BU-FR03789KE_EGIS INTERNATIONAL | B2658: 300000355258258 | C2658: Department | D2658: Active | E2658: 18629 | F2658: 1027428
A2659: SL-Transportation Management TRE-CPC-11-RMAN-TnT Management-BU-FR03789RW_EGIS INTERNATIONAL | B2659: 300000355258147 | C2659: Department | D2659: Active | E2659: 18629 | F2659: 1027428
A2660: SL-Transportation Management TRE-CPC-11-RMAN-TnT Management-BU-FR03936SA_EGIS RAIL | B2660: 300000181470588 | C2660: Department | D2660: Active | E2660: 18629 | F2660: 1027428
A2661: SL-Transportation Management TRE-CPC-11-RMAN-TnT Management-BU-SA03246SA_EGIS SAUDI ENG. CSLT | B2661: 300000181475487 | C2661: Department | D2661: Active | E2661: 18629 | F2661: 1027428
A2662: SL-Transportation Management TRE-CPC-11-RMEA-Transportation Regional Management x EURA-BU-PL03243PL_EGIS POLAND | B2662: 300000149870525 | C2662: Department | D2662: Active | E2662: 18629 | F2662: 1027428
A2663: SL-Transportation Management TRE-CPC-Transportation Regional Management x EURA-BU-FR03936FR_EGIS RAIL | B2663: 300000005750520 | C2663: Department | D2663: Inactive | E2663: 18630 | F2663: 1027428
A2664: SL-Transportation Management TRE-CPC-Transportation Regional Management x EURA-BU-GB03952GB_ETS | B2664: 300000005403957 | C2664: Department | D2664: Inactive | E2664: 45748 | F2664: 1027428
... A3585: zz-DoNotuse-SL-Water and Energy-CPC-Water International Business-BU-FR03252FR_EGIS EAU | B3585: 300000005749114 | C3585: Department | D3585: Active | E3585: 45834 | F3585: 1027428

Sheet LEGACYDATAold
A1: Columns | B1: Status | C1: Error Message | D1: Action | E1: ProjectNumber | F1: ProjectName | H1: ProjectStatusCode | I1: LegalEntityName | K1: OwningOrganizationName | M1: SourceTemplateName | O1: AllowCapitalizedInterestFlag | P1: AssetAllocationMethodCode | Q1: BurdenScheduleName | R1: BurdenScheduleFixedDate | S1: CapitalEventProcessingMethodCode | T1: CIntRateSchName | U1: CIntStopDate | V1: ProjectCurrencyCode | W1: CurrencyConvDate | X1: CurrencyConvRateType | Y1: CurrencyConvDateTypeCode | Z1: IncludeNotesInKPINotificationsFlag | AA1: KPINotificationEnabledFlag | AB1: PlanningProjectFlag | AC1: AllowCrossChargeFlag | AD1: TaskName | AE1: ExternalTaskId | AF1: ExternalParentTaskId | AG1: ElementType | AH1: ExpenseResourceName | AI1: LaborResourceName | AJ1: LaborResourceEmail | AK1: LaborPrimaryResource | AL1: RuleNumber | AM1: Billable | AN1: Chargeable | AO1: ExternalPredecessorTaskId | AP1: ExternalTaskId | AQ1: Lag | AR1: DependencyType | AS1: PersonEmail | AT1: ProjectRole | AU1: StartDate | AV1: ClassCategory | AW1: ClassCode | AX1: CodePercentage | AY1: OpportunityNumber | AZ1: OpportunityName | BA1: OpportunityAmount | BB1: OpportunityCustomerName | BC1: OpportunityCustomerNumber | BD1: OpportunityStatus | BE1: OpportunityWinConfPercent | BF1: PartyName | BG1: PartyNumber | BH1: BusinessUnitName | BI1: CategoryName | BJ1: DatatypeCode | BK1: FileContents | BL1: Title | BM1: FileName | BN1: ProjectEndDate | BO1: ProjectStartDate | BP1: crmNumber | BQ1: supplierPaymentProcess | BR1: supplierPaymentProcess_Display | BS1: domain | BT1: marketSegment | BU1: domain_Display | BV1: marketSegment_Display | BW1: specificities | BX1: specificities_Display | BY1: fundingSource | BZ1: fundingSource_Display | CA1: subFundingSource | CB1: subFundingSource_Display | CC1: procedures | CD1: procedures_Display | CE1: countryDestinationView | CF1: stateOrProvince | CG1: TaskFinishDate | CH1: TaskNumber | CI1: TaskStartDate | CJ1: ObjectType | CK1: ElementType
A2: Status | B2: Technical | C2: Technical | D2: Action | E2: Header | F2: Header | H2: Header | I2: Header | K2: Header | M2: Header | O2: Header | P2: Header | Q2: Header | R2: Header | S2: Header | T2: Header | U2: Header | V2: Header | W2: Header | X2: Header | Y2: Header | Z2: Header | AA2: Header | AB2: Header | AC2: Header | AD2: Tasks | AE2: Tasks | AF2: Tasks | AG2: Tasks | AH2: ExpenseResourceAssignments | AI2: LaborResourceAssignments | AJ2: LaborResourceAssignments | AK2: LaborResourceAssignments | AL2: TaskTransactionControls | AM2: TaskTransactionControls | AN2: TaskTransactionControls | AO2: TaskDependencies | AP2: TaskDependencies | AQ2: TaskDependencies | AR2: TaskDependencies | AS2: ProjectTeamMembers | AT2: ProjectTeamMembers | AU2: ProjectTeamMembers | AV2: ProjectClassifications | AW2: ProjectClassifications | AX2: ProjectClassifications | AY2: ProjectOpportunities | AZ2: ProjectOpportunities | BA2: ProjectOpportunities | BB2: ProjectOpportunities | BC2: ProjectOpportunities | BD2: ProjectOpportunities | BE2: ProjectOpportunities | BF2: ProjectCustomers | BG2: ProjectCustomers | BH2: ProviderBusinessUnits | BI2: Attachments | BJ2: Attachments | BK2: Attachments | BL2: Attachments | BM2: Attachments | BN2: Header | BO2: Header | BP2: Header | BQ2: Header | BR2: Header | BS2: Header | BT2: Header | BU2: Header | BV2: Header | BW2: Header | BX2: Header | BY2: Header | BZ2: Header | CA2: Header | CB2: Header | CC2: Header | CD2: Header | CE2: Header | CF2: Header | CG2: Tasks | CH2: Tasks | CI2: Tasks | CJ2: Tasks | CK2: Tasks
A3: Type | B3: Standard | C3: Standard | D3: Standard | E3: Standard | F3: Standard | H3: Standard | I3: Standard | K3: Standard | M3: Standard | O3: Standard | P3: Standard | Q3: Standard | R3: Standard | S3: Standard | T3: Standard | U3: Standard | V3: Standard | W3: Standard | X3: Standard | Y3: Standard | Z3: Standard | AA3: Standard | AB3: Standard | AC3: Standard | AD3: Standard | AE3: Standard | AF3: Standard | AG3: Standard | AH3: Standard | AI3: Standard | AJ3: Standard | AK3: Standard | AL3: Standard | AM3: Standard | AN3: Standard | AO3: Standard | AP3: Standard | AQ3: Standard | AR3: Standard | AS3: Standard | AT3: Standard | AU3: Standard | AV3: Standard | AW3: Standard | AX3: Standard | AY3: Standard | AZ3: Standard | BA3: Standard | BB3: Standard | BC3: Standard | BD3: Standard | BE3: Standard | BF3: Standard | BG3: Standard | BH3: Standard | BI3: Standard | BJ3: Standard | BK3: Standard | BL3: Standard | BM3: Standard | BN3: Standard | BO3: Standard | BP3: ProjectDFF | BQ3: ProjectDFF | BR3: ProjectDFF | BS3: ProjectDFF | BT3: ProjectDFF | BU3: ProjectDFF | BV3: ProjectDFF | BW3: ProjectDFF | BX3: ProjectDFF | BY3: ProjectDFF | BZ3: ProjectDFF | CA3: ProjectDFF | CB3: ProjectDFF | CC3: ProjectDFF | CD3: ProjectDFF | CE3: ProjectDFF | CF3: ProjectDFF | CG3: Standard | CH3: Standard | CI3: Standard | CJ3: TasksDFF | CK3: TasksDFF
A4: Custom Labels | B4: Status | C4: Error Message | D4: Action | E4: Project Number | F4: Project Name | G4: ProjectName to migrate | H4: Project Status Code | I4: Legal Entity Name | J4: Legal Entity Name to migrate | K4: Owning Organization Name | L4: Owning Organization Name to migrate | M4: Source Template Name | N4: SourceTemplateName to migrate | O4: Allow Capitalized Interest Flag | P4: Asset Allocation Method Code | Q4: Burden Schedule Name | R4: Burden Schedule Fixed Date | S4: Capital Event Processing Method Code | T4: CIntRateSchName | U4: CIntStopDate | V4: Project Currency Code | W4: Currency Conv Date | X4: Currency Conv Rate Type | Y4: Currency Conv Date Type Code | Z4: Include Notes In KPI Notifications Flag | AA4: KPI Notification Enabled Flag | AB4: Planning Project lag | AC4: Allow cross-charge transactions from other business units | AD4: Task Name | AE4: External Task Id | AF4: External Parent Task Id | AG4: Element Type | AH4: Expense Resource Name | AI4: Labor Resource Name | AJ4: Labor Resource Email | AK4: Labor Primary Resource | AL4: Rule Number | AM4: Billable | AN4: Chargeable | AO4: External Predecessor Task Id | AP4: External Task Id | AQ4: Lag | AR4: Dependency Type | AS4: Person Email | AT4: Project Role | AU4: Start Date | AV4: Class Category | AW4: Class Code | AX4: Code Percentage | AY4: Opportunity Number | AZ4: Opportunity Name | BA4: Opportunity Amount | BB4: Opportunity Customer Name | BC4: Opportunity Customer Number | BD4: Opportunity Status | BE4: Opportunity Win Conf Percent | BF4: Party Name | BG4: Party Number | BH4: BusinessUnitName | BI4: Category Name | BJ4: Data type Code | BK4: File Contents | BL4: Title | BM4: File Name | BN4: Project Finish Date | BO4: Project Start Date | CG4: Task Finish Date | CH4: Task Number | CI4: Task Start Date
B5: OK | D5: CREATE | E5: BIL-1007342 | F5: TESTUK1 | G5: ETS-BIL-1007342-TESTUK1 | H5: DRAFT | I5: EGIS UK - CONSULTING AND ENGINEERING LIMITED | J5: =_xlfn.XLOOKUP(I5,LE!A:A,LE!F:F,,1) -> 0 | K5: SL-Nuclear SL-CC-12-NTAI-21-Nuclear Technical Assistance-BU-GB03958GB_EGIS UK | L5: =_xlfn.XLOOKUP(K5,'ORG name (PPM)'!A:A,'ORG name (PPM)'!G:G,,1) -> 0 | M5: EGIS UK - CONSULTING AND ENGINEERING LIMITED Billable | N5: =_xlfn.XLOOKUP(M5,'source template'!A:A,'source template'!I:I,,1) -> 0 | V5: GBP | X5: Corporate | Y5: T | Z5: FALSE | AA5: FALSE | AB5: TRUE | AD5: Tender Costs | AE5: P01 | AG5: FINANCIAL | BN5: 47848 | BO5: 44927 | BP5: ZZZZZ | BQ5: STD | BR5: Standard | CG5: 47848 | CH5: P01 | CI5: 44927 | CJ5: PJF_TASKS | CK5: FINANCIAL
B6: OK | D6: CREATE | E6: BIL-1007342 | F6: TESTUK1 | G6: ETS-BIL-1007342-TESTUK1 | H6: DRAFT | I6: EGIS UK - CONSULTING AND ENGINEERING LIMITED | J6: =_xlfn.XLOOKUP(I6,LE!A:A,LE!F:F,,1) -> 0 | K6: SL-Nuclear SL-CC-12-NTAI-21-Nuclear Technical Assistance-BU-GB03958GB_EGIS UK | L6: =_xlfn.XLOOKUP(K6,'ORG name (PPM)'!A:A,'ORG name (PPM)'!G:G,,1) -> 0 | M6: EGIS UK - CONSULTING AND ENGINEERING LIMITED Billable | N6: =_xlfn.XLOOKUP(M6,'source template'!A:A,'source template'!I:I,,1) -> 0 | V6: GBP | X6: Corporate | Y6: T | Z6: FALSE | AA6: FALSE | AB6: TRUE | AD6: Budget | AE6: P02 | AG6: FINANCIAL | BN6: 47848 | BO6: 44927 | BP6: ZZZZZ | BQ6: STD | BR6: Standard | CG6: 47848 | CH6: P02 | CI6: 44927 | CJ6: PJF_TASKS | CK6: FINANCIAL
B7: OK | D7: CREATE | E7: BIL-1007342 | F7: TESTUK1 | G7: ETS-BIL-1007342-TESTUK1 | H7: DRAFT | I7: EGIS UK - CONSULTING AND ENGINEERING LIMITED | J7: =_xlfn.XLOOKUP(I7,LE!A:A,LE!F:F,,1) -> 0 | K7: SL-Nuclear SL-CC-12-NTAI-21-Nuclear Technical Assistance-BU-GB03958GB_EGIS UK | L7: =_xlfn.XLOOKUP(K7,'ORG name (PPM)'!A:A,'ORG name (PPM)'!G:G,,1) -> 0 | M7: EGIS UK - CONSULTING AND ENGINEERING LIMITED Billable | N7: =_xlfn.XLOOKUP(M7,'source template'!A:A,'source template'!I:I,,1) -> 0 | V7: GBP | X7: Corporate | Y7: T | Z7: FALSE | AA7: FALSE | AB7: TRUE | AD7: Non charegable to client | AE7: P03 | AG7: FINANCIAL | BN7: 47848 | BO7: 44927 | BP7: ZZZZZ | BQ7: STD | BR7: Standard | CG7: 47848 | CH7: P03 | CI7: 44927 | CJ7: PJF_TASKS | CK7: FINANCIAL
B8: OK | D8: CREATE | E8: BIL-1007342 | F8: TESTUK1 | G8: ETS-BIL-1007342-TESTUK1 | H8: DRAFT | I8: EGIS UK - CONSULTING AND ENGINEERING LIMITED | J8: =_xlfn.XLOOKUP(I8,LE!A:A,LE!F:F,,1) -> 0 | K8: SL-Nuclear SL-CC-12-NTAI-21-Nuclear Technical Assistance-BU-GB03958GB_EGIS UK | L8: =_xlfn.XLOOKUP(K8,'ORG name (PPM)'!A:A,'ORG name (PPM)'!G:G,,1) -> 0 | M8: EGIS UK - CONSULTING AND ENGINEERING LIMITED Billable | N8: =_xlfn.XLOOKUP(M8,'source template'!A:A,'source template'!I:I,,1) -> 0 | V8: GBP | X8: Corporate | Y8: T | Z8: FALSE | AA8: FALSE | AB8: TRUE | AD8: 425770 - Egis Structures and Environment - CM | AE8: P04 | AG8: FINANCIAL | BN8: 47848 | BO8: 44927 | BP8: ZZZZZ | BQ8: STD | BR8: Standard | CG8: 47848 | CH8: P04 | CI8: 44927 | CJ8: PJF_TASKS | CK8: FINANCIAL
B9: OK | D9: CREATE | E9: BIL-1007342 | F9: TESTUK1 | G9: ETS-BIL-1007342-TESTUK1 | H9: DRAFT | I9: EGIS UK - CONSULTING AND ENGINEERING LIMITED | J9: =_xlfn.XLOOKUP(I9,LE!A:A,LE!F:F,,1) -> 0 | K9: SL-Nuclear SL-CC-12-NTAI-21-Nuclear Technical Assistance-BU-GB03958GB_EGIS UK | L9: =_xlfn.XLOOKUP(K9,'ORG name (PPM)'!A:A,'ORG name (PPM)'!G:G,,1) -> 0 | M9: EGIS UK - CONSULTING AND ENGINEERING LIMITED Billable | N9: =_xlfn.XLOOKUP(M9,'source template'!A:A,'source template'!I:I,,1) -> 0 | V9: GBP | X9: Corporate | Y9: T | Z9: FALSE | AA9: FALSE | AB9: TRUE | AD9: P05 - Phase 05 | AE9: P05 | AG9: FINANCIAL | BN9: 47848 | BO9: 44927 | BP9: ZZZZZ | BQ9: STD | BR9: Standard | CG9: 47848 | CH9: P05 | CI9: 44927 | CJ9: PJF_TASKS | CK9: FINANCIAL
E10: GB03952GB-IBESDIR1TC | F10: FRA > EGIS Structures and Environment [3952_IBESDIR1TC] | G10: ETS-GB03952GB-IBESDIR1TC-FRA > EGIS Structures and Environment [3952_IBESDIR1TC] | H10: ACTIVE | I10: EGIS TRANSPORT SOLUTIONS LIMITED | J10: =_xlfn.XLOOKUP(I10,LE!A:A,LE!F:F,,1) -> EGIS UK - CONSULTING AND ENGINEERING LIMITED | K10: SL-Advisory Direct-CC-19-AMAN-21-Asset Management Advisory-BU-GB03952GB_ETS | L10: =_xlfn.XLOOKUP(K10,'ORG name (PPM)'!A:A,'ORG name (PPM)'!G:G,,1) -> SL-Advisory Direct-CC-19-AMAN-21-Asset Management Advisory-BU-GB03958GB_EGIS UK | M10: EGIS TRANSPORT SOLUTIONS LIMITED Billable | N10: =_xlfn.XLOOKUP(M10,'source template'!A:A,'source template'!I:I,,1) -> EGIS UK - CONSULTING AND ENGINEERING LIMITED Billable | V10: GBP | X10: Corporate | Y10: T | Z10: FALSE | AA10: FALSE | AB10: TRUE | AS10: Jonathan.ANTHONY@egis-group.com | AT10: Project Manager | AU10: 45716 | BN10: 47848 | BO10: 44927 | BP10: ZZZZZ | BQ10: STD | BR10: Standard
E11: GB03952GB-IBESDIR1TC | F11: FRA > EGIS Structures and Environment [3952_IBESDIR1TC] | G11: GB03952GB-GB03952GB-IBESDIR1TC-FRA > EGIS Structures and Environment [3952_IBESDIR1TC] | H11: ACTIVE | I11: EGIS TRANSPORT SOLUTIONS LIMITED | J11: =_xlfn.XLOOKUP(I11,LE!A:A,LE!F:F,,1) -> EGIS UK - CONSULTING AND ENGINEERING LIMITED | K11: SL-Advisory Direct-CC-19-AMAN-21-Asset Management Advisory-BU-GB03952GB_ETS | L11: =_xlfn.XLOOKUP(K11,'ORG name (PPM)'!A:A,'ORG name (PPM)'!G:G,,1) -> SL-Advisory Direct-CC-19-AMAN-21-Asset Management Advisory-BU-GB03958GB_EGIS UK | M11: EGIS TRANSPORT SOLUTIONS LIMITED Billable | N11: =_xlfn.XLOOKUP(M11,'source template'!A:A,'source template'!I:I,,1) -> EGIS UK - CONSULTING AND ENGINEERING LIMITED Billable | V11: GBP | X11: Corporate | Y11: T | Z11: FALSE | AA11: FALSE | AB11: TRUE | AS11: Joy.WILLIAMS@egis-group.com | AT11: Team Member | AU11: 45790 | BN11: 47848 | BO11: 44927 | BP11: ZZZZZ | BQ11: STD | BR11: Standard
E12: BIL-1007981 | F12: GB03952GB-GB03952GB-PAVSAU1006-SAU > Matarat Asset Management Support [3952_PAVSAU1006] | G12: GB03952GB-PAVSAU1006-SAU > Matarat Asset Management Support [3952_PAVSAU1006] | H12: DRAFT | I12: EGIS UK - CONSULTING AND ENGINEERING LIMITED | J12: =_xlfn.XLOOKUP(I12,LE!A:A,LE!F:F,,1) -> 0 | K12: SL-Advisory Direct-CC-19-AMAN-21-Asset Management Advisory-BU-GB03958GB_EGIS UK | L12: =_xlfn.XLOOKUP(K12,'ORG name (PPM)'!A:A,'ORG name (PPM)'!G:G,,1) -> 0 | M12: EGIS UK - CONSULTING AND ENGINEERING LIMITED Billable | N12: =_xlfn.XLOOKUP(M12,'source template'!A:A,'source template'!I:I,,1) -> 0 | V12: GBP | X12: Corporate | Y12: T | Z12: FALSE | AA12: FALSE | AB12: TRUE | AC12: TRUE | AD12: Tender Costs | AE12: P01 | AG12: FINANCIAL | BN12: 47848 | BO12: 44927 | BP12: 952-000716 | BQ12: STD | BR12: Standard | CG12: 47848 | CH12: P01 | CI12: 44927 | CJ12: PJF_TASKS | CK12: FINANCIAL
E13: CRA-1000030 | F13: Cost Re-Allocation for FR03319FR_EGIS BAT ANT GUY | H13: ACTIVE | I13: EGIS BATIMENTS ANTILLES GUYANE | K13: SL-Shared Services FIN-CC-04-FINA-BL-Accounting BL-BU-FR03319FR_EGIS BAT ANT GUY | M13: EGIS BATIMENTS ANTILLES GUYANE Indirect | V13: EUR | X13: Corporate | Y13: T | Z13: FALSE | AA13: FALSE | AB13: TRUE | AC13: TRUE | AD13: Cost Re-Allocation | AE13: 1 | AF13: CRA-1000030 | AG13: FINANCIAL | BN13: 69763 | BO13: 45292 | BQ13: STD | BR13: Standard | CG13: 69763 | CH13: 1 | CI13: 45292 | CJ13: PJF_TASKS | CK13: FINANCIAL
E14: CRA-1000030 | F14: Cost Re-Allocation for FR03319FR_EGIS BAT ANT GUY | H14: ACTIVE | I14: EGIS BATIMENTS ANTILLES GUYANE | K14: SL-Shared Services FIN-CC-04-FINA-BL-Accounting BL-BU-FR03319FR_EGIS BAT ANT GUY | M14: EGIS BATIMENTS ANTILLES GUYANE Indirect | V14: EUR | X14: Corporate | Y14: T | Z14: FALSE | AA14: FALSE | AB14: TRUE | AC14: TRUE | AV14: Project Classification | AW14: Cost Re-Allocation | BN14: 69763 | BO14: 45292 | BQ14: STD | BR14: Standard
B15: OK | D15: CREATE | E15: BIL-1007983 | F15: TESTME-FR03319FR-4896-30 Logements Siguy [3319_4896] | G15: TESTME--TESTME-FR03319FR-4896-30 Logements Siguy [3319_4896] | H15: DRAFT | I15: EGIS BATIMENTS ILE DE FRANCE | J15: =_xlfn.XLOOKUP(I15,LE!A:A,LE!F:F,,1) -> 0 | K15: SL-Buildings-CC-12-IDMI-01-Ile de France-BU-FR03305FR_EGIS BAT IDF | L15: SL-Buildings-CC-12-IDMI-01-Ile de France-BU-FR03305FR_EGIS BAT IDF | M15: EGIS BATIMENTS ILE DE FRANCE Billable E&SC Small Project | N15: =_xlfn.XLOOKUP(M15,'source template'!A:A,'source template'!I:I,,1) -> 0 | V15: EUR | X15: Corporate | Y15: T | Z15: FALSE | AA15: FALSE | AB15: TRUE | AC15: TRUE | AD15: O | AE15: P01 | AG15: FINANCIAL | BN15: 46203 | BO15: 41275 | BP15: 319-000008 | BQ15: STD | BR15: Standard | CG15: 45657 | CH15: P01 | CI15: 41275 | CJ15: PJF_TASKS | CK15: FINANCIAL
B16: OK | D16: CREATE | E16: BIL-1007983 | F16: TESTME-FR03319FR-4896-30 Logements Siguy [3319_4896] | G16: TESTME--TESTME-FR03319FR-4896-30 Logements Siguy [3319_4896] | H16: DRAFT | I16: EGIS BATIMENTS ILE DE FRANCE | J16: =_xlfn.XLOOKUP(I16,LE!A:A,LE!F:F,,1) -> 0 | K16: SL-Buildings-CC-12-IDMI-01-Ile de France-BU-FR03305FR_EGIS BAT IDF | L16: SL-Buildings-CC-12-IDMI-01-Ile de France-BU-FR03305FR_EGIS BAT IDF | M16: EGIS BATIMENTS ILE DE FRANCE Billable E&SC Small Project | N16: =_xlfn.XLOOKUP(M16,'source template'!A:A,'source template'!I:I,,1) -> 0 | V16: EUR | X16: Corporate | Y16: T | Z16: FALSE | AA16: FALSE | AB16: TRUE | AC16: TRUE | AD16: E | AE16: P02 | AG16: FINANCIAL | BN16: 46203 | BO16: 41275 | BP16: 319-000008 | BQ16: STD | BR16: Standard | CG16: 45688 | CH16: P02 | CI16: 41275 | CJ16: PJF_TASKS | CK16: FINANCIAL
B17: OK | D17: CREATE | E17: BIL-1007983 | F17: TESTME-FR03319FR-4896-30 Logements Siguy [3319_4896] | G17: TESTME--TESTME-FR03319FR-4896-30 Logements Siguy [3319_4896] | H17: DRAFT | I17: EGIS BATIMENTS ILE DE FRANCE | J17: =_xlfn.XLOOKUP(I17,LE!A:A,LE!F:F,,1) -> 0 | K17: SL-Buildings-CC-12-IDMI-01-Ile de France-BU-FR03305FR_EGIS BAT IDF | L17: SL-Buildings-CC-12-IDMI-01-Ile de France-BU-FR03305FR_EGIS BAT IDF | M17: EGIS BATIMENTS ILE DE FRANCE Billable E&SC Small Project | N17: =_xlfn.XLOOKUP(M17,'source template'!A:A,'source template'!I:I,,1) -> 0 | V17: EUR | X17: Corporate | Y17: T | Z17: FALSE | AA17: FALSE | AB17: TRUE | AC17: TRUE | AD17: T | AE17: P03 | AG17: FINANCIAL | BN17: 46203 | BO17: 41275 | BP17: 319-000008 | BQ17: STD | BR17: Standard | CG17: 46203 | CH17: P03 | CI17: 41275 | CJ17: PJF_TASKS | CK17: FINANCIAL
B18: OK | D18: CREATE | E18: BIL-1007983 | F18: TESTME-FR03319FR-4896-30 Logements Siguy [3319_4896] | G18: TESTME--TESTME-FR03319FR-4896-30 Logements Siguy [3319_4896] | H18: DRAFT | I18: EGIS BATIMENTS ILE DE FRANCE | J18: =_xlfn.XLOOKUP(I18,LE!A:A,LE!F:F,,1) -> 0 | K18: SL-Buildings-CC-12-IDMI-01-Ile de France-BU-FR03305FR_EGIS BAT IDF | L18: SL-Buildings-CC-12-IDMI-01-Ile de France-BU-FR03305FR_EGIS BAT IDF | M18: EGIS BATIMENTS ILE DE FRANCE Billable E&SC Small Project | N18: =_xlfn.XLOOKUP(M18,'source template'!A:A,'source template'!I:I,,1) -> 0 | V18: EUR | X18: Corporate | Y18: T | Z18: FALSE | AA18: FALSE | AB18: TRUE | AC18: TRUE | AD18: Facturation Milestone Oracle 2025 | AE18: P97 | AG18: FINANCIAL | BN18: 46203 | BO18: 41275 | BP18: 319-000008 | BQ18: STD | BR18: Standard | CG18: 46022 | CH18: P97 | CI18: 41275 | CJ18: PJF_TASKS | CK18: FINANCIAL
B19: OK | D19: CREATE | E19: BIL-1007983 | F19: TESTME-FR03319FR-4896-30 Logements Siguy [3319_4896] | G19: TESTME--TESTME-FR03319FR-4896-30 Logements Siguy [3319_4896] | H19: DRAFT | I19: EGIS BATIMENTS ILE DE FRANCE | J19: =_xlfn.XLOOKUP(I19,LE!A:A,LE!F:F,,1) -> 0 | K19: SL-Buildings-CC-12-IDMI-01-Ile de France-BU-FR03305FR_EGIS BAT IDF | L19: SL-Buildings-CC-12-IDMI-01-Ile de France-BU-FR03305FR_EGIS BAT IDF | M19: EGIS BATIMENTS ILE DE FRANCE Billable E&SC Small Project | N19: =_xlfn.XLOOKUP(M19,'source template'!A:A,'source template'!I:I,,1) -> 0 | V19: EUR | X19: Corporate | Y19: T | Z19: FALSE | AA19: FALSE | AB19: TRUE | AC19: TRUE | AV19: Project Classification | AW19: Client Project | BN19: 46203 | BO19: 41275 | BP19: 319-000008 | BQ19: STD | BR19: Standard
B20: OK | D20: CREATE | E20: BIL-1007983 | F20: TESTME-FR03319FR-4896-30 Logements Siguy [3319_4896] | G20: TESTME--TESTME-FR03319FR-4896-30 Logements Siguy [3319_4896] | H20: DRAFT | I20: EGIS BATIMENTS ILE DE FRANCE | J20: =_xlfn.XLOOKUP(I20,LE!A:A,LE!F:F,,1) -> 0 | K20: SL-Buildings-CC-12-IDMI-01-Ile de France-BU-FR03305FR_EGIS BAT IDF | L20: SL-Buildings-CC-12-IDMI-01-Ile de France-BU-FR03305FR_EGIS BAT IDF | M20: EGIS BATIMENTS ILE DE FRANCE Billable E&SC Small Project | N20: =_xlfn.XLOOKUP(M20,'source template'!A:A,'source template'!I:I,,1) -> 0 | V20: EUR | X20: Corporate | Y20: T | Z20: FALSE | AA20: FALSE | AB20: TRUE | AC20: TRUE | AS20: Etienne.FERRER@egis-group.com | AT20: Project Manager | AU20: 43864 | BN20: 46203 | BO20: 41275 | BP20: 319-000008 | BQ20: STD | BR20: Standard
B21: OK | D21: CREATE | E21: BIL-1007983 | F21: TESTME-FR03319FR-4896-30 Logements Siguy [3319_4896] | G21: TESTME--TESTME-FR03319FR-4896-30 Logements Siguy [3319_4896] | H21: DRAFT | I21: EGIS BATIMENTS ILE DE FRANCE | J21: =_xlfn.XLOOKUP(I21,LE!A:A,LE!F:F,,1) -> 0 | K21: SL-Buildings-CC-12-IDMI-01-Ile de France-BU-FR03305FR_EGIS BAT IDF | L21: SL-Buildings-CC-12-IDMI-01-Ile de France-BU-FR03305FR_EGIS BAT IDF | M21: EGIS BATIMENTS ILE DE FRANCE Billable E&SC Small Project | N21: =_xlfn.XLOOKUP(M21,'source template'!A:A,'source template'!I:I,,1) -> 0 | V21: EUR | X21: Corporate | Y21: T | Z21: FALSE | AA21: FALSE | AB21: TRUE | AC21: TRUE | AS21: Rokhaya.NDIAYE@egis-group.com | AT21: Financial Controller | AU21: 41883 | BN21: 46203 | BO21: 41275 | BP21: 319-000008 | BQ21: STD | BR21: Standard
B22: OK | D22: CREATE | E22: BIL-1007983 | F22: TESTME-FR03319FR-4896-30 Logements Siguy [3319_4896] | G22: TESTME--TESTME-FR03319FR-4896-30 Logements Siguy [3319_4896] | H22: DRAFT | I22: EGIS BATIMENTS ILE DE FRANCE | J22: =_xlfn.XLOOKUP(I22,LE!A:A,LE!F:F,,1) -> 0 | K22: SL-Buildings-CC-12-IDMI-01-Ile de France-BU-FR03305FR_EGIS BAT IDF | L22: SL-Buildings-CC-12-IDMI-01-Ile de France-BU-FR03305FR_EGIS BAT IDF | M22: EGIS BATIMENTS ILE DE FRANCE Billable E&SC Small Project | N22: =_xlfn.XLOOKUP(M22,'source template'!A:A,'source template'!I:I,,1) -> 0 | V22: EUR | X22: Corporate | Y22: T | Z22: FALSE | AA22: FALSE | AB22: TRUE | AC22: TRUE | AS22: Sebastien.PLICHON@egis-group.com | AT22: RBLD | AU22: 42736 | BN22: 46203 | BO22: 41275 | BP22: 319-000008 | BQ22: STD | BR22: Standard
